Workbook

Sheet Từ vựng HSK2
A1: LUYỆN TẬP TỪ VỰNG HSK 2 (HSK 3.0 — 772 từ)
A2: Nhập chữ Hán giản thể hoặc Pinyin (có/không dấu thanh) vào cột B — chỉ cần sửa các ô màu vàng.
A3: Tổng số câu | B3: Số câu đã làm đúng ✅ | C3: Số câu sai ❌ | D3: Tỷ lệ hoàn thành (%)
A4: =COUNTIF($A$8:$A$1007,"?*") -> 772 | B4: =COUNTIF($C$8:$C$1007,"✅") -> 0 | C4: =COUNTIF($C$8:$C$1007,"❌") -> 0 | D4: =IF(A4=0,0,B4/A4) -> 0
A5: Tiến độ | B5: =REPT("█",ROUND(D4*20,0))&REPT("░",20-ROUND(D4*20,0)) -> ░░░░░░░░░░░░░░░░░░░░ | C5: =IF(B4+C4=0,"Độ chính xác: –","Độ chính xác: "&TEXT(B4/(B4+C4),"0%")) -> Độ chính xác: – | D5: Không
D6: ▲ Hiện gợi ý (Có/Không)
A7: Ý nghĩa | B7: Ô người học nhập | C7: Kết quả | D7: Gợi ý | F7: norm có dấu | G7: norm không dấu
A8: =IF(Data_HSK2!E2="","",Data_HSK2!E2) -> à, nhé, nhỉ (trợ từ ngữ khí) | C8: =IF(OR(A8="",TRIM(B8)=""),"",IF(OR(ISNUMBER(FIND("|"&F8&"|",Data_HSK2!G2)),AND(F8=G8,ISNUMBER(FIND("|"&G8&"|",Data_HSK2!H2)))),"✅","❌")) | D8: =IF(OR(A8="",$D$5<>"Có"),"",Data_HSK2!B2&" ("&Data_HSK2!C2&")") | F8: =IF(TRIM(B8)="","",SUBSTITUTE(SUBSTITUTE(SUBSTITUTE(SUBSTITUTE(SUBSTITUTE(SUBSTITUTE(SUBSTITUTE(SUBSTITUTE(SUBSTITUTE(SUBSTITUTE(SUBSTITUTE(SUBSTITUTE(SUBSTITUTE(SUBSTITUTE(SUBSTITUTE(SUBSTITUTE(LOWER(TRIM(B8))," ",""),"'",""),"’",""),"·",""),"/",""),"-",""),"(",""),")",""),"（",""),"）",""),"ü","v"),";","|"),"；","|"),",","|"),"，","|"),"、","|")) | G8: =SUBSTITUTE(SUBSTITUTE(SUBSTITUTE(SUBSTITUTE(SUBSTITUTE(SUBSTITUTE(SUBSTITUTE(SUBSTITUTE(SUBSTITUTE(SUBSTITUTE(SUBSTITUTE(SUBSTITUTE(SUBSTITUTE(SUBSTITUTE(SUBSTITUTE(SUBSTITUTE(SUBSTITUTE(SUBSTITUTE(SUBSTITUTE(SUBSTITUTE(SUBSTITUTE(SUBSTITUTE(SUBSTITUTE(SUBSTITUTE(F8,"ā","a"),"á","a"),"ǎ","a"),"à","a"),"ē","e"),"é","e"),"ě","e"),"è","e"),"ī","i"),"í","i"),"ǐ","i"),"ì","i"),"ō","o"),"ó","o"),"ǒ","o"),"ò","o"),"ū","u"),"ú","u"),"ǔ","u"),"ù","u"),"ǖ","v"),"ǘ","v"),"ǚ","v"),"ǜ","v")
A9: =IF(Data_HSK2!E3="","",Data_HSK2!E3) -> tình yêu (tình cảm lứa đôi) | C9: =IF(OR(A9="",TRIM(B9)=""),"",IF(OR(ISNUMBER(FIND("|"&F9&"|",Data_HSK2!G3)),AND(F9=G9,ISNUMBER(FIND("|"&G9&"|",Data_HSK2!H3)))),"✅","❌")) | D9: =IF(OR(A9="",$D$5<>"Có"),"",Data_HSK2!B3&" ("&Data_HSK2!C3&")") | F9: =IF(TRIM(B9)="","",SUBSTITUTE(SUBSTITUTE(SUBSTITUTE(SUBSTITUTE(SUBSTITUTE(SUBSTITUTE(SUBSTITUTE(SUBSTITUTE(SUBSTITUTE(SUBSTITUTE(SUBSTITUTE(SUBSTITUTE(SUBSTITUTE(SUBSTITUTE(SUBSTITUTE(SUBSTITUTE(LOWER(TRIM(B9))," ",""),"'",""),"’",""),"·",""),"/",""),"-",""),"(",""),")",""),"（",""),"）",""),"ü","v"),";","|"),"；","|"),",","|"),"，","|"),"、","|")) | G9: =SUBSTITUTE(SUBSTITUTE(SUBSTITUTE(SUBSTITUTE(SUBSTITUTE(SUBSTITUTE(SUBSTITUTE(SUBSTITUTE(SUBSTITUTE(SUBSTITUTE(SUBSTITUTE(SUBSTITUTE(SUBSTITUTE(SUBSTITUTE(SUBSTITUTE(SUBSTITUTE(SUBSTITUTE(SUBSTITUTE(SUBSTITUTE(SUBSTITUTE(SUBSTITUTE(SUBSTITUTE(SUBSTITUTE(SUBSTITUTE(F9,"ā","a"),"á","a"),"ǎ","a"),"à","a"),"ē","e"),"é","e"),"ě","e"),"è","e"),"ī","i"),"í","i"),"ǐ","i"),"ì","i"),"ō","o"),"ó","o"),"ǒ","o"),"ò","o"),"ū","u"),"ú","u"),"ǔ","u"),"ù","u"),"ǖ","v"),"ǘ","v"),"ǚ","v"),"ǜ","v")
A10: =IF(Data_HSK2!E4="","",Data_HSK2!E4) -> vợ hoặc chồng, người yêu | C10: =IF(OR(A10="",TRIM(B10)=""),"",IF(OR(ISNUMBER(FIND("|"&F10&"|",Data_HSK2!G4)),AND(F10=G10,ISNUMBER(FIND("|"&G10&"|",Data_HSK2!H4)))),"✅","❌")) | D10: =IF(OR(A10="",$D$5<>"Có"),"",Data_HSK2!B4&" ("&Data_HSK2!C4&")") | F10: =IF(TRIM(B10)="","",SUBSTITUTE(SUBSTITUTE(SUBSTITUTE(SUBSTITUTE(SUBSTITUTE(SUBSTITUTE(SUBSTITUTE(SUBSTITUTE(SUBSTITUTE(SUBSTITUTE(SUBSTITUTE(SUBSTITUTE(SUBSTITUTE(SUBSTITUTE(SUBSTITUTE(SUBSTITUTE(LOWER(TRIM(B10))," ",""),"'",""),"’",""),"·",""),"/",""),"-",""),"(",""),")",""),"（",""),"）",""),"ü","v"),";","|"),"；","|"),",","|"),"，","|"),"、","|")) | G10: =SUBSTITUTE(SUBSTITUTE(SUBSTITUTE(SUBSTITUTE(SUBSTITUTE(SUBSTITUTE(SUBSTITUTE(SUBSTITUTE(SUBSTITUTE(SUBSTITUTE(SUBSTITUTE(SUBSTITUTE(SUBSTITUTE(SUBSTITUTE(SUBSTITUTE(SUBSTITUTE(SUBSTITUTE(SUBSTITUTE(SUBSTITUTE(SUBSTITUTE(SUBSTITUTE(SUBSTITUTE(SUBSTITUTE(SUBSTITUTE(F10,"ā","a"),"á","a"),"ǎ","a"),"à","a"),"ē","e"),"é","e"),"ě","e"),"è","e"),"ī","i"),"í","i"),"ǐ","i"),"ì","i"),"ō","o"),"ó","o"),"ǒ","o"),"ò","o"),"ū","u"),"ú","u"),"ǔ","u"),"ù","u"),"ǖ","v"),"ǘ","v"),"ǚ","v"),"ǜ","v")
A11: =IF(Data_HSK2!E5="","",Data_HSK2!E5) -> yên tĩnh | C11: =IF(OR(A11="",TRIM(B11)=""),"",IF(OR(ISNUMBER(FIND("|"&F11&"|",Data_HSK2!G5)),AND(F11=G11,ISNUMBER(FIND("|"&G11&"|",Data_HSK2!H5)))),"✅","❌")) | D11: =IF(OR(A11="",$D$5<>"Có"),"",Data_HSK2!B5&" ("&Data_HSK2!C5&")") | F11: =IF(TRIM(B11)="","",SUBSTITUTE(SUBSTITUTE(SUBSTITUTE(SUBSTITUTE(SUBSTITUTE(SUBSTITUTE(SUBSTITUTE(SUBSTITUTE(SUBSTITUTE(SUBSTITUTE(SUBSTITUTE(SUBSTITUTE(SUBSTITUTE(SUBSTITUTE(SUBSTITUTE(SUBSTITUTE(LOWER(TRIM(B11))," ",""),"'",""),"’",""),"·",""),"/",""),"-",""),"(",""),")",""),"（",""),"）",""),"ü","v"),";","|"),"；","|"),",","|"),"，","|"),"、","|")) | G11: =SUBSTITUTE(SUBSTITUTE(SUBSTITUTE(SUBSTITUTE(SUBSTITUTE(SUBSTITUTE(SUBSTITUTE(SUBSTITUTE(SUBSTITUTE(SUBSTITUTE(SUBSTITUTE(SUBSTITUTE(SUBSTITUTE(SUBSTITUTE(SUBSTITUTE(SUBSTITUTE(SUBSTITUTE(SUBSTITUTE(SUBSTITUTE(SUBSTITUTE(SUBSTITUTE(SUBSTITUTE(SUBSTITUTE(SUBSTITUTE(F11,"ā","a"),"á","a"),"ǎ","a"),"à","a"),"ē","e"),"é","e"),"ě","e"),"è","e"),"ī","i"),"í","i"),"ǐ","i"),"ì","i"),"ō","o"),"ó","o"),"ǒ","o"),"ò","o"),"ū","u"),"ú","u"),"ǔ","u"),"ù","u"),"ǖ","v"),"ǘ","v"),"ǚ","v"),"ǜ","v")
A12: =IF(Data_HSK2!E6="","",Data_HSK2!E6) -> an toàn | C12: =IF(OR(A12="",TRIM(B12)=""),"",IF(OR(ISNUMBER(FIND("|"&F12&"|",Data_HSK2!G6)),AND(F12=G12,ISNUMBER(FIND("|"&G12&"|",Data_HSK2!H6)))),"✅","❌")) | D12: =IF(OR(A12="",$D$5<>"Có"),"",Data_HSK2!B6&" ("&Data_HSK2!C6&")") | F12: =IF(TRIM(B12)="","",SUBSTITUTE(SUBSTITUTE(SUBSTITUTE(SUBSTITUTE(SUBSTITUTE(SUBSTITUTE(SUBSTITUTE(SUBSTITUTE(SUBSTITUTE(SUBSTITUTE(SUBSTITUTE(SUBSTITUTE(SUBSTITUTE(SUBSTITUTE(SUBSTITUTE(SUBSTITUTE(LOWER(TRIM(B12))," ",""),"'",""),"’",""),"·",""),"/",""),"-",""),"(",""),")",""),"（",""),"）",""),"ü","v"),";","|"),"；","|"),",","|"),"，","|"),"、","|")) | G12: =SUBSTITUTE(SUBSTITUTE(SUBSTITUTE(SUBSTITUTE(SUBSTITUTE(SUBSTITUTE(SUBSTITUTE(SUBSTITUTE(SUBSTITUTE(SUBSTITUTE(SUBSTITUTE(SUBSTITUTE(SUBSTITUTE(SUBSTITUTE(SUBSTITUTE(SUBSTITUTE(SUBSTITUTE(SUBSTITUTE(SUBSTITUTE(SUBSTITUTE(SUBSTITUTE(SUBSTITUTE(SUBSTITUTE(SUBSTITUTE(F12,"ā","a"),"á","a"),"ǎ","a"),"à","a"),"ē","e"),"é","e"),"ě","e"),"è","e"),"ī","i"),"í","i"),"ǐ","i"),"ì","i"),"ō","o"),"ó","o"),"ǒ","o"),"ò","o"),"ū","u"),"ú","u"),"ǔ","u"),"ù","u"),"ǖ","v"),"ǘ","v"),"ǚ","v"),"ǜ","v")
A13: =IF(Data_HSK2!E7="","",Data_HSK2!E7) -> màu trắng | C13: =IF(OR(A13="",TRIM(B13)=""),"",IF(OR(ISNUMBER(FIND("|"&F13&"|",Data_HSK2!G7)),AND(F13=G13,ISNUMBER(FIND("|"&G13&"|",Data_HSK2!H7)))),"✅","❌")) | D13: =IF(OR(A13="",$D$5<>"Có"),"",Data_HSK2!B7&" ("&Data_HSK2!C7&")") | F13: =IF(TRIM(B13)="","",SUBSTITUTE(SUBSTITUTE(SUBSTITUTE(SUBSTITUTE(SUBSTITUTE(SUBSTITUTE(SUBSTITUTE(SUBSTITUTE(SUBSTITUTE(SUBSTITUTE(SUBSTITUTE(SUBSTITUTE(SUBSTITUTE(SUBSTITUTE(SUBSTITUTE(SUBSTITUTE(LOWER(TRIM(B13))," ",""),"'",""),"’",""),"·",""),"/",""),"-",""),"(",""),")",""),"（",""),"）",""),"ü","v"),";","|"),"；","|"),",","|"),"，","|"),"、","|")) | G13: =SUBSTITUTE(SUBSTITUTE(SUBSTITUTE(SUBSTITUTE(SUBSTITUTE(SUBSTITUTE(SUBSTITUTE(SUBSTITUTE(SUBSTITUTE(SUBSTITUTE(SUBSTITUTE(SUBSTITUTE(SUBSTITUTE(SUBSTITUTE(SUBSTITUTE(SUBSTITUTE(SUBSTITUTE(SUBSTITUTE(SUBSTITUTE(SUBSTITUTE(SUBSTITUTE(SUBSTITUTE(SUBSTITUTE(SUBSTITUTE(F13,"ā","a"),"á","a"),"ǎ","a"),"à","a"),"ē","e"),"é","e"),"ě","e"),"è","e"),"ī","i"),"í","i"),"ǐ","i"),"ì","i"),"ō","o"),"ó","o"),"ǒ","o"),"ò","o"),"ū","u"),"ú","u"),"ǔ","u"),"ù","u"),"ǖ","v"),"ǘ","v"),"ǚ","v"),"ǜ","v")
A14: =IF(Data_HSK2!E8="","",Data_HSK2!E8) -> lớp trưởng | C14: =IF(OR(A14="",TRIM(B14)=""),"",IF(OR(ISNUMBER(FIND("|"&F14&"|",Data_HSK2!G8)),AND(F14=G14,ISNUMBER(FIND("|"&G14&"|",Data_HSK2!H8)))),"✅","❌")) | D14: =IF(OR(A14="",$D$5<>"Có"),"",Data_HSK2!B8&" ("&Data_HSK2!C8&")") | F14: =IF(TRIM(B14)="","",SUBSTITUTE(SUBSTITUTE(SUBSTITUTE(SUBSTITUTE(SUBSTITUTE(SUBSTITUTE(SUBSTITUTE(SUBSTITUTE(SUBSTITUTE(SUBSTITUTE(SUBSTITUTE(SUBSTITUTE(SUBSTITUTE(SUBSTITUTE(SUBSTITUTE(SUBSTITUTE(LOWER(TRIM(B14))," ",""),"'",""),"’",""),"·",""),"/",""),"-",""),"(",""),")",""),"（",""),"）",""),"ü","v"),";","|"),"；","|"),",","|"),"，","|"),"、","|")) | G14: =SUBSTITUTE(SUBSTITUTE(SUBSTITUTE(SUBSTITUTE(SUBSTITUTE(SUBSTITUTE(SUBSTITUTE(SUBSTITUTE(SUBSTITUTE(SUBSTITUTE(SUBSTITUTE(SUBSTITUTE(SUBSTITUTE(SUBSTITUTE(SUBSTITUTE(SUBSTITUTE(SUBSTITUTE(SUBSTITUTE(SUBSTITUTE(SUBSTITUTE(SUBSTITUTE(SUBSTITUTE(SUBSTITUTE(SUBSTITUTE(F14,"ā","a"),"á","a"),"ǎ","a"),"à","a"),"ē","e"),"é","e"),"ě","e"),"è","e"),"ī","i"),"í","i"),"ǐ","i"),"ì","i"),"ō","o"),"ó","o"),"ǒ","o"),"ò","o"),"ū","u"),"ú","u"),"ǔ","u"),"ù","u"),"ǖ","v"),"ǘ","v"),"ǚ","v"),"ǜ","v")
A15: =IF(Data_HSK2!E9="","",Data_HSK2!E9) -> làm, xử lý (công việc) | C15: =IF(OR(A15="",TRIM(B15)=""),"",IF(OR(ISNUMBER(FIND("|"&F15&"|",Data_HSK2!G9)),AND(F15=G15,ISNUMBER(FIND("|"&G15&"|",Data_HSK2!H9)))),"✅","❌")) | D15: =IF(OR(A15="",$D$5<>"Có"),"",Data_HSK2!B9&" ("&Data_HSK2!C9&")") | F15: =IF(TRIM(B15)="","",SUBSTITUTE(SUBSTITUTE(SUBSTITUTE(SUBSTITUTE(SUBSTITUTE(SUBSTITUTE(SUBSTITUTE(SUBSTITUTE(SUBSTITUTE(SUBSTITUTE(SUBSTITUTE(SUBSTITUTE(SUBSTITUTE(SUBSTITUTE(SUBSTITUTE(SUBSTITUTE(LOWER(TRIM(B15))," ",""),"'",""),"’",""),"·",""),"/",""),"-",""),"(",""),")",""),"（",""),"）",""),"ü","v"),";","|"),"；","|"),",","|"),"，","|"),"、","|")) | G15: =SUBSTITUTE(SUBSTITUTE(SUBSTITUTE(SUBSTITUTE(SUBSTITUTE(SUBSTITUTE(SUBSTITUTE(SUBSTITUTE(SUBSTITUTE(SUBSTITUTE(SUBSTITUTE(SUBSTITUTE(SUBSTITUTE(SUBSTITUTE(SUBSTITUTE(SUBSTITUTE(SUBSTITUTE(SUBSTITUTE(SUBSTITUTE(SUBSTITUTE(SUBSTITUTE(SUBSTITUTE(SUBSTITUTE(SUBSTITUTE(F15,"ā","a"),"á","a"),"ǎ","a"),"à","a"),"ē","e"),"é","e"),"ě","e"),"è","e"),"ī","i"),"í","i"),"ǐ","i"),"ì","i"),"ō","o"),"ó","o"),"ǒ","o"),"ò","o"),"ū","u"),"ú","u"),"ǔ","u"),"ù","u"),"ǖ","v"),"ǘ","v"),"ǚ","v"),"ǜ","v")
A16: =IF(Data_HSK2!E10="","",Data_HSK2!E10) -> biện pháp, cách | C16: =IF(OR(A16="",TRIM(B16)=""),"",IF(OR(ISNUMBER(FIND("|"&F16&"|",Data_HSK2!G10)),AND(F16=G16,ISNUMBER(FIND("|"&G16&"|",Data_HSK2!H10)))),"✅","❌")) | D16: =IF(OR(A16="",$D$5<>"Có"),"",Data_HSK2!B10&" ("&Data_HSK2!C10&")") | F16: =IF(TRIM(B16)="","",SUBSTITUTE(SUBSTITUTE(SUBSTITUTE(SUBSTITUTE(SUBSTITUTE(SUBSTITUTE(SUBSTITUTE(SUBSTITUTE(SUBSTITUTE(SUBSTITUTE(SUBSTITUTE(SUBSTITUTE(SUBSTITUTE(SUBSTITUTE(SUBSTITUTE(SUBSTITUTE(LOWER(TRIM(B16))," ",""),"'",""),"’",""),"·",""),"/",""),"-",""),"(",""),")",""),"（",""),"）",""),"ü","v"),";","|"),"；","|"),",","|"),"，","|"),"、","|")) | G16: =SUBSTITUTE(SUBSTITUTE(SUBSTITUTE(SUBSTITUTE(SUBSTITUTE(SUBSTITUTE(SUBSTITUTE(SUBSTITUTE(SUBSTITUTE(SUBSTITUTE(SUBSTITUTE(SUBSTITUTE(SUBSTITUTE(SUBSTITUTE(SUBSTITUTE(SUBSTITUTE(SUBSTITUTE(SUBSTITUTE(SUBSTITUTE(SUBSTITUTE(SUBSTITUTE(SUBSTITUTE(SUBSTITUTE(SUBSTITUTE(F16,"ā","a"),"á","a"),"ǎ","a"),"à","a"),"ē","e"),"é","e"),"ě","e"),"è","e"),"ī","i"),"í","i"),"ǐ","i"),"ì","i"),"ō","o"),"ó","o"),"ǒ","o"),"ò","o"),"ū","u"),"ú","u"),"ǔ","u"),"ù","u"),"ǖ","v"),"ǘ","v"),"ǚ","v"),"ǜ","v")
A17: =IF(Data_HSK2!E11="","",Data_HSK2!E11) -> văn phòng | C17: =IF(OR(A17="",TRIM(B17)=""),"",IF(OR(ISNUMBER(FIND("|"&F17&"|",Data_HSK2!G11)),AND(F17=G17,ISNUMBER(FIND("|"&G17&"|",Data_HSK2!H11)))),"✅","❌")) | D17: =IF(OR(A17="",$D$5<>"Có"),"",Data_HSK2!B11&" ("&Data_HSK2!C11&")") | F17: =IF(TRIM(B17)="","",SUBSTITUTE(SUBSTITUTE(SUBSTITUTE(SUBSTITUTE(SUBSTITUTE(SUBSTITUTE(SUBSTITUTE(SUBSTITUTE(SUBSTITUTE(SUBSTITUTE(SUBSTITUTE(SUBSTITUTE(SUBSTITUTE(SUBSTITUTE(SUBSTITUTE(SUBSTITUTE(LOWER(TRIM(B17))," ",""),"'",""),"’",""),"·",""),"/",""),"-",""),"(",""),")",""),"（",""),"）",""),"ü","v"),";","|"),"；","|"),",","|"),"，","|"),"、","|")) | G17: =SUBSTITUTE(SUBSTITUTE(SUBSTITUTE(SUBSTITUTE(SUBSTITUTE(SUBSTITUTE(SUBSTITUTE(SUBSTITUTE(SUBSTITUTE(SUBSTITUTE(SUBSTITUTE(SUBSTITUTE(SUBSTITUTE(SUBSTITUTE(SUBSTITUTE(SUBSTITUTE(SUBSTITUTE(SUBSTITUTE(SUBSTITUTE(SUBSTITUTE(SUBSTITUTE(SUBSTITUTE(SUBSTITUTE(SUBSTITUTE(F17,"ā","a"),"á","a"),"ǎ","a"),"à","a"),"ē","e"),"é","e"),"ě","e"),"è","e"),"ī","i"),"í","i"),"ǐ","i"),"ì","i"),"ō","o"),"ó","o"),"ǒ","o"),"ò","o"),"ū","u"),"ú","u"),"ǔ","u"),"ù","u"),"ǖ","v"),"ǘ","v"),"ǚ","v"),"ǜ","v")
A18: =IF(Data_HSK2!E12="","",Data_HSK2!E12) -> nửa đêm | C18: =IF(OR(A18="",TRIM(B18)=""),"",IF(OR(ISNUMBER(FIND("|"&F18&"|",Data_HSK2!G12)),AND(F18=G18,ISNUMBER(FIND("|"&G18&"|",Data_HSK2!H12)))),"✅","❌")) | D18: =IF(OR(A18="",$D$5<>"Có"),"",Data_HSK2!B12&" ("&Data_HSK2!C12&")") | F18: =IF(TRIM(B18)="","",SUBSTITUTE(SUBSTITUTE(SUBSTITUTE(SUBSTITUTE(SUBSTITUTE(SUBSTITUTE(SUBSTITUTE(SUBSTITUTE(SUBSTITUTE(SUBSTITUTE(SUBSTITUTE(SUBSTITUTE(SUBSTITUTE(SUBSTITUTE(SUBSTITUTE(SUBSTITUTE(LOWER(TRIM(B18))," ",""),"'",""),"’",""),"·",""),"/",""),"-",""),"(",""),")",""),"（",""),"）",""),"ü","v"),";","|"),"；","|"),",","|"),"，","|"),"、","|")) | G18: =SUBSTITUTE(SUBSTITUTE(SUBSTITUTE(SUBSTITUTE(SUBSTITUTE(SUBSTITUTE(SUBSTITUTE(SUBSTITUTE(SUBSTITUTE(SUBSTITUTE(SUBSTITUTE(SUBSTITUTE(SUBSTITUTE(SUBSTITUTE(SUBSTITUTE(SUBSTITUTE(SUBSTITUTE(SUBSTITUTE(SUBSTITUTE(SUBSTITUTE(SUBSTITUTE(SUBSTITUTE(SUBSTITUTE(SUBSTITUTE(F18,"ā","a"),"á","a"),"ǎ","a"),"à","a"),"ē","e"),"é","e"),"ě","e"),"è","e"),"ī","i"),"í","i"),"ǐ","i"),"ì","i"),"ō","o"),"ó","o"),"ǒ","o"),"ò","o"),"ū","u"),"ú","u"),"ǔ","u"),"ù","u"),"ǖ","v"),"ǘ","v"),"ǚ","v"),"ǜ","v")
A19: =IF(Data_HSK2!E13="","",Data_HSK2!E13) -> giúp đỡ (帮助) | C19: =IF(OR(A19="",TRIM(B19)=""),"",IF(OR(ISNUMBER(FIND("|"&F19&"|",Data_HSK2!G13)),AND(F19=G19,ISNUMBER(FIND("|"&G19&"|",Data_HSK2!H13)))),"✅","❌")) | D19: =IF(OR(A19="",$D$5<>"Có"),"",Data_HSK2!B13&" ("&Data_HSK2!C13&")") | F19: =IF(TRIM(B19)="","",SUBSTITUTE(SUBSTITUTE(SUBSTITUTE(SUBSTITUTE(SUBSTITUTE(SUBSTITUTE(SUBSTITUTE(SUBSTITUTE(SUBSTITUTE(SUBSTITUTE(SUBSTITUTE(SUBSTITUTE(SUBSTITUTE(SUBSTITUTE(SUBSTITUTE(SUBSTITUTE(LOWER(TRIM(B19))," ",""),"'",""),"’",""),"·",""),"/",""),"-",""),"(",""),")",""),"（",""),"）",""),"ü","v"),";","|"),"；","|"),",","|"),"，","|"),"、","|")) | G19: =SUBSTITUTE(SUBSTITUTE(SUBSTITUTE(SUBSTITUTE(SUBSTITUTE(SUBSTITUTE(SUBSTITUTE(SUBSTITUTE(SUBSTITUTE(SUBSTITUTE(SUBSTITUTE(SUBSTITUTE(SUBSTITUTE(SUBSTITUTE(SUBSTITUTE(SUBSTITUTE(SUBSTITUTE(SUBSTITUTE(SUBSTITUTE(SUBSTITUTE(SUBSTITUTE(SUBSTITUTE(SUBSTITUTE(SUBSTITUTE(F19,"ā","a"),"á","a"),"ǎ","a"),"à","a"),"ē","e"),"é","e"),"ě","e"),"è","e"),"ī","i"),"í","i"),"ǐ","i"),"ì","i"),"ō","o"),"ó","o"),"ǒ","o"),"ò","o"),"ū","u"),"ú","u"),"ǔ","u"),"ù","u"),"ǖ","v"),"ǘ","v"),"ǚ","v"),"ǜ","v")
... A1007: =IF(Data_HSK2!E1001="","",Data_HSK2!E1001) | C1007: =IF(OR(A1007="",TRIM(B1007)=""),"",IF(OR(ISNUMBER(FIND("|"&F1007&"|",Data_HSK2!G1001)),AND(F1007=G1007,ISNUMBER(FIND("|"&G1007&"|",Data_HSK2!H1001)))),"✅","❌")) | D1007: =IF(OR(A1007="",$D$5<>"Có"),"",Data_HSK2!B1001&" ("&Data_HSK2!C1001&")") | F1007: =IF(TRIM(B1007)="","",SUBSTITUTE(SUBSTITUTE(SUBSTITUTE(SUBSTITUTE(SUBSTITUTE(SUBSTITUTE(SUBSTITUTE(SUBSTITUTE(SUBSTITUTE(SUBSTITUTE(SUBSTITUTE(SUBSTITUTE(SUBSTITUTE(SUBSTITUTE(SUBSTITUTE(SUBSTITUTE(LOWER(TRIM(B1007))," ",""),"'",""),"’",""),"·",""),"/",""),"-",""),"(",""),")",""),"（",""),"）",""),"ü","v"),";","|"),"；","|"),",","|"),"，","|"),"、","|")) | G1007: =SUBSTITUTE(SUBSTITUTE(SUBSTITUTE(SUBSTITUTE(SUBSTITUTE(SUBSTITUTE(SUBSTITUTE(SUBSTITUTE(SUBSTITUTE(SUBSTITUTE(SUBSTITUTE(SUBSTITUTE(SUBSTITUTE(SUBSTITUTE(SUBSTITUTE(SUBSTITUTE(SUBSTITUTE(SUBSTITUTE(SUBSTITUTE(SUBSTITUTE(SUBSTITUTE(SUBSTITUTE(SUBSTITUTE(SUBSTITUTE(F1007,"ā","a"),"á","a"),"ǎ","a"),"à","a"),"ē","e"),"é","e"),"ě","e"),"è","e"),"ī","i"),"í","i"),"ǐ","i"),"ì","i"),"ō","o"),"ó","o"),"ǒ","o"),"ò","o"),"ū","u"),"ú","u"),"ǔ","u"),"ù","u"),"ǖ","v"),"ǘ","v"),"ǚ","v"),"ǜ","v")

Sheet Từ vựng HSK3
A1: LUYỆN TẬP TỪ VỰNG HSK 3 (HSK 3.0 — 973 từ)
A2: Nhập chữ Hán giản thể hoặc Pinyin (có/không dấu thanh) vào cột B — chỉ cần sửa các ô màu vàng.
A3: Tổng số câu | B3: Số câu đã làm đúng ✅ | C3: Số câu sai ❌ | D3: Tỷ lệ hoàn thành (%)
A4: =COUNTIF($A$8:$A$1207,"?*") -> 973 | B4: =COUNTIF($C$8:$C$1207,"✅") -> 0 | C4: =COUNTIF($C$8:$C$1207,"❌") -> 0 | D4: =IF(A4=0,0,B4/A4) -> 0
A5: Tiến độ | B5: =REPT("█",ROUND(D4*20,0))&REPT("░",20-ROUND(D4*20,0)) -> ░░░░░░░░░░░░░░░░░░░░ | C5: =IF(B4+C4=0,"Độ chính xác: –","Độ chính xác: "&TEXT(B4/(B4+C4),"0%")) -> Độ chính xác: – | D5: Không
D6: ▲ Hiện gợi ý (Có/Không)
A7: Ý nghĩa | B7: Ô người học nhập | C7: Kết quả | D7: Gợi ý | F7: norm có dấu | G7: norm không dấu
A8: =IF(Data_HSK3!E2="","",Data_HSK3!E2) -> lòng yêu thương | C8: =IF(OR(A8="",TRIM(B8)=""),"",IF(OR(ISNUMBER(FIND("|"&F8&"|",Data_HSK3!G2)),AND(F8=G8,ISNUMBER(FIND("|"&G8&"|",Data_HSK3!H2)))),"✅","❌")) | D8: =IF(OR(A8="",$D$5<>"Có"),"",Data_HSK3!B2&" ("&Data_HSK3!C2&")") | F8: =IF(TRIM(B8)="","",SUBSTITUTE(SUBSTITUTE(SUBSTITUTE(SUBSTITUTE(SUBSTITUTE(SUBSTITUTE(SUBSTITUTE(SUBSTITUTE(SUBSTITUTE(SUBSTITUTE(SUBSTITUTE(SUBSTITUTE(SUBSTITUTE(SUBSTITUTE(SUBSTITUTE(SUBSTITUTE(LOWER(TRIM(B8))," ",""),"'",""),"’",""),"·",""),"/",""),"-",""),"(",""),")",""),"（",""),"）",""),"ü","v"),";","|"),"；","|"),",","|"),"，","|"),"、","|")) | G8: =SUBSTITUTE(SUBSTITUTE(SUBSTITUTE(SUBSTITUTE(SUBSTITUTE(SUBSTITUTE(SUBSTITUTE(SUBSTITUTE(SUBSTITUTE(SUBSTITUTE(SUBSTITUTE(SUBSTITUTE(SUBSTITUTE(SUBSTITUTE(SUBSTITUTE(SUBSTITUTE(SUBSTITUTE(SUBSTITUTE(SUBSTITUTE(SUBSTITUTE(SUBSTITUTE(SUBSTITUTE(SUBSTITUTE(SUBSTITUTE(F8,"ā","a"),"á","a"),"ǎ","a"),"à","a"),"ē","e"),"é","e"),"ě","e"),"è","e"),"ī","i"),"í","i"),"ǐ","i"),"ì","i"),"ō","o"),"ó","o"),"ǒ","o"),"ò","o"),"ū","u"),"ú","u"),"ǔ","u"),"ù","u"),"ǖ","v"),"ǘ","v"),"ǚ","v"),"ǜ","v")
A9: =IF(Data_HSK3!E3="","",Data_HSK3!E3) -> sắp xếp, bố trí | C9: =IF(OR(A9="",TRIM(B9)=""),"",IF(OR(ISNUMBER(FIND("|"&F9&"|",Data_HSK3!G3)),AND(F9=G9,ISNUMBER(FIND("|"&G9&"|",Data_HSK3!H3)))),"✅","❌")) | D9: =IF(OR(A9="",$D$5<>"Có"),"",Data_HSK3!B3&" ("&Data_HSK3!C3&")") | F9: =IF(TRIM(B9)="","",SUBSTITUTE(SUBSTITUTE(SUBSTITUTE(SUBSTITUTE(SUBSTITUTE(SUBSTITUTE(SUBSTITUTE(SUBSTITUTE(SUBSTITUTE(SUBSTITUTE(SUBSTITUTE(SUBSTITUTE(SUBSTITUTE(SUBSTITUTE(SUBSTITUTE(SUBSTITUTE(LOWER(TRIM(B9))," ",""),"'",""),"’",""),"·",""),"/",""),"-",""),"(",""),")",""),"（",""),"）",""),"ü","v"),";","|"),"；","|"),",","|"),"，","|"),"、","|")) | G9: =SUBSTITUTE(SUBSTITUTE(SUBSTITUTE(SUBSTITUTE(SUBSTITUTE(SUBSTITUTE(SUBSTITUTE(SUBSTITUTE(SUBSTITUTE(SUBSTITUTE(SUBSTITUTE(SUBSTITUTE(SUBSTITUTE(SUBSTITUTE(SUBSTITUTE(SUBSTITUTE(SUBSTITUTE(SUBSTITUTE(SUBSTITUTE(SUBSTITUTE(SUBSTITUTE(SUBSTITUTE(SUBSTITUTE(SUBSTITUTE(F9,"ā","a"),"á","a"),"ǎ","a"),"à","a"),"ē","e"),"é","e"),"ě","e"),"è","e"),"ī","i"),"í","i"),"ǐ","i"),"ì","i"),"ō","o"),"ó","o"),"ǒ","o"),"ò","o"),"ū","u"),"ú","u"),"ǔ","u"),"ù","u"),"ǖ","v"),"ǘ","v"),"ǚ","v"),"ǜ","v")
A10: =IF(Data_HSK3!E4="","",Data_HSK3!E4) -> lắp đặt, cài đặt | C10: =IF(OR(A10="",TRIM(B10)=""),"",IF(OR(ISNUMBER(FIND("|"&F10&"|",Data_HSK3!G4)),AND(F10=G10,ISNUMBER(FIND("|"&G10&"|",Data_HSK3!H4)))),"✅","❌")) | D10: =IF(OR(A10="",$D$5<>"Có"),"",Data_HSK3!B4&" ("&Data_HSK3!C4&")") | F10: =IF(TRIM(B10)="","",SUBSTITUTE(SUBSTITUTE(SUBSTITUTE(SUBSTITUTE(SUBSTITUTE(SUBSTITUTE(SUBSTITUTE(SUBSTITUTE(SUBSTITUTE(SUBSTITUTE(SUBSTITUTE(SUBSTITUTE(SUBSTITUTE(SUBSTITUTE(SUBSTITUTE(SUBSTITUTE(LOWER(TRIM(B10))," ",""),"'",""),"’",""),"·",""),"/",""),"-",""),"(",""),")",""),"（",""),"）",""),"ü","v"),";","|"),"；","|"),",","|"),"，","|"),"、","|")) | G10: =SUBSTITUTE(SUBSTITUTE(SUBSTITUTE(SUBSTITUTE(SUBSTITUTE(SUBSTITUTE(SUBSTITUTE(SUBSTITUTE(SUBSTITUTE(SUBSTITUTE(SUBSTITUTE(SUBSTITUTE(SUBSTITUTE(SUBSTITUTE(SUBSTITUTE(SUBSTITUTE(SUBSTITUTE(SUBSTITUTE(SUBSTITUTE(SUBSTITUTE(SUBSTITUTE(SUBSTITUTE(SUBSTITUTE(SUBSTITUTE(F10,"ā","a"),"á","a"),"ǎ","a"),"à","a"),"ē","e"),"é","e"),"ě","e"),"è","e"),"ī","i"),"í","i"),"ǐ","i"),"ì","i"),"ō","o"),"ó","o"),"ǒ","o"),"ò","o"),"ū","u"),"ú","u"),"ǔ","u"),"ù","u"),"ǖ","v"),"ǘ","v"),"ǚ","v"),"ǜ","v")
A11: =IF(Data_HSK3!E5="","",Data_HSK3!E5) -> ấn, bấm; theo (1 chữ) | C11: =IF(OR(A11="",TRIM(B11)=""),"",IF(OR(ISNUMBER(FIND("|"&F11&"|",Data_HSK3!G5)),AND(F11=G11,ISNUMBER(FIND("|"&G11&"|",Data_HSK3!H5)))),"✅","❌")) | D11: =IF(OR(A11="",$D$5<>"Có"),"",Data_HSK3!B5&" ("&Data_HSK3!C5&")") | F11: =IF(TRIM(B11)="","",SUBSTITUTE(SUBSTITUTE(SUBSTITUTE(SUBSTITUTE(SUBSTITUTE(SUBSTITUTE(SUBSTITUTE(SUBSTITUTE(SUBSTITUTE(SUBSTITUTE(SUBSTITUTE(SUBSTITUTE(SUBSTITUTE(SUBSTITUTE(SUBSTITUTE(SUBSTITUTE(LOWER(TRIM(B11))," ",""),"'",""),"’",""),"·",""),"/",""),"-",""),"(",""),")",""),"（",""),"）",""),"ü","v"),";","|"),"；","|"),",","|"),"，","|"),"、","|")) | G11: =SUBSTITUTE(SUBSTITUTE(SUBSTITUTE(SUBSTITUTE(SUBSTITUTE(SUBSTITUTE(SUBSTITUTE(SUBSTITUTE(SUBSTITUTE(SUBSTITUTE(SUBSTITUTE(SUBSTITUTE(SUBSTITUTE(SUBSTITUTE(SUBSTITUTE(SUBSTITUTE(SUBSTITUTE(SUBSTITUTE(SUBSTITUTE(SUBSTITUTE(SUBSTITUTE(SUBSTITUTE(SUBSTITUTE(SUBSTITUTE(F11,"ā","a"),"á","a"),"ǎ","a"),"à","a"),"ē","e"),"é","e"),"ě","e"),"è","e"),"ī","i"),"í","i"),"ǐ","i"),"ì","i"),"ō","o"),"ó","o"),"ǒ","o"),"ò","o"),"ū","u"),"ú","u"),"ǔ","u"),"ù","u"),"ǖ","v"),"ǘ","v"),"ǚ","v"),"ǜ","v")
A12: =IF(Data_HSK3!E6="","",Data_HSK3!E6) -> theo, căn cứ theo | C12: =IF(OR(A12="",TRIM(B12)=""),"",IF(OR(ISNUMBER(FIND("|"&F12&"|",Data_HSK3!G6)),AND(F12=G12,ISNUMBER(FIND("|"&G12&"|",Data_HSK3!H6)))),"✅","❌")) | D12: =IF(OR(A12="",$D$5<>"Có"),"",Data_HSK3!B6&" ("&Data_HSK3!C6&")") | F12: =IF(TRIM(B12)="","",SUBSTITUTE(SUBSTITUTE(SUBSTITUTE(SUBSTITUTE(SUBSTITUTE(SUBSTITUTE(SUBSTITUTE(SUBSTITUTE(SUBSTITUTE(SUBSTITUTE(SUBSTITUTE(SUBSTITUTE(SUBSTITUTE(SUBSTITUTE(SUBSTITUTE(SUBSTITUTE(LOWER(TRIM(B12))," ",""),"'",""),"’",""),"·",""),"/",""),"-",""),"(",""),")",""),"（",""),"）",""),"ü","v"),";","|"),"；","|"),",","|"),"，","|"),"、","|")) | G12: =SUBSTITUTE(SUBSTITUTE(SUBSTITUTE(SUBSTITUTE(SUBSTITUTE(SUBSTITUTE(SUBSTITUTE(SUBSTITUTE(SUBSTITUTE(SUBSTITUTE(SUBSTITUTE(SUBSTITUTE(SUBSTITUTE(SUBSTITUTE(SUBSTITUTE(SUBSTITUTE(SUBSTITUTE(SUBSTITUTE(SUBSTITUTE(SUBSTITUTE(SUBSTITUTE(SUBSTITUTE(SUBSTITUTE(SUBSTITUTE(F12,"ā","a"),"á","a"),"ǎ","a"),"à","a"),"ē","e"),"é","e"),"ě","e"),"è","e"),"ī","i"),"í","i"),"ǐ","i"),"ì","i"),"ō","o"),"ó","o"),"ǒ","o"),"ò","o"),"ū","u"),"ú","u"),"ǔ","u"),"ù","u"),"ǖ","v"),"ǘ","v"),"ǚ","v"),"ǜ","v")
A13: =IF(Data_HSK3!E7="","",Data_HSK3!E7) -> đem, lấy (giới từ câu chữ 把) | C13: =IF(OR(A13="",TRIM(B13)=""),"",IF(OR(ISNUMBER(FIND("|"&F13&"|",Data_HSK3!G7)),AND(F13=G13,ISNUMBER(FIND("|"&G13&"|",Data_HSK3!H7)))),"✅","❌")) | D13: =IF(OR(A13="",$D$5<>"Có"),"",Data_HSK3!B7&" ("&Data_HSK3!C7&")") | F13: =IF(TRIM(B13)="","",SUBSTITUTE(SUBSTITUTE(SUBSTITUTE(SUBSTITUTE(SUBSTITUTE(SUBSTITUTE(SUBSTITUTE(SUBSTITUTE(SUBSTITUTE(SUBSTITUTE(SUBSTITUTE(SUBSTITUTE(SUBSTITUTE(SUBSTITUTE(SUBSTITUTE(SUBSTITUTE(LOWER(TRIM(B13))," ",""),"'",""),"’",""),"·",""),"/",""),"-",""),"(",""),")",""),"（",""),"）",""),"ü","v"),";","|"),"；","|"),",","|"),"，","|"),"、","|")) | G13: =SUBSTITUTE(SUBSTITUTE(SUBSTITUTE(SUBSTITUTE(SUBSTITUTE(SUBSTITUTE(SUBSTITUTE(SUBSTITUTE(SUBSTITUTE(SUBSTITUTE(SUBSTITUTE(SUBSTITUTE(SUBSTITUTE(SUBSTITUTE(SUBSTITUTE(SUBSTITUTE(SUBSTITUTE(SUBSTITUTE(SUBSTITUTE(SUBSTITUTE(SUBSTITUTE(SUBSTITUTE(SUBSTITUTE(SUBSTITUTE(F13,"ā","a"),"á","a"),"ǎ","a"),"à","a"),"ē","e"),"é","e"),"ě","e"),"è","e"),"ī","i"),"í","i"),"ǐ","i"),"ì","i"),"ō","o"),"ó","o"),"ǒ","o"),"ò","o"),"ū","u"),"ú","u"),"ǔ","u"),"ù","u"),"ǖ","v"),"ǘ","v"),"ǚ","v"),"ǜ","v")
A14: =IF(Data_HSK3!E8="","",Data_HSK3!E8) -> cái, chiếc (vật có tay cầm); nắm | C14: =IF(OR(A14="",TRIM(B14)=""),"",IF(OR(ISNUMBER(FIND("|"&F14&"|",Data_HSK3!G8)),AND(F14=G14,ISNUMBER(FIND("|"&G14&"|",Data_HSK3!H8)))),"✅","❌")) | D14: =IF(OR(A14="",$D$5<>"Có"),"",Data_HSK3!B8&" ("&Data_HSK3!C8&")") | F14: =IF(TRIM(B14)="","",SUBSTITUTE(SUBSTITUTE(SUBSTITUTE(SUBSTITUTE(SUBSTITUTE(SUBSTITUTE(SUBSTITUTE(SUBSTITUTE(SUBSTITUTE(SUBSTITUTE(SUBSTITUTE(SUBSTITUTE(SUBSTITUTE(SUBSTITUTE(SUBSTITUTE(SUBSTITUTE(LOWER(TRIM(B14))," ",""),"'",""),"’",""),"·",""),"/",""),"-",""),"(",""),")",""),"（",""),"）",""),"ü","v"),";","|"),"；","|"),",","|"),"，","|"),"、","|")) | G14: =SUBSTITUTE(SUBSTITUTE(SUBSTITUTE(SUBSTITUTE(SUBSTITUTE(SUBSTITUTE(SUBSTITUTE(SUBSTITUTE(SUBSTITUTE(SUBSTITUTE(SUBSTITUTE(SUBSTITUTE(SUBSTITUTE(SUBSTITUTE(SUBSTITUTE(SUBSTITUTE(SUBSTITUTE(SUBSTITUTE(SUBSTITUTE(SUBSTITUTE(SUBSTITUTE(SUBSTITUTE(SUBSTITUTE(SUBSTITUTE(F14,"ā","a"),"á","a"),"ǎ","a"),"à","a"),"ē","e"),"é","e"),"ě","e"),"è","e"),"ī","i"),"í","i"),"ǐ","i"),"ì","i"),"ō","o"),"ó","o"),"ǒ","o"),"ò","o"),"ū","u"),"ú","u"),"ǔ","u"),"ù","u"),"ǖ","v"),"ǘ","v"),"ǚ","v"),"ǜ","v")
A15: =IF(Data_HSK3!E9="","",Data_HSK3!E9) -> nắm chắc; sự chắc chắn | C15: =IF(OR(A15="",TRIM(B15)=""),"",IF(OR(ISNUMBER(FIND("|"&F15&"|",Data_HSK3!G9)),AND(F15=G15,ISNUMBER(FIND("|"&G15&"|",Data_HSK3!H9)))),"✅","❌")) | D15: =IF(OR(A15="",$D$5<>"Có"),"",Data_HSK3!B9&" ("&Data_HSK3!C9&")") | F15: =IF(TRIM(B15)="","",SUBSTITUTE(SUBSTITUTE(SUBSTITUTE(SUBSTITUTE(SUBSTITUTE(SUBSTITUTE(SUBSTITUTE(SUBSTITUTE(SUBSTITUTE(SUBSTITUTE(SUBSTITUTE(SUBSTITUTE(SUBSTITUTE(SUBSTITUTE(SUBSTITUTE(SUBSTITUTE(LOWER(TRIM(B15))," ",""),"'",""),"’",""),"·",""),"/",""),"-",""),"(",""),")",""),"（",""),"）",""),"ü","v"),";","|"),"；","|"),",","|"),"，","|"),"、","|")) | G15: =SUBSTITUTE(SUBSTITUTE(SUBSTITUTE(SUBSTITUTE(SUBSTITUTE(SUBSTITUTE(SUBSTITUTE(SUBSTITUTE(SUBSTITUTE(SUBSTITUTE(SUBSTITUTE(SUBSTITUTE(SUBSTITUTE(SUBSTITUTE(SUBSTITUTE(SUBSTITUTE(SUBSTITUTE(SUBSTITUTE(SUBSTITUTE(SUBSTITUTE(SUBSTITUTE(SUBSTITUTE(SUBSTITUTE(SUBSTITUTE(F15,"ā","a"),"á","a"),"ǎ","a"),"à","a"),"ē","e"),"é","e"),"ě","e"),"è","e"),"ī","i"),"í","i"),"ǐ","i"),"ì","i"),"ō","o"),"ó","o"),"ǒ","o"),"ò","o"),"ū","u"),"ú","u"),"ǔ","u"),"ù","u"),"ǖ","v"),"ǘ","v"),"ǚ","v"),"ǜ","v")
A16: =IF(Data_HSK3!E10="","",Data_HSK3!E10) -> uổng công, vô ích (phó từ) | C16: =IF(OR(A16="",TRIM(B16)=""),"",IF(OR(ISNUMBER(FIND("|"&F16&"|",Data_HSK3!G10)),AND(F16=G16,ISNUMBER(FIND("|"&G16&"|",Data_HSK3!H10)))),"✅","❌")) | D16: =IF(OR(A16="",$D$5<>"Có"),"",Data_HSK3!B10&" ("&Data_HSK3!C10&")") | F16: =IF(TRIM(B16)="","",SUBSTITUTE(SUBSTITUTE(SUBSTITUTE(SUBSTITUTE(SUBSTITUTE(SUBSTITUTE(SUBSTITUTE(SUBSTITUTE(SUBSTITUTE(SUBSTITUTE(SUBSTITUTE(SUBSTITUTE(SUBSTITUTE(SUBSTITUTE(SUBSTITUTE(SUBSTITUTE(LOWER(TRIM(B16))," ",""),"'",""),"’",""),"·",""),"/",""),"-",""),"(",""),")",""),"（",""),"）",""),"ü","v"),";","|"),"；","|"),",","|"),"，","|"),"、","|")) | G16: =SUBSTITUTE(SUBSTITUTE(SUBSTITUTE(SUBSTITUTE(SUBSTITUTE(SUBSTITUTE(SUBSTITUTE(SUBSTITUTE(SUBSTITUTE(SUBSTITUTE(SUBSTITUTE(SUBSTITUTE(SUBSTITUTE(SUBSTITUTE(SUBSTITUTE(SUBSTITUTE(SUBSTITUTE(SUBSTITUTE(SUBSTITUTE(SUBSTITUTE(SUBSTITUTE(SUBSTITUTE(SUBSTITUTE(SUBSTITUTE(F16,"ā","a"),"á","a"),"ǎ","a"),"à","a"),"ē","e"),"é","e"),"ě","e"),"è","e"),"ī","i"),"í","i"),"ǐ","i"),"ì","i"),"ō","o"),"ó","o"),"ǒ","o"),"ò","o"),"ū","u"),"ú","u"),"ǔ","u"),"ù","u"),"ǖ","v"),"ǘ","v"),"ǚ","v"),"ǜ","v")
A17: =IF(Data_HSK3!E11="","",Data_HSK3!E11) -> cải thảo | C17: =IF(OR(A17="",TRIM(B17)=""),"",IF(OR(ISNUMBER(FIND("|"&F17&"|",Data_HSK3!G11)),AND(F17=G17,ISNUMBER(FIND("|"&G17&"|",Data_HSK3!H11)))),"✅","❌")) | D17: =IF(OR(A17="",$D$5<>"Có"),"",Data_HSK3!B11&" ("&Data_HSK3!C11&")") | F17: =IF(TRIM(B17)="","",SUBSTITUTE(SUBSTITUTE(SUBSTITUTE(SUBSTITUTE(SUBSTITUTE(SUBSTITUTE(SUBSTITUTE(SUBSTITUTE(SUBSTITUTE(SUBSTITUTE(SUBSTITUTE(SUBSTITUTE(SUBSTITUTE(SUBSTITUTE(SUBSTITUTE(SUBSTITUTE(LOWER(TRIM(B17))," ",""),"'",""),"’",""),"·",""),"/",""),"-",""),"(",""),")",""),"（",""),"）",""),"ü","v"),";","|"),"；","|"),",","|"),"，","|"),"、","|")) | G17: =SUBSTITUTE(SUBSTITUTE(SUBSTITUTE(SUBSTITUTE(SUBSTITUTE(SUBSTITUTE(SUBSTITUTE(SUBSTITUTE(SUBSTITUTE(SUBSTITUTE(SUBSTITUTE(SUBSTITUTE(SUBSTITUTE(SUBSTITUTE(SUBSTITUTE(SUBSTITUTE(SUBSTITUTE(SUBSTITUTE(SUBSTITUTE(SUBSTITUTE(SUBSTITUTE(SUBSTITUTE(SUBSTITUTE(SUBSTITUTE(F17,"ā","a"),"á","a"),"ǎ","a"),"à","a"),"ē","e"),"é","e"),"ě","e"),"è","e"),"ī","i"),"í","i"),"ǐ","i"),"ì","i"),"ō","o"),"ó","o"),"ǒ","o"),"ò","o"),"ū","u"),"ú","u"),"ǔ","u"),"ù","u"),"ǖ","v"),"ǘ","v"),"ǚ","v"),"ǜ","v")
A18: =IF(Data_HSK3!E12="","",Data_HSK3!E12) -> lớp học, khối lớp (班级) | C18: =IF(OR(A18="",TRIM(B18)=""),"",IF(OR(ISNUMBER(FIND("|"&F18&"|",Data_HSK3!G12)),AND(F18=G18,ISNUMBER(FIND("|"&G18&"|",Data_HSK3!H12)))),"✅","❌")) | D18: =IF(OR(A18="",$D$5<>"Có"),"",Data_HSK3!B12&" ("&Data_HSK3!C12&")") | F18: =IF(TRIM(B18)="","",SUBSTITUTE(SUBSTITUTE(SUBSTITUTE(SUBSTITUTE(SUBSTITUTE(SUBSTITUTE(SUBSTITUTE(SUBSTITUTE(SUBSTITUTE(SUBSTITUTE(SUBSTITUTE(SUBSTITUTE(SUBSTITUTE(SUBSTITUTE(SUBSTITUTE(SUBSTITUTE(LOWER(TRIM(B18))," ",""),"'",""),"’",""),"·",""),"/",""),"-",""),"(",""),")",""),"（",""),"）",""),"ü","v"),";","|"),"；","|"),",","|"),"，","|"),"、","|")) | G18: =SUBSTITUTE(SUBSTITUTE(SUBSTITUTE(SUBSTITUTE(SUBSTITUTE(SUBSTITUTE(SUBSTITUTE(SUBSTITUTE(SUBSTITUTE(SUBSTITUTE(SUBSTITUTE(SUBSTITUTE(SUBSTITUTE(SUBSTITUTE(SUBSTITUTE(SUBSTITUTE(SUBSTITUTE(SUBSTITUTE(SUBSTITUTE(SUBSTITUTE(SUBSTITUTE(SUBSTITUTE(SUBSTITUTE(SUBSTITUTE(F18,"ā","a"),"á","a"),"ǎ","a"),"à","a"),"ē","e"),"é","e"),"ě","e"),"è","e"),"ī","i"),"í","i"),"ǐ","i"),"ì","i"),"ō","o"),"ó","o"),"ǒ","o"),"ò","o"),"ū","u"),"ú","u"),"ǔ","u"),"ù","u"),"ǖ","v"),"ǘ","v"),"ǚ","v"),"ǜ","v")
A19: =IF(Data_HSK3!E13="","",Data_HSK3!E13) -> chuyển, khuân, dọn | C19: =IF(OR(A19="",TRIM(B19)=""),"",IF(OR(ISNUMBER(FIND("|"&F19&"|",Data_HSK3!G13)),AND(F19=G19,ISNUMBER(FIND("|"&G19&"|",Data_HSK3!H13)))),"✅","❌")) | D19: =IF(OR(A19="",$D$5<>"Có"),"",Data_HSK3!B13&" ("&Data_HSK3!C13&")") | F19: =IF(TRIM(B19)="","",SUBSTITUTE(SUBSTITUTE(SUBSTITUTE(SUBSTITUTE(SUBSTITUTE(SUBSTITUTE(SUBSTITUTE(SUBSTITUTE(SUBSTITUTE(SUBSTITUTE(SUBSTITUTE(SUBSTITUTE(SUBSTITUTE(SUBSTITUTE(SUBSTITUTE(SUBSTITUTE(LOWER(TRIM(B19))," ",""),"'",""),"’",""),"·",""),"/",""),"-",""),"(",""),")",""),"（",""),"）",""),"ü","v"),";","|"),"；","|"),",","|"),"，","|"),"、","|")) | G19: =SUBSTITUTE(SUBSTITUTE(SUBSTITUTE(SUBSTITUTE(SUBSTITUTE(SUBSTITUTE(SUBSTITUTE(SUBSTITUTE(SUBSTITUTE(SUBSTITUTE(SUBSTITUTE(SUBSTITUTE(SUBSTITUTE(SUBSTITUTE(SUBSTITUTE(SUBSTITUTE(SUBSTITUTE(SUBSTITUTE(SUBSTITUTE(SUBSTITUTE(SUBSTITUTE(SUBSTITUTE(SUBSTITUTE(SUBSTITUTE(F19,"ā","a"),"á","a"),"ǎ","a"),"à","a"),"ē","e"),"é","e"),"ě","e"),"è","e"),"ī","i"),"í","i"),"ǐ","i"),"ì","i"),"ō","o"),"ó","o"),"ǒ","o"),"ò","o"),"ū","u"),"ú","u"),"ǔ","u"),"ù","u"),"ǖ","v"),"ǘ","v"),"ǚ","v"),"ǜ","v")
... A1207: =IF(Data_HSK3!E1201="","",Data_HSK3!E1201) | C1207: =IF(OR(A1207="",TRIM(B1207)=""),"",IF(OR(ISNUMBER(FIND("|"&F1207&"|",Data_HSK3!G1201)),AND(F1207=G1207,ISNUMBER(FIND("|"&G1207&"|",Data_HSK3!H1201)))),"✅","❌")) | D1207: =IF(OR(A1207="",$D$5<>"Có"),"",Data_HSK3!B1201&" ("&Data_HSK3!C1201&")") | F1207: =IF(TRIM(B1207)="","",SUBSTITUTE(SUBSTITUTE(SUBSTITUTE(SUBSTITUTE(SUBSTITUTE(SUBSTITUTE(SUBSTITUTE(SUBSTITUTE(SUBSTITUTE(SUBSTITUTE(SUBSTITUTE(SUBSTITUTE(SUBSTITUTE(SUBSTITUTE(SUBSTITUTE(SUBSTITUTE(LOWER(TRIM(B1207))," ",""),"'",""),"’",""),"·",""),"/",""),"-",""),"(",""),")",""),"（",""),"）",""),"ü","v"),";","|"),"；","|"),",","|"),"，","|"),"、","|")) | G1207: =SUBSTITUTE(SUBSTITUTE(SUBSTITUTE(SUBSTITUTE(SUBSTITUTE(SUBSTITUTE(SUBSTITUTE(SUBSTITUTE(SUBSTITUTE(SUBSTITUTE(SUBSTITUTE(SUBSTITUTE(SUBSTITUTE(SUBSTITUTE(SUBSTITUTE(SUBSTITUTE(SUBSTITUTE(SUBSTITUTE(SUBSTITUTE(SUBSTITUTE(SUBSTITUTE(SUBSTITUTE(SUBSTITUTE(SUBSTITUTE(F1207,"ā","a"),"á","a"),"ǎ","a"),"à","a"),"ē","e"),"é","e"),"ě","e"),"è","e"),"ī","i"),"í","i"),"ǐ","i"),"ì","i"),"ō","o"),"ó","o"),"ǒ","o"),"ò","o"),"ū","u"),"ú","u"),"ǔ","u"),"ù","u"),"ǖ","v"),"ǘ","v"),"ǚ","v"),"ǜ","v")

Sheet Từ vựng HSK4
A1: LUYỆN TẬP TỪ VỰNG HSK 4 (HSK 3.0 — 1000 từ)
A2: Nhập chữ Hán giản thể hoặc Pinyin (có/không dấu thanh) vào cột B — chỉ cần sửa các ô màu vàng.
A3: Tổng số câu | B3: Số câu đã làm đúng ✅ | C3: Số câu sai ❌ | D3: Tỷ lệ hoàn thành (%)
A4: =COUNTIF($A$8:$A$1207,"?*") -> 1000 | B4: =COUNTIF($C$8:$C$1207,"✅") -> 0 | C4: =COUNTIF($C$8:$C$1207,"❌") -> 0 | D4: =IF(A4=0,0,B4/A4) -> 0
A5: Tiến độ | B5: =REPT("█",ROUND(D4*20,0))&REPT("░",20-ROUND(D4*20,0)) -> ░░░░░░░░░░░░░░░░░░░░ | C5: =IF(B4+C4=0,"Độ chính xác: –","Độ chính xác: "&TEXT(B4/(B4+C4),"0%")) -> Độ chính xác: – | D5: Không
D6: ▲ Hiện gợi ý (Có/Không)
A7: Ý nghĩa | B7: Ô người học nhập | C7: Kết quả | D7: Gợi ý | F7: norm có dấu | G7: norm không dấu
A8: =IF(Data_HSK4!E2="","",Data_HSK4!E2) -> cô, dì, thím | C8: =IF(OR(A8="",TRIM(B8)=""),"",IF(OR(ISNUMBER(FIND("|"&F8&"|",Data_HSK4!G2)),AND(F8=G8,ISNUMBER(FIND("|"&G8&"|",Data_HSK4!H2)))),"✅","❌")) | D8: =IF(OR(A8="",$D$5<>"Có"),"",Data_HSK4!B2&" ("&Data_HSK4!C2&")") | F8: =IF(TRIM(B8)="","",SUBSTITUTE(SUBSTITUTE(SUBSTITUTE(SUBSTITUTE(SUBSTITUTE(SUBSTITUTE(SUBSTITUTE(SUBSTITUTE(SUBSTITUTE(SUBSTITUTE(SUBSTITUTE(SUBSTITUTE(SUBSTITUTE(SUBSTITUTE(SUBSTITUTE(SUBSTITUTE(LOWER(TRIM(B8))," ",""),"'",""),"’",""),"·",""),"/",""),"-",""),"(",""),")",""),"（",""),"）",""),"ü","v"),";","|"),"；","|"),",","|"),"，","|"),"、","|")) | G8: =SUBSTITUTE(SUBSTITUTE(SUBSTITUTE(SUBSTITUTE(SUBSTITUTE(SUBSTITUTE(SUBSTITUTE(SUBSTITUTE(SUBSTITUTE(SUBSTITUTE(SUBSTITUTE(SUBSTITUTE(SUBSTITUTE(SUBSTITUTE(SUBSTITUTE(SUBSTITUTE(SUBSTITUTE(SUBSTITUTE(SUBSTITUTE(SUBSTITUTE(SUBSTITUTE(SUBSTITUTE(SUBSTITUTE(SUBSTITUTE(F8,"ā","a"),"á","a"),"ǎ","a"),"à","a"),"ē","e"),"é","e"),"ě","e"),"è","e"),"ī","i"),"í","i"),"ǐ","i"),"ì","i"),"ō","o"),"ó","o"),"ǒ","o"),"ò","o"),"ū","u"),"ú","u"),"ǔ","u"),"ù","u"),"ǖ","v"),"ǘ","v"),"ǚ","v"),"ǜ","v")
A9: =IF(Data_HSK4!E3="","",Data_HSK4!E3) -> a, à (thán từ) | C9: =IF(OR(A9="",TRIM(B9)=""),"",IF(OR(ISNUMBER(FIND("|"&F9&"|",Data_HSK4!G3)),AND(F9=G9,ISNUMBER(FIND("|"&G9&"|",Data_HSK4!H3)))),"✅","❌")) | D9: =IF(OR(A9="",$D$5<>"Có"),"",Data_HSK4!B3&" ("&Data_HSK4!C3&")") | F9: =IF(TRIM(B9)="","",SUBSTITUTE(SUBSTITUTE(SUBSTITUTE(SUBSTITUTE(SUBSTITUTE(SUBSTITUTE(SUBSTITUTE(SUBSTITUTE(SUBSTITUTE(SUBSTITUTE(SUBSTITUTE(SUBSTITUTE(SUBSTITUTE(SUBSTITUTE(SUBSTITUTE(SUBSTITUTE(LOWER(TRIM(B9))," ",""),"'",""),"’",""),"·",""),"/",""),"-",""),"(",""),")",""),"（",""),"）",""),"ü","v"),";","|"),"；","|"),",","|"),"，","|"),"、","|")) | G9: =SUBSTITUTE(SUBSTITUTE(SUBSTITUTE(SUBSTITUTE(SUBSTITUTE(SUBSTITUTE(SUBSTITUTE(SUBSTITUTE(SUBSTITUTE(SUBSTITUTE(SUBSTITUTE(SUBSTITUTE(SUBSTITUTE(SUBSTITUTE(SUBSTITUTE(SUBSTITUTE(SUBSTITUTE(SUBSTITUTE(SUBSTITUTE(SUBSTITUTE(SUBSTITUTE(SUBSTITUTE(SUBSTITUTE(SUBSTITUTE(F9,"ā","a"),"á","a"),"ǎ","a"),"à","a"),"ē","e"),"é","e"),"ě","e"),"è","e"),"ī","i"),"í","i"),"ǐ","i"),"ì","i"),"ō","o"),"ó","o"),"ǒ","o"),"ò","o"),"ū","u"),"ú","u"),"ǔ","u"),"ù","u"),"ǖ","v"),"ǘ","v"),"ǚ","v"),"ǜ","v")
A10: =IF(Data_HSK4!E4="","",Data_HSK4!E4) -> thấp | C10: =IF(OR(A10="",TRIM(B10)=""),"",IF(OR(ISNUMBER(FIND("|"&F10&"|",Data_HSK4!G4)),AND(F10=G10,ISNUMBER(FIND("|"&G10&"|",Data_HSK4!H4)))),"✅","❌")) | D10: =IF(OR(A10="",$D$5<>"Có"),"",Data_HSK4!B4&" ("&Data_HSK4!C4&")") | F10: =IF(TRIM(B10)="","",SUBSTITUTE(SUBSTITUTE(SUBSTITUTE(SUBSTITUTE(SUBSTITUTE(SUBSTITUTE(SUBSTITUTE(SUBSTITUTE(SUBSTITUTE(SUBSTITUTE(SUBSTITUTE(SUBSTITUTE(SUBSTITUTE(SUBSTITUTE(SUBSTITUTE(SUBSTITUTE(LOWER(TRIM(B10))," ",""),"'",""),"’",""),"·",""),"/",""),"-",""),"(",""),")",""),"（",""),"）",""),"ü","v"),";","|"),"；","|"),",","|"),"，","|"),"、","|")) | G10: =SUBSTITUTE(SUBSTITUTE(SUBSTITUTE(SUBSTITUTE(SUBSTITUTE(SUBSTITUTE(SUBSTITUTE(SUBSTITUTE(SUBSTITUTE(SUBSTITUTE(SUBSTITUTE(SUBSTITUTE(SUBSTITUTE(SUBSTITUTE(SUBSTITUTE(SUBSTITUTE(SUBSTITUTE(SUBSTITUTE(SUBSTITUTE(SUBSTITUTE(SUBSTITUTE(SUBSTITUTE(SUBSTITUTE(SUBSTITUTE(F10,"ā","a"),"á","a"),"ǎ","a"),"à","a"),"ē","e"),"é","e"),"ě","e"),"è","e"),"ī","i"),"í","i"),"ǐ","i"),"ì","i"),"ō","o"),"ó","o"),"ǒ","o"),"ò","o"),"ū","u"),"ú","u"),"ǔ","u"),"ù","u"),"ǖ","v"),"ǘ","v"),"ǚ","v"),"ǜ","v")
A11: =IF(Data_HSK4!E5="","",Data_HSK4!E5) -> thấp bé | C11: =IF(OR(A11="",TRIM(B11)=""),"",IF(OR(ISNUMBER(FIND("|"&F11&"|",Data_HSK4!G5)),AND(F11=G11,ISNUMBER(FIND("|"&G11&"|",Data_HSK4!H5)))),"✅","❌")) | D11: =IF(OR(A11="",$D$5<>"Có"),"",Data_HSK4!B5&" ("&Data_HSK4!C5&")") | F11: =IF(TRIM(B11)="","",SUBSTITUTE(SUBSTITUTE(SUBSTITUTE(SUBSTITUTE(SUBSTITUTE(SUBSTITUTE(SUBSTITUTE(SUBSTITUTE(SUBSTITUTE(SUBSTITUTE(SUBSTITUTE(SUBSTITUTE(SUBSTITUTE(SUBSTITUTE(SUBSTITUTE(SUBSTITUTE(LOWER(TRIM(B11))," ",""),"'",""),"’",""),"·",""),"/",""),"-",""),"(",""),")",""),"（",""),"）",""),"ü","v"),";","|"),"；","|"),",","|"),"，","|"),"、","|")) | G11: =SUBSTITUTE(SUBSTITUTE(SUBSTITUTE(SUBSTITUTE(SUBSTITUTE(SUBSTITUTE(SUBSTITUTE(SUBSTITUTE(SUBSTITUTE(SUBSTITUTE(SUBSTITUTE(SUBSTITUTE(SUBSTITUTE(SUBSTITUTE(SUBSTITUTE(SUBSTITUTE(SUBSTITUTE(SUBSTITUTE(SUBSTITUTE(SUBSTITUTE(SUBSTITUTE(SUBSTITUTE(SUBSTITUTE(SUBSTITUTE(F11,"ā","a"),"á","a"),"ǎ","a"),"à","a"),"ē","e"),"é","e"),"ě","e"),"è","e"),"ī","i"),"í","i"),"ǐ","i"),"ì","i"),"ō","o"),"ó","o"),"ǒ","o"),"ò","o"),"ū","u"),"ú","u"),"ǔ","u"),"ù","u"),"ǖ","v"),"ǘ","v"),"ǚ","v"),"ǜ","v")
A12: =IF(Data_HSK4!E6="","",Data_HSK4!E6) -> yêu nước | C12: =IF(OR(A12="",TRIM(B12)=""),"",IF(OR(ISNUMBER(FIND("|"&F12&"|",Data_HSK4!G6)),AND(F12=G12,ISNUMBER(FIND("|"&G12&"|",Data_HSK4!H6)))),"✅","❌")) | D12: =IF(OR(A12="",$D$5<>"Có"),"",Data_HSK4!B6&" ("&Data_HSK4!C6&")") | F12: =IF(TRIM(B12)="","",SUBSTITUTE(SUBSTITUTE(SUBSTITUTE(SUBSTITUTE(SUBSTITUTE(SUBSTITUTE(SUBSTITUTE(SUBSTITUTE(SUBSTITUTE(SUBSTITUTE(SUBSTITUTE(SUBSTITUTE(SUBSTITUTE(SUBSTITUTE(SUBSTITUTE(SUBSTITUTE(LOWER(TRIM(B12))," ",""),"'",""),"’",""),"·",""),"/",""),"-",""),"(",""),")",""),"（",""),"）",""),"ü","v"),";","|"),"；","|"),",","|"),"，","|"),"、","|")) | G12: =SUBSTITUTE(SUBSTITUTE(SUBSTITUTE(SUBSTITUTE(SUBSTITUTE(SUBSTITUTE(SUBSTITUTE(SUBSTITUTE(SUBSTITUTE(SUBSTITUTE(SUBSTITUTE(SUBSTITUTE(SUBSTITUTE(SUBSTITUTE(SUBSTITUTE(SUBSTITUTE(SUBSTITUTE(SUBSTITUTE(SUBSTITUTE(SUBSTITUTE(SUBSTITUTE(SUBSTITUTE(SUBSTITUTE(SUBSTITUTE(F12,"ā","a"),"á","a"),"ǎ","a"),"à","a"),"ē","e"),"é","e"),"ě","e"),"è","e"),"ī","i"),"í","i"),"ǐ","i"),"ì","i"),"ō","o"),"ó","o"),"ǒ","o"),"ò","o"),"ū","u"),"ú","u"),"ǔ","u"),"ù","u"),"ǖ","v"),"ǘ","v"),"ǚ","v"),"ǜ","v")
A13: =IF(Data_HSK4!E7="","",Data_HSK4!E7) -> yêu quý, chăm sóc | C13: =IF(OR(A13="",TRIM(B13)=""),"",IF(OR(ISNUMBER(FIND("|"&F13&"|",Data_HSK4!G7)),AND(F13=G13,ISNUMBER(FIND("|"&G13&"|",Data_HSK4!H7)))),"✅","❌")) | D13: =IF(OR(A13="",$D$5<>"Có"),"",Data_HSK4!B7&" ("&Data_HSK4!C7&")") | F13: =IF(TRIM(B13)="","",SUBSTITUTE(SUBSTITUTE(SUBSTITUTE(SUBSTITUTE(SUBSTITUTE(SUBSTITUTE(SUBSTITUTE(SUBSTITUTE(SUBSTITUTE(SUBSTITUTE(SUBSTITUTE(SUBSTITUTE(SUBSTITUTE(SUBSTITUTE(SUBSTITUTE(SUBSTITUTE(LOWER(TRIM(B13))," ",""),"'",""),"’",""),"·",""),"/",""),"-",""),"(",""),")",""),"（",""),"）",""),"ü","v"),";","|"),"；","|"),",","|"),"，","|"),"、","|")) | G13: =SUBSTITUTE(SUBSTITUTE(SUBSTITUTE(SUBSTITUTE(SUBSTITUTE(SUBSTITUTE(SUBSTITUTE(SUBSTITUTE(SUBSTITUTE(SUBSTITUTE(SUBSTITUTE(SUBSTITUTE(SUBSTITUTE(SUBSTITUTE(SUBSTITUTE(SUBSTITUTE(SUBSTITUTE(SUBSTITUTE(SUBSTITUTE(SUBSTITUTE(SUBSTITUTE(SUBSTITUTE(SUBSTITUTE(SUBSTITUTE(F13,"ā","a"),"á","a"),"ǎ","a"),"à","a"),"ē","e"),"é","e"),"ě","e"),"è","e"),"ī","i"),"í","i"),"ǐ","i"),"ì","i"),"ō","o"),"ó","o"),"ǒ","o"),"ò","o"),"ū","u"),"ú","u"),"ǔ","u"),"ù","u"),"ǖ","v"),"ǘ","v"),"ǚ","v"),"ǜ","v")
A14: =IF(Data_HSK4!E8="","",Data_HSK4!E8) -> yên ổn; lắp đặt | C14: =IF(OR(A14="",TRIM(B14)=""),"",IF(OR(ISNUMBER(FIND("|"&F14&"|",Data_HSK4!G8)),AND(F14=G14,ISNUMBER(FIND("|"&G14&"|",Data_HSK4!H8)))),"✅","❌")) | D14: =IF(OR(A14="",$D$5<>"Có"),"",Data_HSK4!B8&" ("&Data_HSK4!C8&")") | F14: =IF(TRIM(B14)="","",SUBSTITUTE(SUBSTITUTE(SUBSTITUTE(SUBSTITUTE(SUBSTITUTE(SUBSTITUTE(SUBSTITUTE(SUBSTITUTE(SUBSTITUTE(SUBSTITUTE(SUBSTITUTE(SUBSTITUTE(SUBSTITUTE(SUBSTITUTE(SUBSTITUTE(SUBSTITUTE(LOWER(TRIM(B14))," ",""),"'",""),"’",""),"·",""),"/",""),"-",""),"(",""),")",""),"（",""),"）",""),"ü","v"),";","|"),"；","|"),",","|"),"，","|"),"、","|")) | G14: =SUBSTITUTE(SUBSTITUTE(SUBSTITUTE(SUBSTITUTE(SUBSTITUTE(SUBSTITUTE(SUBSTITUTE(SUBSTITUTE(SUBSTITUTE(SUBSTITUTE(SUBSTITUTE(SUBSTITUTE(SUBSTITUTE(SUBSTITUTE(SUBSTITUTE(SUBSTITUTE(SUBSTITUTE(SUBSTITUTE(SUBSTITUTE(SUBSTITUTE(SUBSTITUTE(SUBSTITUTE(SUBSTITUTE(SUBSTITUTE(F14,"ā","a"),"á","a"),"ǎ","a"),"à","a"),"ē","e"),"é","e"),"ě","e"),"è","e"),"ī","i"),"í","i"),"ǐ","i"),"ì","i"),"ō","o"),"ó","o"),"ǒ","o"),"ò","o"),"ū","u"),"ú","u"),"ǔ","u"),"ù","u"),"ǖ","v"),"ǘ","v"),"ǚ","v"),"ǜ","v")
A15: =IF(Data_HSK4!E9="","",Data_HSK4!E9) -> bố trí, sắp xếp | C15: =IF(OR(A15="",TRIM(B15)=""),"",IF(OR(ISNUMBER(FIND("|"&F15&"|",Data_HSK4!G9)),AND(F15=G15,ISNUMBER(FIND("|"&G15&"|",Data_HSK4!H9)))),"✅","❌")) | D15: =IF(OR(A15="",$D$5<>"Có"),"",Data_HSK4!B9&" ("&Data_HSK4!C9&")") | F15: =IF(TRIM(B15)="","",SUBSTITUTE(SUBSTITUTE(SUBSTITUTE(SUBSTITUTE(SUBSTITUTE(SUBSTITUTE(SUBSTITUTE(SUBSTITUTE(SUBSTITUTE(SUBSTITUTE(SUBSTITUTE(SUBSTITUTE(SUBSTITUTE(SUBSTITUTE(SUBSTITUTE(SUBSTITUTE(LOWER(TRIM(B15))," ",""),"'",""),"’",""),"·",""),"/",""),"-",""),"(",""),")",""),"（",""),"）",""),"ü","v"),";","|"),"；","|"),",","|"),"，","|"),"、","|")) | G15: =SUBSTITUTE(SUBSTITUTE(SUBSTITUTE(SUBSTITUTE(SUBSTITUTE(SUBSTITUTE(SUBSTITUTE(SUBSTITUTE(SUBSTITUTE(SUBSTITUTE(SUBSTITUTE(SUBSTITUTE(SUBSTITUTE(SUBSTITUTE(SUBSTITUTE(SUBSTITUTE(SUBSTITUTE(SUBSTITUTE(SUBSTITUTE(SUBSTITUTE(SUBSTITUTE(SUBSTITUTE(SUBSTITUTE(SUBSTITUTE(F15,"ā","a"),"á","a"),"ǎ","a"),"à","a"),"ē","e"),"é","e"),"ě","e"),"è","e"),"ī","i"),"í","i"),"ǐ","i"),"ì","i"),"ō","o"),"ó","o"),"ǒ","o"),"ò","o"),"ū","u"),"ú","u"),"ǔ","u"),"ù","u"),"ǖ","v"),"ǘ","v"),"ǚ","v"),"ǜ","v")
A16: =IF(Data_HSK4!E10="","",Data_HSK4!E10) -> đúng giờ | C16: =IF(OR(A16="",TRIM(B16)=""),"",IF(OR(ISNUMBER(FIND("|"&F16&"|",Data_HSK4!G10)),AND(F16=G16,ISNUMBER(FIND("|"&G16&"|",Data_HSK4!H10)))),"✅","❌")) | D16: =IF(OR(A16="",$D$5<>"Có"),"",Data_HSK4!B10&" ("&Data_HSK4!C10&")") | F16: =IF(TRIM(B16)="","",SUBSTITUTE(SUBSTITUTE(SUBSTITUTE(SUBSTITUTE(SUBSTITUTE(SUBSTITUTE(SUBSTITUTE(SUBSTITUTE(SUBSTITUTE(SUBSTITUTE(SUBSTITUTE(SUBSTITUTE(SUBSTITUTE(SUBSTITUTE(SUBSTITUTE(SUBSTITUTE(LOWER(TRIM(B16))," ",""),"'",""),"’",""),"·",""),"/",""),"-",""),"(",""),")",""),"（",""),"）",""),"ü","v"),";","|"),"；","|"),",","|"),"，","|"),"、","|")) | G16: =SUBSTITUTE(SUBSTITUTE(SUBSTITUTE(SUBSTITUTE(SUBSTITUTE(SUBSTITUTE(SUBSTITUTE(SUBSTITUTE(SUBSTITUTE(SUBSTITUTE(SUBSTITUTE(SUBSTITUTE(SUBSTITUTE(SUBSTITUTE(SUBSTITUTE(SUBSTITUTE(SUBSTITUTE(SUBSTITUTE(SUBSTITUTE(SUBSTITUTE(SUBSTITUTE(SUBSTITUTE(SUBSTITUTE(SUBSTITUTE(F16,"ā","a"),"á","a"),"ǎ","a"),"à","a"),"ē","e"),"é","e"),"ě","e"),"è","e"),"ī","i"),"í","i"),"ǐ","i"),"ì","i"),"ō","o"),"ó","o"),"ǒ","o"),"ò","o"),"ū","u"),"ú","u"),"ǔ","u"),"ù","u"),"ǖ","v"),"ǘ","v"),"ǚ","v"),"ǜ","v")
A17: =IF(Data_HSK4!E11="","",Data_HSK4!E11) -> tối | C17: =IF(OR(A17="",TRIM(B17)=""),"",IF(OR(ISNUMBER(FIND("|"&F17&"|",Data_HSK4!G11)),AND(F17=G17,ISNUMBER(FIND("|"&G17&"|",Data_HSK4!H11)))),"✅","❌")) | D17: =IF(OR(A17="",$D$5<>"Có"),"",Data_HSK4!B11&" ("&Data_HSK4!C11&")") | F17: =IF(TRIM(B17)="","",SUBSTITUTE(SUBSTITUTE(SUBSTITUTE(SUBSTITUTE(SUBSTITUTE(SUBSTITUTE(SUBSTITUTE(SUBSTITUTE(SUBSTITUTE(SUBSTITUTE(SUBSTITUTE(SUBSTITUTE(SUBSTITUTE(SUBSTITUTE(SUBSTITUTE(SUBSTITUTE(LOWER(TRIM(B17))," ",""),"'",""),"’",""),"·",""),"/",""),"-",""),"(",""),")",""),"（",""),"）",""),"ü","v"),";","|"),"；","|"),",","|"),"，","|"),"、","|")) | G17: =SUBSTITUTE(SUBSTITUTE(SUBSTITUTE(SUBSTITUTE(SUBSTITUTE(SUBSTITUTE(SUBSTITUTE(SUBSTITUTE(SUBSTITUTE(SUBSTITUTE(SUBSTITUTE(SUBSTITUTE(SUBSTITUTE(SUBSTITUTE(SUBSTITUTE(SUBSTITUTE(SUBSTITUTE(SUBSTITUTE(SUBSTITUTE(SUBSTITUTE(SUBSTITUTE(SUBSTITUTE(SUBSTITUTE(SUBSTITUTE(F17,"ā","a"),"á","a"),"ǎ","a"),"à","a"),"ē","e"),"é","e"),"ě","e"),"è","e"),"ī","i"),"í","i"),"ǐ","i"),"ì","i"),"ō","o"),"ó","o"),"ǒ","o"),"ò","o"),"ū","u"),"ú","u"),"ǔ","u"),"ù","u"),"ǖ","v"),"ǘ","v"),"ǚ","v"),"ǜ","v")
A18: =IF(Data_HSK4!E12="","",Data_HSK4!E12) -> ám chỉ, gợi ý | C18: =IF(OR(A18="",TRIM(B18)=""),"",IF(OR(ISNUMBER(FIND("|"&F18&"|",Data_HSK4!G12)),AND(F18=G18,ISNUMBER(FIND("|"&G18&"|",Data_HSK4!H12)))),"✅","❌")) | D18: =IF(OR(A18="",$D$5<>"Có"),"",Data_HSK4!B12&" ("&Data_HSK4!C12&")") | F18: =IF(TRIM(B18)="","",SUBSTITUTE(SUBSTITUTE(SUBSTITUTE(SUBSTITUTE(SUBSTITUTE(SUBSTITUTE(SUBSTITUTE(SUBSTITUTE(SUBSTITUTE(SUBSTITUTE(SUBSTITUTE(SUBSTITUTE(SUBSTITUTE(SUBSTITUTE(SUBSTITUTE(SUBSTITUTE(LOWER(TRIM(B18))," ",""),"'",""),"’",""),"·",""),"/",""),"-",""),"(",""),")",""),"（",""),"）",""),"ü","v"),";","|"),"；","|"),",","|"),"，","|"),"、","|")) | G18: =SUBSTITUTE(SUBSTITUTE(SUBSTITUTE(SUBSTITUTE(SUBSTITUTE(SUBSTITUTE(SUBSTITUTE(SUBSTITUTE(SUBSTITUTE(SUBSTITUTE(SUBSTITUTE(SUBSTITUTE(SUBSTITUTE(SUBSTITUTE(SUBSTITUTE(SUBSTITUTE(SUBSTITUTE(SUBSTITUTE(SUBSTITUTE(SUBSTITUTE(SUBSTITUTE(SUBSTITUTE(SUBSTITUTE(SUBSTITUTE(F18,"ā","a"),"á","a"),"ǎ","a"),"à","a"),"ē","e"),"é","e"),"ě","e"),"è","e"),"ī","i"),"í","i"),"ǐ","i"),"ì","i"),"ō","o"),"ó","o"),"ǒ","o"),"ò","o"),"ū","u"),"ú","u"),"ǔ","u"),"ù","u"),"ǖ","v"),"ǘ","v"),"ǚ","v"),"ǜ","v")
A19: =IF(Data_HSK4!E13="","",Data_HSK4!E13) -> xe buýt | C19: =IF(OR(A19="",TRIM(B19)=""),"",IF(OR(ISNUMBER(FIND("|"&F19&"|",Data_HSK4!G13)),AND(F19=G19,ISNUMBER(FIND("|"&G19&"|",Data_HSK4!H13)))),"✅","❌")) | D19: =IF(OR(A19="",$D$5<>"Có"),"",Data_HSK4!B13&" ("&Data_HSK4!C13&")") | F19: =IF(TRIM(B19)="","",SUBSTITUTE(SUBSTITUTE(SUBSTITUTE(SUBSTITUTE(SUBSTITUTE(SUBSTITUTE(SUBSTITUTE(SUBSTITUTE(SUBSTITUTE(SUBSTITUTE(SUBSTITUTE(SUBSTITUTE(SUBSTITUTE(SUBSTITUTE(SUBSTITUTE(SUBSTITUTE(LOWER(TRIM(B19))," ",""),"'",""),"’",""),"·",""),"/",""),"-",""),"(",""),")",""),"（",""),"）",""),"ü","v"),";","|"),"；","|"),",","|"),"，","|"),"、","|")) | G19: =SUBSTITUTE(SUBSTITUTE(SUBSTITUTE(SUBSTITUTE(SUBSTITUTE(SUBSTITUTE(SUBSTITUTE(SUBSTITUTE(SUBSTITUTE(SUBSTITUTE(SUBSTITUTE(SUBSTITUTE(SUBSTITUTE(SUBSTITUTE(SUBSTITUTE(SUBSTITUTE(SUBSTITUTE(SUBSTITUTE(SUBSTITUTE(SUBSTITUTE(SUBSTITUTE(SUBSTITUTE(SUBSTITUTE(SUBSTITUTE(F19,"ā","a"),"á","a"),"ǎ","a"),"à","a"),"ē","e"),"é","e"),"ě","e"),"è","e"),"ī","i"),"í","i"),"ǐ","i"),"ì","i"),"ō","o"),"ó","o"),"ǒ","o"),"ò","o"),"ū","u"),"ú","u"),"ǔ","u"),"ù","u"),"ǖ","v"),"ǘ","v"),"ǚ","v"),"ǜ","v")
... A1207: =IF(Data_HSK4!E1201="","",Data_HSK4!E1201) | C1207: =IF(OR(A1207="",TRIM(B1207)=""),"",IF(OR(ISNUMBER(FIND("|"&F1207&"|",Data_HSK4!G1201)),AND(F1207=G1207,ISNUMBER(FIND("|"&G1207&"|",Data_HSK4!H1201)))),"✅","❌")) | D1207: =IF(OR(A1207="",$D$5<>"Có"),"",Data_HSK4!B1201&" ("&Data_HSK4!C1201&")") | F1207: =IF(TRIM(B1207)="","",SUBSTITUTE(SUBSTITUTE(SUBSTITUTE(SUBSTITUTE(SUBSTITUTE(SUBSTITUTE(SUBSTITUTE(SUBSTITUTE(SUBSTITUTE(SUBSTITUTE(SUBSTITUTE(SUBSTITUTE(SUBSTITUTE(SUBSTITUTE(SUBSTITUTE(SUBSTITUTE(LOWER(TRIM(B1207))," ",""),"'",""),"’",""),"·",""),"/",""),"-",""),"(",""),")",""),"（",""),"）",""),"ü","v"),";","|"),"；","|"),",","|"),"，","|"),"、","|")) | G1207: =SUBSTITUTE(SUBSTITUTE(SUBSTITUTE(SUBSTITUTE(SUBSTITUTE(SUBSTITUTE(SUBSTITUTE(SUBSTITUTE(SUBSTITUTE(SUBSTITUTE(SUBSTITUTE(SUBSTITUTE(SUBSTITUTE(SUBSTITUTE(SUBSTITUTE(SUBSTITUTE(SUBSTITUTE(SUBSTITUTE(SUBSTITUTE(SUBSTITUTE(SUBSTITUTE(SUBSTITUTE(SUBSTITUTE(SUBSTITUTE(F1207,"ā","a"),"á","a"),"ǎ","a"),"à","a"),"ē","e"),"é","e"),"ě","e"),"è","e"),"ī","i"),"í","i"),"ǐ","i"),"ì","i"),"ō","o"),"ó","o"),"ǒ","o"),"ò","o"),"ū","u"),"ú","u"),"ǔ","u"),"ù","u"),"ǖ","v"),"ǘ","v"),"ǚ","v"),"ǜ","v")

Sheet Từ vựng HSK1
A1: LUYỆN TẬP TỪ VỰNG HSK 1 (HSK 3.0 — 500 từ)
A2: Nhập chữ Hán giản thể hoặc Pinyin (có/không dấu thanh) vào cột B — chỉ cần sửa các ô màu vàng. | H2: Các bạn nhấn Tệp -> tạo bản sao lưu về drive cá nhân. Nếu có vấn đề các bạn comment bài viết cho mình hay với nha. Tks!
A3: Tổng số câu | B3: Số câu đã làm đúng ✅ | C3: Số câu sai ❌ | D3: Tỷ lệ hoàn thành (%)
A4: =COUNTIF($A$8:$A$707,"?*") -> 500 | B4: =COUNTIF($C$8:$C$707,"✅") -> 1 | C4: =COUNTIF($C$8:$C$707,"❌") -> 1 | D4: =IF(A4=0,0,B4/A4) -> 0.002
A5: Tiến độ | B5: =REPT("█",ROUND(D4*20,0))&REPT("░",20-ROUND(D4*20,0)) -> ░░░░░░░░░░░░░░░░░░░░ | C5: =IF(B4+C4=0,"Độ chính xác: –","Độ chính xác: "&TEXT(B4/(B4+C4),"0%")) -> Độ chính xác: 50% | D5: Không
D6: ▲ Hiện gợi ý (Có/Không)
A7: Ý nghĩa | B7: Ô người học nhập | C7: Kết quả | D7: Gợi ý | F7: norm có dấu | G7: norm không dấu
A8: =IF(Data_HSK1!E2="","",Data_HSK1!E2) -> yêu, yêu thích | B8: haha | C8: =IF(OR(A8="",TRIM(B8)=""),"",IF(OR(ISNUMBER(FIND("|"&F8&"|",Data_HSK1!G2)),AND(F8=G8,ISNUMBER(FIND("|"&G8&"|",Data_HSK1!H2)))),"✅","❌")) -> ❌ | D8: =IF(OR(A8="",$D$5<>"Có"),"",Data_HSK1!B2&" ("&Data_HSK1!C2&")") | F8: =IF(TRIM(B8)="","",SUBSTITUTE(SUBSTITUTE(SUBSTITUTE(SUBSTITUTE(SUBSTITUTE(SUBSTITUTE(SUBSTITUTE(SUBSTITUTE(SUBSTITUTE(SUBSTITUTE(SUBSTITUTE(SUBSTITUTE(SUBSTITUTE(SUBSTITUTE(SUBSTITUTE(SUBSTITUTE(LOWER(TRIM(B8))," ",""),"'",""),"’",""),"·",""),"/",""),"-",""),"(",""),")",""),"（",""),"）",""),"ü","v"),";","|"),"；","|"),",","|"),"，","|"),"、","|")) -> haha | G8: =SUBSTITUTE(SUBSTITUTE(SUBSTITUTE(SUBSTITUTE(SUBSTITUTE(SUBSTITUTE(SUBSTITUTE(SUBSTITUTE(SUBSTITUTE(SUBSTITUTE(SUBSTITUTE(SUBSTITUTE(SUBSTITUTE(SUBSTITUTE(SUBSTITUTE(SUBSTITUTE(SUBSTITUTE(SUBSTITUTE(SUBSTITUTE(SUBSTITUTE(SUBSTITUTE(SUBSTITUTE(SUBSTITUTE(SUBSTITUTE(F8,"ā","a"),"á","a"),"ǎ","a"),"à","a"),"ē","e"),"é","e"),"ě","e"),"è","e"),"ī","i"),"í","i"),"ǐ","i"),"ì","i"),"ō","o"),"ó","o"),"ǒ","o"),"ò","o"),"ū","u"),"ú","u"),"ǔ","u"),"ù","u"),"ǖ","v"),"ǘ","v"),"ǚ","v"),"ǜ","v") -> haha
A9: =IF(Data_HSK1!E3="","",Data_HSK1!E3) -> sở thích; ham thích | B9: 爱好 | C9: =IF(OR(A9="",TRIM(B9)=""),"",IF(OR(ISNUMBER(FIND("|"&F9&"|",Data_HSK1!G3)),AND(F9=G9,ISNUMBER(FIND("|"&G9&"|",Data_HSK1!H3)))),"✅","❌")) -> ✅ | D9: =IF(OR(A9="",$D$5<>"Có"),"",Data_HSK1!B3&" ("&Data_HSK1!C3&")") | F9: =IF(TRIM(B9)="","",SUBSTITUTE(SUBSTITUTE(SUBSTITUTE(SUBSTITUTE(SUBSTITUTE(SUBSTITUTE(SUBSTITUTE(SUBSTITUTE(SUBSTITUTE(SUBSTITUTE(SUBSTITUTE(SUBSTITUTE(SUBSTITUTE(SUBSTITUTE(SUBSTITUTE(SUBSTITUTE(LOWER(TRIM(B9))," ",""),"'",""),"’",""),"·",""),"/",""),"-",""),"(",""),")",""),"（",""),"）",""),"ü","v"),";","|"),"；","|"),",","|"),"，","|"),"、","|")) -> 爱好 | G9: =SUBSTITUTE(SUBSTITUTE(SUBSTITUTE(SUBSTITUTE(SUBSTITUTE(SUBSTITUTE(SUBSTITUTE(SUBSTITUTE(SUBSTITUTE(SUBSTITUTE(SUBSTITUTE(SUBSTITUTE(SUBSTITUTE(SUBSTITUTE(SUBSTITUTE(SUBSTITUTE(SUBSTITUTE(SUBSTITUTE(SUBSTITUTE(SUBSTITUTE(SUBSTITUTE(SUBSTITUTE(SUBSTITUTE(SUBSTITUTE(F9,"ā","a"),"á","a"),"ǎ","a"),"à","a"),"ē","e"),"é","e"),"ě","e"),"è","e"),"ī","i"),"í","i"),"ǐ","i"),"ì","i"),"ō","o"),"ó","o"),"ǒ","o"),"ò","o"),"ū","u"),"ú","u"),"ǔ","u"),"ù","u"),"ǖ","v"),"ǘ","v"),"ǚ","v"),"ǜ","v") -> 爱好
A10: =IF(Data_HSK1!E4="","",Data_HSK1!E4) -> số 8 (tám) | C10: =IF(OR(A10="",TRIM(B10)=""),"",IF(OR(ISNUMBER(FIND("|"&F10&"|",Data_HSK1!G4)),AND(F10=G10,ISNUMBER(FIND("|"&G10&"|",Data_HSK1!H4)))),"✅","❌")) | D10: =IF(OR(A10="",$D$5<>"Có"),"",Data_HSK1!B4&" ("&Data_HSK1!C4&")") | F10: =IF(TRIM(B10)="","",SUBSTITUTE(SUBSTITUTE(SUBSTITUTE(SUBSTITUTE(SUBSTITUTE(SUBSTITUTE(SUBSTITUTE(SUBSTITUTE(SUBSTITUTE(SUBSTITUTE(SUBSTITUTE(SUBSTITUTE(SUBSTITUTE(SUBSTITUTE(SUBSTITUTE(SUBSTITUTE(LOWER(TRIM(B10))," ",""),"'",""),"’",""),"·",""),"/",""),"-",""),"(",""),")",""),"（",""),"）",""),"ü","v"),";","|"),"；","|"),",","|"),"，","|"),"、","|")) | G10: =SUBSTITUTE(SUBSTITUTE(SUBSTITUTE(SUBSTITUTE(SUBSTITUTE(SUBSTITUTE(SUBSTITUTE(SUBSTITUTE(SUBSTITUTE(SUBSTITUTE(SUBSTITUTE(SUBSTITUTE(SUBSTITUTE(SUBSTITUTE(SUBSTITUTE(SUBSTITUTE(SUBSTITUTE(SUBSTITUTE(SUBSTITUTE(SUBSTITUTE(SUBSTITUTE(SUBSTITUTE(SUBSTITUTE(SUBSTITUTE(F10,"ā","a"),"á","a"),"ǎ","a"),"à","a"),"ē","e"),"é","e"),"ě","e"),"è","e"),"ī","i"),"í","i"),"ǐ","i"),"ì","i"),"ō","o"),"ó","o"),"ǒ","o"),"ò","o"),"ū","u"),"ú","u"),"ǔ","u"),"ù","u"),"ǖ","v"),"ǘ","v"),"ǚ","v"),"ǜ","v")
A11: =IF(Data_HSK1!E5="","",Data_HSK1!E5) -> bố | C11: =IF(OR(A11="",TRIM(B11)=""),"",IF(OR(ISNUMBER(FIND("|"&F11&"|",Data_HSK1!G5)),AND(F11=G11,ISNUMBER(FIND("|"&G11&"|",Data_HSK1!H5)))),"✅","❌")) | D11: =IF(OR(A11="",$D$5<>"Có"),"",Data_HSK1!B5&" ("&Data_HSK1!C5&")") | F11: =IF(TRIM(B11)="","",SUBSTITUTE(SUBSTITUTE(SUBSTITUTE(SUBSTITUTE(SUBSTITUTE(SUBSTITUTE(SUBSTITUTE(SUBSTITUTE(SUBSTITUTE(SUBSTITUTE(SUBSTITUTE(SUBSTITUTE(SUBSTITUTE(SUBSTITUTE(SUBSTITUTE(SUBSTITUTE(LOWER(TRIM(B11))," ",""),"'",""),"’",""),"·",""),"/",""),"-",""),"(",""),")",""),"（",""),"）",""),"ü","v"),";","|"),"；","|"),",","|"),"，","|"),"、","|")) | G11: =SUBSTITUTE(SUBSTITUTE(SUBSTITUTE(SUBSTITUTE(SUBSTITUTE(SUBSTITUTE(SUBSTITUTE(SUBSTITUTE(SUBSTITUTE(SUBSTITUTE(SUBSTITUTE(SUBSTITUTE(SUBSTITUTE(SUBSTITUTE(SUBSTITUTE(SUBSTITUTE(SUBSTITUTE(SUBSTITUTE(SUBSTITUTE(SUBSTITUTE(SUBSTITUTE(SUBSTITUTE(SUBSTITUTE(SUBSTITUTE(F11,"ā","a"),"á","a"),"ǎ","a"),"à","a"),"ē","e"),"é","e"),"ě","e"),"è","e"),"ī","i"),"í","i"),"ǐ","i"),"ì","i"),"ō","o"),"ó","o"),"ǒ","o"),"ò","o"),"ū","u"),"ú","u"),"ǔ","u"),"ù","u"),"ǖ","v"),"ǘ","v"),"ǚ","v"),"ǜ","v")
A12: =IF(Data_HSK1!E6="","",Data_HSK1!E6) -> nhé, nhỉ, đi (trợ từ cuối câu) | C12: =IF(OR(A12="",TRIM(B12)=""),"",IF(OR(ISNUMBER(FIND("|"&F12&"|",Data_HSK1!G6)),AND(F12=G12,ISNUMBER(FIND("|"&G12&"|",Data_HSK1!H6)))),"✅","❌")) | D12: =IF(OR(A12="",$D$5<>"Có"),"",Data_HSK1!B6&" ("&Data_HSK1!C6&")") | F12: =IF(TRIM(B12)="","",SUBSTITUTE(SUBSTITUTE(SUBSTITUTE(SUBSTITUTE(SUBSTITUTE(SUBSTITUTE(SUBSTITUTE(SUBSTITUTE(SUBSTITUTE(SUBSTITUTE(SUBSTITUTE(SUBSTITUTE(SUBSTITUTE(SUBSTITUTE(SUBSTITUTE(SUBSTITUTE(LOWER(TRIM(B12))," ",""),"'",""),"’",""),"·",""),"/",""),"-",""),"(",""),")",""),"（",""),"）",""),"ü","v"),";","|"),"；","|"),",","|"),"，","|"),"、","|")) | G12: =SUBSTITUTE(SUBSTITUTE(SUBSTITUTE(SUBSTITUTE(SUBSTITUTE(SUBSTITUTE(SUBSTITUTE(SUBSTITUTE(SUBSTITUTE(SUBSTITUTE(SUBSTITUTE(SUBSTITUTE(SUBSTITUTE(SUBSTITUTE(SUBSTITUTE(SUBSTITUTE(SUBSTITUTE(SUBSTITUTE(SUBSTITUTE(SUBSTITUTE(SUBSTITUTE(SUBSTITUTE(SUBSTITUTE(SUBSTITUTE(F12,"ā","a"),"á","a"),"ǎ","a"),"à","a"),"ē","e"),"é","e"),"ě","e"),"è","e"),"ī","i"),"í","i"),"ǐ","i"),"ì","i"),"ō","o"),"ó","o"),"ǒ","o"),"ò","o"),"ū","u"),"ú","u"),"ǔ","u"),"ù","u"),"ǖ","v"),"ǘ","v"),"ǚ","v"),"ǜ","v")
A13: =IF(Data_HSK1!E7="","",Data_HSK1!E7) -> trắng | C13: =IF(OR(A13="",TRIM(B13)=""),"",IF(OR(ISNUMBER(FIND("|"&F13&"|",Data_HSK1!G7)),AND(F13=G13,ISNUMBER(FIND("|"&G13&"|",Data_HSK1!H7)))),"✅","❌")) | D13: =IF(OR(A13="",$D$5<>"Có"),"",Data_HSK1!B7&" ("&Data_HSK1!C7&")") | F13: =IF(TRIM(B13)="","",SUBSTITUTE(SUBSTITUTE(SUBSTITUTE(SUBSTITUTE(SUBSTITUTE(SUBSTITUTE(SUBSTITUTE(SUBSTITUTE(SUBSTITUTE(SUBSTITUTE(SUBSTITUTE(SUBSTITUTE(SUBSTITUTE(SUBSTITUTE(SUBSTITUTE(SUBSTITUTE(LOWER(TRIM(B13))," ",""),"'",""),"’",""),"·",""),"/",""),"-",""),"(",""),")",""),"（",""),"）",""),"ü","v"),";","|"),"；","|"),",","|"),"，","|"),"、","|")) | G13: =SUBSTITUTE(SUBSTITUTE(SUBSTITUTE(SUBSTITUTE(SUBSTITUTE(SUBSTITUTE(SUBSTITUTE(SUBSTITUTE(SUBSTITUTE(SUBSTITUTE(SUBSTITUTE(SUBSTITUTE(SUBSTITUTE(SUBSTITUTE(SUBSTITUTE(SUBSTITUTE(SUBSTITUTE(SUBSTITUTE(SUBSTITUTE(SUBSTITUTE(SUBSTITUTE(SUBSTITUTE(SUBSTITUTE(SUBSTITUTE(F13,"ā","a"),"á","a"),"ǎ","a"),"à","a"),"ē","e"),"é","e"),"ě","e"),"è","e"),"ī","i"),"í","i"),"ǐ","i"),"ì","i"),"ō","o"),"ó","o"),"ǒ","o"),"ò","o"),"ū","u"),"ú","u"),"ǔ","u"),"ù","u"),"ǖ","v"),"ǘ","v"),"ǚ","v"),"ǜ","v")
A14: =IF(Data_HSK1!E8="","",Data_HSK1!E8) -> ban ngày | C14: =IF(OR(A14="",TRIM(B14)=""),"",IF(OR(ISNUMBER(FIND("|"&F14&"|",Data_HSK1!G8)),AND(F14=G14,ISNUMBER(FIND("|"&G14&"|",Data_HSK1!H8)))),"✅","❌")) | D14: =IF(OR(A14="",$D$5<>"Có"),"",Data_HSK1!B8&" ("&Data_HSK1!C8&")") | F14: =IF(TRIM(B14)="","",SUBSTITUTE(SUBSTITUTE(SUBSTITUTE(SUBSTITUTE(SUBSTITUTE(SUBSTITUTE(SUBSTITUTE(SUBSTITUTE(SUBSTITUTE(SUBSTITUTE(SUBSTITUTE(SUBSTITUTE(SUBSTITUTE(SUBSTITUTE(SUBSTITUTE(SUBSTITUTE(LOWER(TRIM(B14))," ",""),"'",""),"’",""),"·",""),"/",""),"-",""),"(",""),")",""),"（",""),"）",""),"ü","v"),";","|"),"；","|"),",","|"),"，","|"),"、","|")) | G14: =SUBSTITUTE(SUBSTITUTE(SUBSTITUTE(SUBSTITUTE(SUBSTITUTE(SUBSTITUTE(SUBSTITUTE(SUBSTITUTE(SUBSTITUTE(SUBSTITUTE(SUBSTITUTE(SUBSTITUTE(SUBSTITUTE(SUBSTITUTE(SUBSTITUTE(SUBSTITUTE(SUBSTITUTE(SUBSTITUTE(SUBSTITUTE(SUBSTITUTE(SUBSTITUTE(SUBSTITUTE(SUBSTITUTE(SUBSTITUTE(F14,"ā","a"),"á","a"),"ǎ","a"),"à","a"),"ē","e"),"é","e"),"ě","e"),"è","e"),"ī","i"),"í","i"),"ǐ","i"),"ì","i"),"ō","o"),"ó","o"),"ǒ","o"),"ò","o"),"ū","u"),"ú","u"),"ǔ","u"),"ù","u"),"ǖ","v"),"ǘ","v"),"ǚ","v"),"ǜ","v")
A15: =IF(Data_HSK1!E9="","",Data_HSK1!E9) -> trăm | C15: =IF(OR(A15="",TRIM(B15)=""),"",IF(OR(ISNUMBER(FIND("|"&F15&"|",Data_HSK1!G9)),AND(F15=G15,ISNUMBER(FIND("|"&G15&"|",Data_HSK1!H9)))),"✅","❌")) | D15: =IF(OR(A15="",$D$5<>"Có"),"",Data_HSK1!B9&" ("&Data_HSK1!C9&")") | F15: =IF(TRIM(B15)="","",SUBSTITUTE(SUBSTITUTE(SUBSTITUTE(SUBSTITUTE(SUBSTITUTE(SUBSTITUTE(SUBSTITUTE(SUBSTITUTE(SUBSTITUTE(SUBSTITUTE(SUBSTITUTE(SUBSTITUTE(SUBSTITUTE(SUBSTITUTE(SUBSTITUTE(SUBSTITUTE(LOWER(TRIM(B15))," ",""),"'",""),"’",""),"·",""),"/",""),"-",""),"(",""),")",""),"（",""),"）",""),"ü","v"),";","|"),"；","|"),",","|"),"，","|"),"、","|")) | G15: =SUBSTITUTE(SUBSTITUTE(SUBSTITUTE(SUBSTITUTE(SUBSTITUTE(SUBSTITUTE(SUBSTITUTE(SUBSTITUTE(SUBSTITUTE(SUBSTITUTE(SUBSTITUTE(SUBSTITUTE(SUBSTITUTE(SUBSTITUTE(SUBSTITUTE(SUBSTITUTE(SUBSTITUTE(SUBSTITUTE(SUBSTITUTE(SUBSTITUTE(SUBSTITUTE(SUBSTITUTE(SUBSTITUTE(SUBSTITUTE(F15,"ā","a"),"á","a"),"ǎ","a"),"à","a"),"ē","e"),"é","e"),"ě","e"),"è","e"),"ī","i"),"í","i"),"ǐ","i"),"ì","i"),"ō","o"),"ó","o"),"ǒ","o"),"ò","o"),"ū","u"),"ú","u"),"ǔ","u"),"ù","u"),"ǖ","v"),"ǘ","v"),"ǚ","v"),"ǜ","v")
A16: =IF(Data_HSK1!E10="","",Data_HSK1!E10) -> lớp học; ca (làm việc) | C16: =IF(OR(A16="",TRIM(B16)=""),"",IF(OR(ISNUMBER(FIND("|"&F16&"|",Data_HSK1!G10)),AND(F16=G16,ISNUMBER(FIND("|"&G16&"|",Data_HSK1!H10)))),"✅","❌")) | D16: =IF(OR(A16="",$D$5<>"Có"),"",Data_HSK1!B10&" ("&Data_HSK1!C10&")") | F16: =IF(TRIM(B16)="","",SUBSTITUTE(SUBSTITUTE(SUBSTITUTE(SUBSTITUTE(SUBSTITUTE(SUBSTITUTE(SUBSTITUTE(SUBSTITUTE(SUBSTITUTE(SUBSTITUTE(SUBSTITUTE(SUBSTITUTE(SUBSTITUTE(SUBSTITUTE(SUBSTITUTE(SUBSTITUTE(LOWER(TRIM(B16))," ",""),"'",""),"’",""),"·",""),"/",""),"-",""),"(",""),")",""),"（",""),"）",""),"ü","v"),";","|"),"；","|"),",","|"),"，","|"),"、","|")) | G16: =SUBSTITUTE(SUBSTITUTE(SUBSTITUTE(SUBSTITUTE(SUBSTITUTE(SUBSTITUTE(SUBSTITUTE(SUBSTITUTE(SUBSTITUTE(SUBSTITUTE(SUBSTITUTE(SUBSTITUTE(SUBSTITUTE(SUBSTITUTE(SUBSTITUTE(SUBSTITUTE(SUBSTITUTE(SUBSTITUTE(SUBSTITUTE(SUBSTITUTE(SUBSTITUTE(SUBSTITUTE(SUBSTITUTE(SUBSTITUTE(F16,"ā","a"),"á","a"),"ǎ","a"),"à","a"),"ē","e"),"é","e"),"ě","e"),"è","e"),"ī","i"),"í","i"),"ǐ","i"),"ì","i"),"ō","o"),"ó","o"),"ǒ","o"),"ò","o"),"ū","u"),"ú","u"),"ǔ","u"),"ù","u"),"ǖ","v"),"ǘ","v"),"ǚ","v"),"ǜ","v")
A17: =IF(Data_HSK1!E11="","",Data_HSK1!E11) -> một nửa | C17: =IF(OR(A17="",TRIM(B17)=""),"",IF(OR(ISNUMBER(FIND("|"&F17&"|",Data_HSK1!G11)),AND(F17=G17,ISNUMBER(FIND("|"&G17&"|",Data_HSK1!H11)))),"✅","❌")) | D17: =IF(OR(A17="",$D$5<>"Có"),"",Data_HSK1!B11&" ("&Data_HSK1!C11&")") | F17: =IF(TRIM(B17)="","",SUBSTITUTE(SUBSTITUTE(SUBSTITUTE(SUBSTITUTE(SUBSTITUTE(SUBSTITUTE(SUBSTITUTE(SUBSTITUTE(SUBSTITUTE(SUBSTITUTE(SUBSTITUTE(SUBSTITUTE(SUBSTITUTE(SUBSTITUTE(SUBSTITUTE(SUBSTITUTE(LOWER(TRIM(B17))," ",""),"'",""),"’",""),"·",""),"/",""),"-",""),"(",""),")",""),"（",""),"）",""),"ü","v"),";","|"),"；","|"),",","|"),"，","|"),"、","|")) | G17: =SUBSTITUTE(SUBSTITUTE(SUBSTITUTE(SUBSTITUTE(SUBSTITUTE(SUBSTITUTE(SUBSTITUTE(SUBSTITUTE(SUBSTITUTE(SUBSTITUTE(SUBSTITUTE(SUBSTITUTE(SUBSTITUTE(SUBSTITUTE(SUBSTITUTE(SUBSTITUTE(SUBSTITUTE(SUBSTITUTE(SUBSTITUTE(SUBSTITUTE(SUBSTITUTE(SUBSTITUTE(SUBSTITUTE(SUBSTITUTE(F17,"ā","a"),"á","a"),"ǎ","a"),"à","a"),"ē","e"),"é","e"),"ě","e"),"è","e"),"ī","i"),"í","i"),"ǐ","i"),"ì","i"),"ō","o"),"ó","o"),"ǒ","o"),"ò","o"),"ū","u"),"ú","u"),"ǔ","u"),"ù","u"),"ǖ","v"),"ǘ","v"),"ǚ","v"),"ǜ","v")
A18: =IF(Data_HSK1!E12="","",Data_HSK1!E12) -> nửa năm | C18: =IF(OR(A18="",TRIM(B18)=""),"",IF(OR(ISNUMBER(FIND("|"&F18&"|",Data_HSK1!G12)),AND(F18=G18,ISNUMBER(FIND("|"&G18&"|",Data_HSK1!H12)))),"✅","❌")) | D18: =IF(OR(A18="",$D$5<>"Có"),"",Data_HSK1!B12&" ("&Data_HSK1!C12&")") | F18: =IF(TRIM(B18)="","",SUBSTITUTE(SUBSTITUTE(SUBSTITUTE(SUBSTITUTE(SUBSTITUTE(SUBSTITUTE(SUBSTITUTE(SUBSTITUTE(SUBSTITUTE(SUBSTITUTE(SUBSTITUTE(SUBSTITUTE(SUBSTITUTE(SUBSTITUTE(SUBSTITUTE(SUBSTITUTE(LOWER(TRIM(B18))," ",""),"'",""),"’",""),"·",""),"/",""),"-",""),"(",""),")",""),"（",""),"）",""),"ü","v"),";","|"),"；","|"),",","|"),"，","|"),"、","|")) | G18: =SUBSTITUTE(SUBSTITUTE(SUBSTITUTE(SUBSTITUTE(SUBSTITUTE(SUBSTITUTE(SUBSTITUTE(SUBSTITUTE(SUBSTITUTE(SUBSTITUTE(SUBSTITUTE(SUBSTITUTE(SUBSTITUTE(SUBSTITUTE(SUBSTITUTE(SUBSTITUTE(SUBSTITUTE(SUBSTITUTE(SUBSTITUTE(SUBSTITUTE(SUBSTITUTE(SUBSTITUTE(SUBSTITUTE(SUBSTITUTE(F18,"ā","a"),"á","a"),"ǎ","a"),"à","a"),"ē","e"),"é","e"),"ě","e"),"è","e"),"ī","i"),"í","i"),"ǐ","i"),"ì","i"),"ō","o"),"ó","o"),"ǒ","o"),"ò","o"),"ū","u"),"ú","u"),"ǔ","u"),"ù","u"),"ǖ","v"),"ǘ","v"),"ǚ","v"),"ǜ","v")
A19: =IF(Data_HSK1!E13="","",Data_HSK1!E13) -> nửa ngày | C19: =IF(OR(A19="",TRIM(B19)=""),"",IF(OR(ISNUMBER(FIND("|"&F19&"|",Data_HSK1!G13)),AND(F19=G19,ISNUMBER(FIND("|"&G19&"|",Data_HSK1!H13)))),"✅","❌")) | D19: =IF(OR(A19="",$D$5<>"Có"),"",Data_HSK1!B13&" ("&Data_HSK1!C13&")") | F19: =IF(TRIM(B19)="","",SUBSTITUTE(SUBSTITUTE(SUBSTITUTE(SUBSTITUTE(SUBSTITUTE(SUBSTITUTE(SUBSTITUTE(SUBSTITUTE(SUBSTITUTE(SUBSTITUTE(SUBSTITUTE(SUBSTITUTE(SUBSTITUTE(SUBSTITUTE(SUBSTITUTE(SUBSTITUTE(LOWER(TRIM(B19))," ",""),"'",""),"’",""),"·",""),"/",""),"-",""),"(",""),")",""),"（",""),"）",""),"ü","v"),";","|"),"；","|"),",","|"),"，","|"),"、","|")) | G19: =SUBSTITUTE(SUBSTITUTE(SUBSTITUTE(SUBSTITUTE(SUBSTITUTE(SUBSTITUTE(SUBSTITUTE(SUBSTITUTE(SUBSTITUTE(SUBSTITUTE(SUBSTITUTE(SUBSTITUTE(SUBSTITUTE(SUBSTITUTE(SUBSTITUTE(SUBSTITUTE(SUBSTITUTE(SUBSTITUTE(SUBSTITUTE(SUBSTITUTE(SUBSTITUTE(SUBSTITUTE(SUBSTITUTE(SUBSTITUTE(F19,"ā","a"),"á","a"),"ǎ","a"),"à","a"),"ē","e"),"é","e"),"ě","e"),"è","e"),"ī","i"),"í","i"),"ǐ","i"),"ì","i"),"ō","o"),"ó","o"),"ǒ","o"),"ò","o"),"ū","u"),"ú","u"),"ǔ","u"),"ù","u"),"ǖ","v"),"ǘ","v"),"ǚ","v"),"ǜ","v")
A20: =IF(Data_HSK1!E14="","",Data_HSK1!E14) -> giúp (1 chữ) | C20: =IF(OR(A20="",TRIM(B20)=""),"",IF(OR(ISNUMBER(FIND("|"&F20&"|",Data_HSK1!G14)),AND(F20=G20,ISNUMBER(FIND("|"&G20&"|",Data_HSK1!H14)))),"✅","❌")) | D20: =IF(OR(A20="",$D$5<>"Có"),"",Data_HSK1!B14&" ("&Data_HSK1!C14&")") | F20: =IF(TRIM(B20)="","",SUBSTITUTE(SUBSTITUTE(SUBSTITUTE(SUBSTITUTE(SUBSTITUTE(SUBSTITUTE(SUBSTITUTE(SUBSTITUTE(SUBSTITUTE(SUBSTITUTE(SUBSTITUTE(SUBSTITUTE(SUBSTITUTE(SUBSTITUTE(SUBSTITUTE(SUBSTITUTE(LOWER(TRIM(B20))," ",""),"'",""),"’",""),"·",""),"/",""),"-",""),"(",""),")",""),"（",""),"）",""),"ü","v"),";","|"),"；","|"),",","|"),"，","|"),"、","|")) | G20: =SUBSTITUTE(SUBSTITUTE(SUBSTITUTE(SUBSTITUTE(SUBSTITUTE(SUBSTITUTE(SUBSTITUTE(SUBSTITUTE(SUBSTITUTE(SUBSTITUTE(SUBSTITUTE(SUBSTITUTE(SUBSTITUTE(SUBSTITUTE(SUBSTITUTE(SUBSTITUTE(SUBSTITUTE(SUBSTITUTE(SUBSTITUTE(SUBSTITUTE(SUBSTITUTE(SUBSTITUTE(SUBSTITUTE(SUBSTITUTE(F20,"ā","a"),"á","a"),"ǎ","a"),"à","a"),"ē","e"),"é","e"),"ě","e"),"è","e"),"ī","i"),"í","i"),"ǐ","i"),"ì","i"),"ō","o"),"ó","o"),"ǒ","o"),"ò","o"),"ū","u"),"ú","u"),"ǔ","u"),"ù","u"),"ǖ","v"),"ǘ","v"),"ǚ","v"),"ǜ","v")
A21: =IF(Data_HSK1!E15="","",Data_HSK1!E15) -> giúp đỡ, giúp một tay | C21: =IF(OR(A21="",TRIM(B21)=""),"",IF(OR(ISNUMBER(FIND("|"&F21&"|",Data_HSK1!G15)),AND(F21=G21,ISNUMBER(FIND("|"&G21&"|",Data_HSK1!H15)))),"✅","❌")) | D21: =IF(OR(A21="",$D$5<>"Có"),"",Data_HSK1!B15&" ("&Data_HSK1!C15&")") | F21: =IF(TRIM(B21)="","",SUBSTITUTE(SUBSTITUTE(SUBSTITUTE(SUBSTITUTE(SUBSTITUTE(SUBSTITUTE(SUBSTITUTE(SUBSTITUTE(SUBSTITUTE(SUBSTITUTE(SUBSTITUTE(SUBSTITUTE(SUBSTITUTE(SUBSTITUTE(SUBSTITUTE(SUBSTITUTE(LOWER(TRIM(B21))," ",""),"'",""),"’",""),"·",""),"/",""),"-",""),"(",""),")",""),"（",""),"）",""),"ü","v"),";","|"),"；","|"),",","|"),"，","|"),"、","|")) | G21: =SUBSTITUTE(SUBSTITUTE(SUBSTITUTE(SUBSTITUTE(SUBSTITUTE(SUBSTITUTE(SUBSTITUTE(SUBSTITUTE(SUBSTITUTE(SUBSTITUTE(SUBSTITUTE(SUBSTITUTE(SUBSTITUTE(SUBSTITUTE(SUBSTITUTE(SUBSTITUTE(SUBSTITUTE(SUBSTITUTE(SUBSTITUTE(SUBSTITUTE(SUBSTITUTE(SUBSTITUTE(SUBSTITUTE(SUBSTITUTE(F21,"ā","a"),"á","a"),"ǎ","a"),"à","a"),"ē","e"),"é","e"),"ě","e"),"è","e"),"ī","i"),"í","i"),"ǐ","i"),"ì","i"),"ō","o"),"ó","o"),"ǒ","o"),"ò","o"),"ū","u"),"ú","u"),"ǔ","u"),"ù","u"),"ǖ","v"),"ǘ","v"),"ǚ","v"),"ǜ","v")
... A707: =IF(Data_HSK1!E701="","",Data_HSK1!E701) | C707: =IF(OR(A707="",TRIM(B707)=""),"",IF(OR(ISNUMBER(FIND("|"&F707&"|",Data_HSK1!G701)),AND(F707=G707,ISNUMBER(FIND("|"&G707&"|",Data_HSK1!H701)))),"✅","❌")) | D707: =IF(OR(A707="",$D$5<>"Có"),"",Data_HSK1!B701&" ("&Data_HSK1!C701&")") | F707: =IF(TRIM(B707)="","",SUBSTITUTE(SUBSTITUTE(SUBSTITUTE(SUBSTITUTE(SUBSTITUTE(SUBSTITUTE(SUBSTITUTE(SUBSTITUTE(SUBSTITUTE(SUBSTITUTE(SUBSTITUTE(SUBSTITUTE(SUBSTITUTE(SUBSTITUTE(SUBSTITUTE(SUBSTITUTE(LOWER(TRIM(B707))," ",""),"'",""),"’",""),"·",""),"/",""),"-",""),"(",""),")",""),"（",""),"）",""),"ü","v"),";","|"),"；","|"),",","|"),"，","|"),"、","|")) | G707: =SUBSTITUTE(SUBSTITUTE(SUBSTITUTE(SUBSTITUTE(SUBSTITUTE(SUBSTITUTE(SUBSTITUTE(SUBSTITUTE(SUBSTITUTE(SUBSTITUTE(SUBSTITUTE(SUBSTITUTE(SUBSTITUTE(SUBSTITUTE(SUBSTITUTE(SUBSTITUTE(SUBSTITUTE(SUBSTITUTE(SUBSTITUTE(SUBSTITUTE(SUBSTITUTE(SUBSTITUTE(SUBSTITUTE(SUBSTITUTE(F707,"ā","a"),"á","a"),"ǎ","a"),"à","a"),"ē","e"),"é","e"),"ě","e"),"è","e"),"ī","i"),"í","i"),"ǐ","i"),"ì","i"),"ō","o"),"ó","o"),"ǒ","o"),"ò","o"),"ū","u"),"ú","u"),"ǔ","u"),"ù","u"),"ǖ","v"),"ǘ","v"),"ǚ","v"),"ǜ","v")

Sheet Từ vựng HSK5
A1: LUYỆN TẬP TỪ VỰNG HSK 5 (HSK 3.0 — 1300 từ)
A2: Nhập chữ Hán giản thể hoặc Pinyin (có/không dấu thanh) vào cột B — chỉ cần sửa các ô màu vàng.
A3: Tổng số câu | B3: Số câu đã làm đúng ✅ | C3: Số câu sai ❌ | D3: Tỷ lệ hoàn thành (%)
A4: =COUNTIF($A$8:$A$1507,"?*") -> 1300 | B4: =COUNTIF($C$8:$C$1507,"✅") -> 0 | C4: =COUNTIF($C$8:$C$1507,"❌") -> 0 | D4: =IF(A4=0,0,B4/A4) -> 0
A5: Tiến độ | B5: =REPT("█",ROUND(D4*20,0))&REPT("░",20-ROUND(D4*20,0)) -> ░░░░░░░░░░░░░░░░░░░░ | C5: =IF(B4+C4=0,"Độ chính xác: –","Độ chính xác: "&TEXT(B4/(B4+C4),"0%")) -> Độ chính xác: – | D5: Không
D6: ▲ Hiện gợi ý (Có/Không)
A7: Ý nghĩa | B7: Ô người học nhập | C7: Kết quả | D7: Gợi ý | F7: norm có dấu | G7: norm không dấu
A8: =IF(Data_HSK5!E2="","",Data_HSK5!E2) -> than ôi | C8: =IF(OR(A8="",TRIM(B8)=""),"",IF(OR(ISNUMBER(FIND("|"&F8&"|",Data_HSK5!G2)),AND(F8=G8,ISNUMBER(FIND("|"&G8&"|",Data_HSK5!H2)))),"✅","❌")) | D8: =IF(OR(A8="",$D$5<>"Có"),"",Data_HSK5!B2&" ("&Data_HSK5!C2&")") | F8: =IF(TRIM(B8)="","",SUBSTITUTE(SUBSTITUTE(SUBSTITUTE(SUBSTITUTE(SUBSTITUTE(SUBSTITUTE(SUBSTITUTE(SUBSTITUTE(SUBSTITUTE(SUBSTITUTE(SUBSTITUTE(SUBSTITUTE(SUBSTITUTE(SUBSTITUTE(SUBSTITUTE(SUBSTITUTE(LOWER(TRIM(B8))," ",""),"'",""),"’",""),"·",""),"/",""),"-",""),"(",""),")",""),"（",""),"）",""),"ü","v"),";","|"),"；","|"),",","|"),"，","|"),"、","|")) | G8: =SUBSTITUTE(SUBSTITUTE(SUBSTITUTE(SUBSTITUTE(SUBSTITUTE(SUBSTITUTE(SUBSTITUTE(SUBSTITUTE(SUBSTITUTE(SUBSTITUTE(SUBSTITUTE(SUBSTITUTE(SUBSTITUTE(SUBSTITUTE(SUBSTITUTE(SUBSTITUTE(SUBSTITUTE(SUBSTITUTE(SUBSTITUTE(SUBSTITUTE(SUBSTITUTE(SUBSTITUTE(SUBSTITUTE(SUBSTITUTE(F8,"ā","a"),"á","a"),"ǎ","a"),"à","a"),"ē","e"),"é","e"),"ě","e"),"è","e"),"ī","i"),"í","i"),"ǐ","i"),"ì","i"),"ō","o"),"ó","o"),"ǒ","o"),"ò","o"),"ū","u"),"ú","u"),"ǔ","u"),"ù","u"),"ǖ","v"),"ǘ","v"),"ǚ","v"),"ǜ","v")
A9: =IF(Data_HSK5!E3="","",Data_HSK5!E3) -> lòng nhân ái | C9: =IF(OR(A9="",TRIM(B9)=""),"",IF(OR(ISNUMBER(FIND("|"&F9&"|",Data_HSK5!G3)),AND(F9=G9,ISNUMBER(FIND("|"&G9&"|",Data_HSK5!H3)))),"✅","❌")) | D9: =IF(OR(A9="",$D$5<>"Có"),"",Data_HSK5!B3&" ("&Data_HSK5!C3&")") | F9: =IF(TRIM(B9)="","",SUBSTITUTE(SUBSTITUTE(SUBSTITUTE(SUBSTITUTE(SUBSTITUTE(SUBSTITUTE(SUBSTITUTE(SUBSTITUTE(SUBSTITUTE(SUBSTITUTE(SUBSTITUTE(SUBSTITUTE(SUBSTITUTE(SUBSTITUTE(SUBSTITUTE(SUBSTITUTE(LOWER(TRIM(B9))," ",""),"'",""),"’",""),"·",""),"/",""),"-",""),"(",""),")",""),"（",""),"）",""),"ü","v"),";","|"),"；","|"),",","|"),"，","|"),"、","|")) | G9: =SUBSTITUTE(SUBSTITUTE(SUBSTITUTE(SUBSTITUTE(SUBSTITUTE(SUBSTITUTE(SUBSTITUTE(SUBSTITUTE(SUBSTITUTE(SUBSTITUTE(SUBSTITUTE(SUBSTITUTE(SUBSTITUTE(SUBSTITUTE(SUBSTITUTE(SUBSTITUTE(SUBSTITUTE(SUBSTITUTE(SUBSTITUTE(SUBSTITUTE(SUBSTITUTE(SUBSTITUTE(SUBSTITUTE(SUBSTITUTE(F9,"ā","a"),"á","a"),"ǎ","a"),"à","a"),"ē","e"),"é","e"),"ě","e"),"è","e"),"ī","i"),"í","i"),"ǐ","i"),"ì","i"),"ō","o"),"ó","o"),"ǒ","o"),"ò","o"),"ū","u"),"ú","u"),"ǔ","u"),"ù","u"),"ǖ","v"),"ǘ","v"),"ǚ","v"),"ǜ","v")
A10: =IF(Data_HSK5!E4="","",Data_HSK5!E4) -> an ủi | C10: =IF(OR(A10="",TRIM(B10)=""),"",IF(OR(ISNUMBER(FIND("|"&F10&"|",Data_HSK5!G4)),AND(F10=G10,ISNUMBER(FIND("|"&G10&"|",Data_HSK5!H4)))),"✅","❌")) | D10: =IF(OR(A10="",$D$5<>"Có"),"",Data_HSK5!B4&" ("&Data_HSK5!C4&")") | F10: =IF(TRIM(B10)="","",SUBSTITUTE(SUBSTITUTE(SUBSTITUTE(SUBSTITUTE(SUBSTITUTE(SUBSTITUTE(SUBSTITUTE(SUBSTITUTE(SUBSTITUTE(SUBSTITUTE(SUBSTITUTE(SUBSTITUTE(SUBSTITUTE(SUBSTITUTE(SUBSTITUTE(SUBSTITUTE(LOWER(TRIM(B10))," ",""),"'",""),"’",""),"·",""),"/",""),"-",""),"(",""),")",""),"（",""),"）",""),"ü","v"),";","|"),"；","|"),",","|"),"，","|"),"、","|")) | G10: =SUBSTITUTE(SUBSTITUTE(SUBSTITUTE(SUBSTITUTE(SUBSTITUTE(SUBSTITUTE(SUBSTITUTE(SUBSTITUTE(SUBSTITUTE(SUBSTITUTE(SUBSTITUTE(SUBSTITUTE(SUBSTITUTE(SUBSTITUTE(SUBSTITUTE(SUBSTITUTE(SUBSTITUTE(SUBSTITUTE(SUBSTITUTE(SUBSTITUTE(SUBSTITUTE(SUBSTITUTE(SUBSTITUTE(SUBSTITUTE(F10,"ā","a"),"á","a"),"ǎ","a"),"à","a"),"ē","e"),"é","e"),"ě","e"),"è","e"),"ī","i"),"í","i"),"ǐ","i"),"ì","i"),"ō","o"),"ó","o"),"ǒ","o"),"ò","o"),"ū","u"),"ú","u"),"ǔ","u"),"ù","u"),"ǖ","v"),"ǘ","v"),"ǚ","v"),"ǜ","v")
A11: =IF(Data_HSK5!E5="","",Data_HSK5!E5) -> bờ | C11: =IF(OR(A11="",TRIM(B11)=""),"",IF(OR(ISNUMBER(FIND("|"&F11&"|",Data_HSK5!G5)),AND(F11=G11,ISNUMBER(FIND("|"&G11&"|",Data_HSK5!H5)))),"✅","❌")) | D11: =IF(OR(A11="",$D$5<>"Có"),"",Data_HSK5!B5&" ("&Data_HSK5!C5&")") | F11: =IF(TRIM(B11)="","",SUBSTITUTE(SUBSTITUTE(SUBSTITUTE(SUBSTITUTE(SUBSTITUTE(SUBSTITUTE(SUBSTITUTE(SUBSTITUTE(SUBSTITUTE(SUBSTITUTE(SUBSTITUTE(SUBSTITUTE(SUBSTITUTE(SUBSTITUTE(SUBSTITUTE(SUBSTITUTE(LOWER(TRIM(B11))," ",""),"'",""),"’",""),"·",""),"/",""),"-",""),"(",""),")",""),"（",""),"）",""),"ü","v"),";","|"),"；","|"),",","|"),"，","|"),"、","|")) | G11: =SUBSTITUTE(SUBSTITUTE(SUBSTITUTE(SUBSTITUTE(SUBSTITUTE(SUBSTITUTE(SUBSTITUTE(SUBSTITUTE(SUBSTITUTE(SUBSTITUTE(SUBSTITUTE(SUBSTITUTE(SUBSTITUTE(SUBSTITUTE(SUBSTITUTE(SUBSTITUTE(SUBSTITUTE(SUBSTITUTE(SUBSTITUTE(SUBSTITUTE(SUBSTITUTE(SUBSTITUTE(SUBSTITUTE(SUBSTITUTE(F11,"ā","a"),"á","a"),"ǎ","a"),"à","a"),"ē","e"),"é","e"),"ě","e"),"è","e"),"ī","i"),"í","i"),"ǐ","i"),"ì","i"),"ō","o"),"ó","o"),"ǒ","o"),"ò","o"),"ū","u"),"ú","u"),"ǔ","u"),"ù","u"),"ǖ","v"),"ǘ","v"),"ǚ","v"),"ǜ","v")
A12: =IF(Data_HSK5!E6="","",Data_HSK5!E6) -> thức khuya | C12: =IF(OR(A12="",TRIM(B12)=""),"",IF(OR(ISNUMBER(FIND("|"&F12&"|",Data_HSK5!G6)),AND(F12=G12,ISNUMBER(FIND("|"&G12&"|",Data_HSK5!H6)))),"✅","❌")) | D12: =IF(OR(A12="",$D$5<>"Có"),"",Data_HSK5!B6&" ("&Data_HSK5!C6&")") | F12: =IF(TRIM(B12)="","",SUBSTITUTE(SUBSTITUTE(SUBSTITUTE(SUBSTITUTE(SUBSTITUTE(SUBSTITUTE(SUBSTITUTE(SUBSTITUTE(SUBSTITUTE(SUBSTITUTE(SUBSTITUTE(SUBSTITUTE(SUBSTITUTE(SUBSTITUTE(SUBSTITUTE(SUBSTITUTE(LOWER(TRIM(B12))," ",""),"'",""),"’",""),"·",""),"/",""),"-",""),"(",""),")",""),"（",""),"）",""),"ü","v"),";","|"),"；","|"),",","|"),"，","|"),"、","|")) | G12: =SUBSTITUTE(SUBSTITUTE(SUBSTITUTE(SUBSTITUTE(SUBSTITUTE(SUBSTITUTE(SUBSTITUTE(SUBSTITUTE(SUBSTITUTE(SUBSTITUTE(SUBSTITUTE(SUBSTITUTE(SUBSTITUTE(SUBSTITUTE(SUBSTITUTE(SUBSTITUTE(SUBSTITUTE(SUBSTITUTE(SUBSTITUTE(SUBSTITUTE(SUBSTITUTE(SUBSTITUTE(SUBSTITUTE(SUBSTITUTE(F12,"ā","a"),"á","a"),"ǎ","a"),"à","a"),"ē","e"),"é","e"),"ě","e"),"è","e"),"ī","i"),"í","i"),"ǐ","i"),"ì","i"),"ō","o"),"ó","o"),"ǒ","o"),"ò","o"),"ū","u"),"ú","u"),"ǔ","u"),"ù","u"),"ǖ","v"),"ǘ","v"),"ǚ","v"),"ǜ","v")
A13: =IF(Data_HSK5!E7="","",Data_HSK5!E7) -> bao gồm | C13: =IF(OR(A13="",TRIM(B13)=""),"",IF(OR(ISNUMBER(FIND("|"&F13&"|",Data_HSK5!G7)),AND(F13=G13,ISNUMBER(FIND("|"&G13&"|",Data_HSK5!H7)))),"✅","❌")) | D13: =IF(OR(A13="",$D$5<>"Có"),"",Data_HSK5!B7&" ("&Data_HSK5!C7&")") | F13: =IF(TRIM(B13)="","",SUBSTITUTE(SUBSTITUTE(SUBSTITUTE(SUBSTITUTE(SUBSTITUTE(SUBSTITUTE(SUBSTITUTE(SUBSTITUTE(SUBSTITUTE(SUBSTITUTE(SUBSTITUTE(SUBSTITUTE(SUBSTITUTE(SUBSTITUTE(SUBSTITUTE(SUBSTITUTE(LOWER(TRIM(B13))," ",""),"'",""),"’",""),"·",""),"/",""),"-",""),"(",""),")",""),"（",""),"）",""),"ü","v"),";","|"),"；","|"),",","|"),"，","|"),"、","|")) | G13: =SUBSTITUTE(SUBSTITUTE(SUBSTITUTE(SUBSTITUTE(SUBSTITUTE(SUBSTITUTE(SUBSTITUTE(SUBSTITUTE(SUBSTITUTE(SUBSTITUTE(SUBSTITUTE(SUBSTITUTE(SUBSTITUTE(SUBSTITUTE(SUBSTITUTE(SUBSTITUTE(SUBSTITUTE(SUBSTITUTE(SUBSTITUTE(SUBSTITUTE(SUBSTITUTE(SUBSTITUTE(SUBSTITUTE(SUBSTITUTE(F13,"ā","a"),"á","a"),"ǎ","a"),"à","a"),"ē","e"),"é","e"),"ě","e"),"è","e"),"ī","i"),"í","i"),"ǐ","i"),"ì","i"),"ō","o"),"ó","o"),"ǒ","o"),"ò","o"),"ū","u"),"ú","u"),"ǔ","u"),"ù","u"),"ǖ","v"),"ǘ","v"),"ǚ","v"),"ǜ","v")
A14: =IF(Data_HSK5!E8="","",Data_HSK5!E8) -> quý báu | C14: =IF(OR(A14="",TRIM(B14)=""),"",IF(OR(ISNUMBER(FIND("|"&F14&"|",Data_HSK5!G8)),AND(F14=G14,ISNUMBER(FIND("|"&G14&"|",Data_HSK5!H8)))),"✅","❌")) | D14: =IF(OR(A14="",$D$5<>"Có"),"",Data_HSK5!B8&" ("&Data_HSK5!C8&")") | F14: =IF(TRIM(B14)="","",SUBSTITUTE(SUBSTITUTE(SUBSTITUTE(SUBSTITUTE(SUBSTITUTE(SUBSTITUTE(SUBSTITUTE(SUBSTITUTE(SUBSTITUTE(SUBSTITUTE(SUBSTITUTE(SUBSTITUTE(SUBSTITUTE(SUBSTITUTE(SUBSTITUTE(SUBSTITUTE(LOWER(TRIM(B14))," ",""),"'",""),"’",""),"·",""),"/",""),"-",""),"(",""),")",""),"（",""),"）",""),"ü","v"),";","|"),"；","|"),",","|"),"，","|"),"、","|")) | G14: =SUBSTITUTE(SUBSTITUTE(SUBSTITUTE(SUBSTITUTE(SUBSTITUTE(SUBSTITUTE(SUBSTITUTE(SUBSTITUTE(SUBSTITUTE(SUBSTITUTE(SUBSTITUTE(SUBSTITUTE(SUBSTITUTE(SUBSTITUTE(SUBSTITUTE(SUBSTITUTE(SUBSTITUTE(SUBSTITUTE(SUBSTITUTE(SUBSTITUTE(SUBSTITUTE(SUBSTITUTE(SUBSTITUTE(SUBSTITUTE(F14,"ā","a"),"á","a"),"ǎ","a"),"à","a"),"ē","e"),"é","e"),"ě","e"),"è","e"),"ī","i"),"í","i"),"ǐ","i"),"ì","i"),"ō","o"),"ó","o"),"ǒ","o"),"ò","o"),"ū","u"),"ú","u"),"ǔ","u"),"ù","u"),"ǖ","v"),"ǘ","v"),"ǚ","v"),"ǜ","v")
A15: =IF(Data_HSK5!E9="","",Data_HSK5!E9) -> bảo tồn | C15: =IF(OR(A15="",TRIM(B15)=""),"",IF(OR(ISNUMBER(FIND("|"&F15&"|",Data_HSK5!G9)),AND(F15=G15,ISNUMBER(FIND("|"&G15&"|",Data_HSK5!H9)))),"✅","❌")) | D15: =IF(OR(A15="",$D$5<>"Có"),"",Data_HSK5!B9&" ("&Data_HSK5!C9&")") | F15: =IF(TRIM(B15)="","",SUBSTITUTE(SUBSTITUTE(SUBSTITUTE(SUBSTITUTE(SUBSTITUTE(SUBSTITUTE(SUBSTITUTE(SUBSTITUTE(SUBSTITUTE(SUBSTITUTE(SUBSTITUTE(SUBSTITUTE(SUBSTITUTE(SUBSTITUTE(SUBSTITUTE(SUBSTITUTE(LOWER(TRIM(B15))," ",""),"'",""),"’",""),"·",""),"/",""),"-",""),"(",""),")",""),"（",""),"）",""),"ü","v"),";","|"),"；","|"),",","|"),"，","|"),"、","|")) | G15: =SUBSTITUTE(SUBSTITUTE(SUBSTITUTE(SUBSTITUTE(SUBSTITUTE(SUBSTITUTE(SUBSTITUTE(SUBSTITUTE(SUBSTITUTE(SUBSTITUTE(SUBSTITUTE(SUBSTITUTE(SUBSTITUTE(SUBSTITUTE(SUBSTITUTE(SUBSTITUTE(SUBSTITUTE(SUBSTITUTE(SUBSTITUTE(SUBSTITUTE(SUBSTITUTE(SUBSTITUTE(SUBSTITUTE(SUBSTITUTE(F15,"ā","a"),"á","a"),"ǎ","a"),"à","a"),"ē","e"),"é","e"),"ě","e"),"è","e"),"ī","i"),"í","i"),"ǐ","i"),"ì","i"),"ō","o"),"ó","o"),"ǒ","o"),"ò","o"),"ū","u"),"ú","u"),"ǔ","u"),"ù","u"),"ǖ","v"),"ǘ","v"),"ǚ","v"),"ǜ","v")
A16: =IF(Data_HSK5!E10="","",Data_HSK5!E10) -> giữ lại | C16: =IF(OR(A16="",TRIM(B16)=""),"",IF(OR(ISNUMBER(FIND("|"&F16&"|",Data_HSK5!G10)),AND(F16=G16,ISNUMBER(FIND("|"&G16&"|",Data_HSK5!H10)))),"✅","❌")) | D16: =IF(OR(A16="",$D$5<>"Có"),"",Data_HSK5!B10&" ("&Data_HSK5!C10&")") | F16: =IF(TRIM(B16)="","",SUBSTITUTE(SUBSTITUTE(SUBSTITUTE(SUBSTITUTE(SUBSTITUTE(SUBSTITUTE(SUBSTITUTE(SUBSTITUTE(SUBSTITUTE(SUBSTITUTE(SUBSTITUTE(SUBSTITUTE(SUBSTITUTE(SUBSTITUTE(SUBSTITUTE(SUBSTITUTE(LOWER(TRIM(B16))," ",""),"'",""),"’",""),"·",""),"/",""),"-",""),"(",""),")",""),"（",""),"）",""),"ü","v"),";","|"),"；","|"),",","|"),"，","|"),"、","|")) | G16: =SUBSTITUTE(SUBSTITUTE(SUBSTITUTE(SUBSTITUTE(SUBSTITUTE(SUBSTITUTE(SUBSTITUTE(SUBSTITUTE(SUBSTITUTE(SUBSTITUTE(SUBSTITUTE(SUBSTITUTE(SUBSTITUTE(SUBSTITUTE(SUBSTITUTE(SUBSTITUTE(SUBSTITUTE(SUBSTITUTE(SUBSTITUTE(SUBSTITUTE(SUBSTITUTE(SUBSTITUTE(SUBSTITUTE(SUBSTITUTE(F16,"ā","a"),"á","a"),"ǎ","a"),"à","a"),"ē","e"),"é","e"),"ě","e"),"è","e"),"ī","i"),"í","i"),"ǐ","i"),"ì","i"),"ō","o"),"ó","o"),"ǒ","o"),"ò","o"),"ū","u"),"ú","u"),"ǔ","u"),"ù","u"),"ǖ","v"),"ǘ","v"),"ǚ","v"),"ǜ","v")
A17: =IF(Data_HSK5!E11="","",Data_HSK5!E11) -> báo danh | C17: =IF(OR(A17="",TRIM(B17)=""),"",IF(OR(ISNUMBER(FIND("|"&F17&"|",Data_HSK5!G11)),AND(F17=G17,ISNUMBER(FIND("|"&G17&"|",Data_HSK5!H11)))),"✅","❌")) | D17: =IF(OR(A17="",$D$5<>"Có"),"",Data_HSK5!B11&" ("&Data_HSK5!C11&")") | F17: =IF(TRIM(B17)="","",SUBSTITUTE(SUBSTITUTE(SUBSTITUTE(SUBSTITUTE(SUBSTITUTE(SUBSTITUTE(SUBSTITUTE(SUBSTITUTE(SUBSTITUTE(SUBSTITUTE(SUBSTITUTE(SUBSTITUTE(SUBSTITUTE(SUBSTITUTE(SUBSTITUTE(SUBSTITUTE(LOWER(TRIM(B17))," ",""),"'",""),"’",""),"·",""),"/",""),"-",""),"(",""),")",""),"（",""),"）",""),"ü","v"),";","|"),"；","|"),",","|"),"，","|"),"、","|")) | G17: =SUBSTITUTE(SUBSTITUTE(SUBSTITUTE(SUBSTITUTE(SUBSTITUTE(SUBSTITUTE(SUBSTITUTE(SUBSTITUTE(SUBSTITUTE(SUBSTITUTE(SUBSTITUTE(SUBSTITUTE(SUBSTITUTE(SUBSTITUTE(SUBSTITUTE(SUBSTITUTE(SUBSTITUTE(SUBSTITUTE(SUBSTITUTE(SUBSTITUTE(SUBSTITUTE(SUBSTITUTE(SUBSTITUTE(SUBSTITUTE(F17,"ā","a"),"á","a"),"ǎ","a"),"à","a"),"ē","e"),"é","e"),"ě","e"),"è","e"),"ī","i"),"í","i"),"ǐ","i"),"ì","i"),"ō","o"),"ó","o"),"ǒ","o"),"ò","o"),"ū","u"),"ú","u"),"ǔ","u"),"ù","u"),"ǖ","v"),"ǘ","v"),"ǚ","v"),"ǜ","v")
A18: =IF(Data_HSK5!E12="","",Data_HSK5!E12) -> báo cáo | C18: =IF(OR(A18="",TRIM(B18)=""),"",IF(OR(ISNUMBER(FIND("|"&F18&"|",Data_HSK5!G12)),AND(F18=G18,ISNUMBER(FIND("|"&G18&"|",Data_HSK5!H12)))),"✅","❌")) | D18: =IF(OR(A18="",$D$5<>"Có"),"",Data_HSK5!B12&" ("&Data_HSK5!C12&")") | F18: =IF(TRIM(B18)="","",SUBSTITUTE(SUBSTITUTE(SUBSTITUTE(SUBSTITUTE(SUBSTITUTE(SUBSTITUTE(SUBSTITUTE(SUBSTITUTE(SUBSTITUTE(SUBSTITUTE(SUBSTITUTE(SUBSTITUTE(SUBSTITUTE(SUBSTITUTE(SUBSTITUTE(SUBSTITUTE(LOWER(TRIM(B18))," ",""),"'",""),"’",""),"·",""),"/",""),"-",""),"(",""),")",""),"（",""),"）",""),"ü","v"),";","|"),"；","|"),",","|"),"，","|"),"、","|")) | G18: =SUBSTITUTE(SUBSTITUTE(SUBSTITUTE(SUBSTITUTE(SUBSTITUTE(SUBSTITUTE(SUBSTITUTE(SUBSTITUTE(SUBSTITUTE(SUBSTITUTE(SUBSTITUTE(SUBSTITUTE(SUBSTITUTE(SUBSTITUTE(SUBSTITUTE(SUBSTITUTE(SUBSTITUTE(SUBSTITUTE(SUBSTITUTE(SUBSTITUTE(SUBSTITUTE(SUBSTITUTE(SUBSTITUTE(SUBSTITUTE(F18,"ā","a"),"á","a"),"ǎ","a"),"à","a"),"ē","e"),"é","e"),"ě","e"),"è","e"),"ī","i"),"í","i"),"ǐ","i"),"ì","i"),"ō","o"),"ó","o"),"ǒ","o"),"ò","o"),"ū","u"),"ú","u"),"ǔ","u"),"ù","u"),"ǖ","v"),"ǘ","v"),"ǚ","v"),"ǜ","v")
A19: =IF(Data_HSK5!E13="","",Data_HSK5!E13) -> bi quan | C19: =IF(OR(A19="",TRIM(B19)=""),"",IF(OR(ISNUMBER(FIND("|"&F19&"|",Data_HSK5!G13)),AND(F19=G19,ISNUMBER(FIND("|"&G19&"|",Data_HSK5!H13)))),"✅","❌")) | D19: =IF(OR(A19="",$D$5<>"Có"),"",Data_HSK5!B13&" ("&Data_HSK5!C13&")") | F19: =IF(TRIM(B19)="","",SUBSTITUTE(SUBSTITUTE(SUBSTITUTE(SUBSTITUTE(SUBSTITUTE(SUBSTITUTE(SUBSTITUTE(SUBSTITUTE(SUBSTITUTE(SUBSTITUTE(SUBSTITUTE(SUBSTITUTE(SUBSTITUTE(SUBSTITUTE(SUBSTITUTE(SUBSTITUTE(LOWER(TRIM(B19))," ",""),"'",""),"’",""),"·",""),"/",""),"-",""),"(",""),")",""),"（",""),"）",""),"ü","v"),";","|"),"；","|"),",","|"),"，","|"),"、","|")) | G19: =SUBSTITUTE(SUBSTITUTE(SUBSTITUTE(SUBSTITUTE(SUBSTITUTE(SUBSTITUTE(SUBSTITUTE(SUBSTITUTE(SUBSTITUTE(SUBSTITUTE(SUBSTITUTE(SUBSTITUTE(SUBSTITUTE(SUBSTITUTE(SUBSTITUTE(SUBSTITUTE(SUBSTITUTE(SUBSTITUTE(SUBSTITUTE(SUBSTITUTE(SUBSTITUTE(SUBSTITUTE(SUBSTITUTE(SUBSTITUTE(F19,"ā","a"),"á","a"),"ǎ","a"),"à","a"),"ē","e"),"é","e"),"ě","e"),"è","e"),"ī","i"),"í","i"),"ǐ","i"),"ì","i"),"ō","o"),"ó","o"),"ǒ","o"),"ò","o"),"ū","u"),"ú","u"),"ǔ","u"),"ù","u"),"ǖ","v"),"ǘ","v"),"ǚ","v"),"ǜ","v")
... A1507: =IF(Data_HSK5!E1501="","",Data_HSK5!E1501) | C1507: =IF(OR(A1507="",TRIM(B1507)=""),"",IF(OR(ISNUMBER(FIND("|"&F1507&"|",Data_HSK5!G1501)),AND(F1507=G1507,ISNUMBER(FIND("|"&G1507&"|",Data_HSK5!H1501)))),"✅","❌")) | D1507: =IF(OR(A1507="",$D$5<>"Có"),"",Data_HSK5!B1501&" ("&Data_HSK5!C1501&")") | F1507: =IF(TRIM(B1507)="","",SUBSTITUTE(SUBSTITUTE(SUBSTITUTE(SUBSTITUTE(SUBSTITUTE(SUBSTITUTE(SUBSTITUTE(SUBSTITUTE(SUBSTITUTE(SUBSTITUTE(SUBSTITUTE(SUBSTITUTE(SUBSTITUTE(SUBSTITUTE(SUBSTITUTE(SUBSTITUTE(LOWER(TRIM(B1507))," ",""),"'",""),"’",""),"·",""),"/",""),"-",""),"(",""),")",""),"（",""),"）",""),"ü","v"),";","|"),"；","|"),",","|"),"，","|"),"、","|")) | G1507: =SUBSTITUTE(SUBSTITUTE(SUBSTITUTE(SUBSTITUTE(SUBSTITUTE(SUBSTITUTE(SUBSTITUTE(SUBSTITUTE(SUBSTITUTE(SUBSTITUTE(SUBSTITUTE(SUBSTITUTE(SUBSTITUTE(SUBSTITUTE(SUBSTITUTE(SUBSTITUTE(SUBSTITUTE(SUBSTITUTE(SUBSTITUTE(SUBSTITUTE(SUBSTITUTE(SUBSTITUTE(SUBSTITUTE(SUBSTITUTE(F1507,"ā","a"),"á","a"),"ǎ","a"),"à","a"),"ē","e"),"é","e"),"ě","e"),"è","e"),"ī","i"),"í","i"),"ǐ","i"),"ì","i"),"ō","o"),"ó","o"),"ǒ","o"),"ò","o"),"ū","u"),"ú","u"),"ǔ","u"),"ù","u"),"ǖ","v"),"ǘ","v"),"ǚ","v"),"ǜ","v")

Sheet Data_HSK1
A1: STT | B1: Chữ Hán | C1: Pinyin | D1: Từ loại | E1: Nghĩa tiếng Việt | F1: Đáp án chấp nhận (cách nhau bằng dấu ;) — có thể thêm tùy ý | G1: Chuẩn hóa có dấu (tự động) | H1: Chuẩn hóa không dấu (tự động)
A2: 1 | B2: 爱 | C2: ài | D2: động từ | E2: yêu, yêu thích | F2: 爱; ài; ai | G2: =IF(AND(B2="",C2="",F2=""),"","|"&SUBSTITUTE(SUBSTITUTE(SUBSTITUTE(SUBSTITUTE(SUBSTITUTE(SUBSTITUTE(SUBSTITUTE(SUBSTITUTE(SUBSTITUTE(SUBSTITUTE(SUBSTITUTE(SUBSTITUTE(SUBSTITUTE(SUBSTITUTE(SUBSTITUTE(SUBSTITUTE(LOWER(B2&";"&C2&";"&F2)," ",""),"'",""),"’",""),"·",""),"/",""),"-",""),"(",""),")",""),"（",""),"）",""),"ü","v"),";","|"),"；","|"),",","|"),"，","|"),"、","|")&"|") -> |爱|ài|爱|ài|ai| | H2: =SUBSTITUTE(SUBSTITUTE(SUBSTITUTE(SUBSTITUTE(SUBSTITUTE(SUBSTITUTE(SUBSTITUTE(SUBSTITUTE(SUBSTITUTE(SUBSTITUTE(SUBSTITUTE(SUBSTITUTE(SUBSTITUTE(SUBSTITUTE(SUBSTITUTE(SUBSTITUTE(SUBSTITUTE(SUBSTITUTE(SUBSTITUTE(SUBSTITUTE(SUBSTITUTE(SUBSTITUTE(SUBSTITUTE(SUBSTITUTE(G2,"ā","a"),"á","a"),"ǎ","a"),"à","a"),"ē","e"),"é","e"),"ě","e"),"è","e"),"ī","i"),"í","i"),"ǐ","i"),"ì","i"),"ō","o"),"ó","o"),"ǒ","o"),"ò","o"),"ū","u"),"ú","u"),"ǔ","u"),"ù","u"),"ǖ","v"),"ǘ","v"),"ǚ","v"),"ǜ","v") -> |爱|ai|爱|ai|ai|
A3: 2 | B3: 爱好 | C3: àihào | D3: động từ, danh từ | E3: sở thích; ham thích | F3: 爱好; àihào; aihao | G3: =IF(AND(B3="",C3="",F3=""),"","|"&SUBSTITUTE(SUBSTITUTE(SUBSTITUTE(SUBSTITUTE(SUBSTITUTE(SUBSTITUTE(SUBSTITUTE(SUBSTITUTE(SUBSTITUTE(SUBSTITUTE(SUBSTITUTE(SUBSTITUTE(SUBSTITUTE(SUBSTITUTE(SUBSTITUTE(SUBSTITUTE(LOWER(B3&";"&C3&";"&F3)," ",""),"'",""),"’",""),"·",""),"/",""),"-",""),"(",""),")",""),"（",""),"）",""),"ü","v"),";","|"),"；","|"),",","|"),"，","|"),"、","|")&"|") -> |爱好|àihào|爱好|àihào|aihao| | H3: =SUBSTITUTE(SUBSTITUTE(SUBSTITUTE(SUBSTITUTE(SUBSTITUTE(SUBSTITUTE(SUBSTITUTE(SUBSTITUTE(SUBSTITUTE(SUBSTITUTE(SUBSTITUTE(SUBSTITUTE(SUBSTITUTE(SUBSTITUTE(SUBSTITUTE(SUBSTITUTE(SUBSTITUTE(SUBSTITUTE(SUBSTITUTE(SUBSTITUTE(SUBSTITUTE(SUBSTITUTE(SUBSTITUTE(SUBSTITUTE(G3,"ā","a"),"á","a"),"ǎ","a"),"à","a"),"ē","e"),"é","e"),"ě","e"),"è","e"),"ī","i"),"í","i"),"ǐ","i"),"ì","i"),"ō","o"),"ó","o"),"ǒ","o"),"ò","o"),"ū","u"),"ú","u"),"ǔ","u"),"ù","u"),"ǖ","v"),"ǘ","v"),"ǚ","v"),"ǜ","v") -> |爱好|aihao|爱好|aihao|aihao|
A4: 3 | B4: 八 | C4: bā | D4: số từ | E4: số 8 (tám) | F4: 八; bā; 8; ba | G4: =IF(AND(B4="",C4="",F4=""),"","|"&SUBSTITUTE(SUBSTITUTE(SUBSTITUTE(SUBSTITUTE(SUBSTITUTE(SUBSTITUTE(SUBSTITUTE(SUBSTITUTE(SUBSTITUTE(SUBSTITUTE(SUBSTITUTE(SUBSTITUTE(SUBSTITUTE(SUBSTITUTE(SUBSTITUTE(SUBSTITUTE(LOWER(B4&";"&C4&";"&F4)," ",""),"'",""),"’",""),"·",""),"/",""),"-",""),"(",""),")",""),"（",""),"）",""),"ü","v"),";","|"),"；","|"),",","|"),"，","|"),"、","|")&"|") -> |八|bā|八|bā|8|ba| | H4: =SUBSTITUTE(SUBSTITUTE(SUBSTITUTE(SUBSTITUTE(SUBSTITUTE(SUBSTITUTE(SUBSTITUTE(SUBSTITUTE(SUBSTITUTE(SUBSTITUTE(SUBSTITUTE(SUBSTITUTE(SUBSTITUTE(SUBSTITUTE(SUBSTITUTE(SUBSTITUTE(SUBSTITUTE(SUBSTITUTE(SUBSTITUTE(SUBSTITUTE(SUBSTITUTE(SUBSTITUTE(SUBSTITUTE(SUBSTITUTE(G4,"ā","a"),"á","a"),"ǎ","a"),"à","a"),"ē","e"),"é","e"),"ě","e"),"è","e"),"ī","i"),"í","i"),"ǐ","i"),"ì","i"),"ō","o"),"ó","o"),"ǒ","o"),"ò","o"),"ū","u"),"ú","u"),"ǔ","u"),"ù","u"),"ǖ","v"),"ǘ","v"),"ǚ","v"),"ǜ","v") -> |八|ba|八|ba|8|ba|
A5: 4 | B5: 爸爸 | C5: bàba | D5: danh từ | E5: bố | F5: 爸爸; bàba; 爸; bà; 父亲; fùqīn; 老爸; lǎobà; baba; ba; fuqin; laoba | G5: =IF(AND(B5="",C5="",F5=""),"","|"&SUBSTITUTE(SUBSTITUTE(SUBSTITUTE(SUBSTITUTE(SUBSTITUTE(SUBSTITUTE(SUBSTITUTE(SUBSTITUTE(SUBSTITUTE(SUBSTITUTE(SUBSTITUTE(SUBSTITUTE(SUBSTITUTE(SUBSTITUTE(SUBSTITUTE(SUBSTITUTE(LOWER(B5&";"&C5&";"&F5)," ",""),"'",""),"’",""),"·",""),"/",""),"-",""),"(",""),")",""),"（",""),"）",""),"ü","v"),";","|"),"；","|"),",","|"),"，","|"),"、","|")&"|") -> |爸爸|bàba|爸爸|bàba|爸|bà|父亲|fùqīn|老爸|lǎobà|baba|ba|fuqin|laoba| | H5: =SUBSTITUTE(SUBSTITUTE(SUBSTITUTE(SUBSTITUTE(SUBSTITUTE(SUBSTITUTE(SUBSTITUTE(SUBSTITUTE(SUBSTITUTE(SUBSTITUTE(SUBSTITUTE(SUBSTITUTE(SUBSTITUTE(SUBSTITUTE(SUBSTITUTE(SUBSTITUTE(SUBSTITUTE(SUBSTITUTE(SUBSTITUTE(SUBSTITUTE(SUBSTITUTE(SUBSTITUTE(SUBSTITUTE(SUBSTITUTE(G5,"ā","a"),"á","a"),"ǎ","a"),"à","a"),"ē","e"),"é","e"),"ě","e"),"è","e"),"ī","i"),"í","i"),"ǐ","i"),"ì","i"),"ō","o"),"ó","o"),"ǒ","o"),"ò","o"),"ū","u"),"ú","u"),"ǔ","u"),"ù","u"),"ǖ","v"),"ǘ","v"),"ǚ","v"),"ǜ","v") -> |爸爸|baba|爸爸|baba|爸|ba|父亲|fuqin|老爸|laoba|baba|ba|fuqin|laoba|
A6: 5 | B6: 吧 | C6: ba | D6: trợ từ | E6: nhé, nhỉ, đi (trợ từ cuối câu) | F6: 吧; ba | G6: =IF(AND(B6="",C6="",F6=""),"","|"&SUBSTITUTE(SUBSTITUTE(SUBSTITUTE(SUBSTITUTE(SUBSTITUTE(SUBSTITUTE(SUBSTITUTE(SUBSTITUTE(SUBSTITUTE(SUBSTITUTE(SUBSTITUTE(SUBSTITUTE(SUBSTITUTE(SUBSTITUTE(SUBSTITUTE(SUBSTITUTE(LOWER(B6&";"&C6&";"&F6)," ",""),"'",""),"’",""),"·",""),"/",""),"-",""),"(",""),")",""),"（",""),"）",""),"ü","v"),";","|"),"；","|"),",","|"),"，","|"),"、","|")&"|") -> |吧|ba|吧|ba| | H6: =SUBSTITUTE(SUBSTITUTE(SUBSTITUTE(SUBSTITUTE(SUBSTITUTE(SUBSTITUTE(SUBSTITUTE(SUBSTITUTE(SUBSTITUTE(SUBSTITUTE(SUBSTITUTE(SUBSTITUTE(SUBSTITUTE(SUBSTITUTE(SUBSTITUTE(SUBSTITUTE(SUBSTITUTE(SUBSTITUTE(SUBSTITUTE(SUBSTITUTE(SUBSTITUTE(SUBSTITUTE(SUBSTITUTE(SUBSTITUTE(G6,"ā","a"),"á","a"),"ǎ","a"),"à","a"),"ē","e"),"é","e"),"ě","e"),"è","e"),"ī","i"),"í","i"),"ǐ","i"),"ì","i"),"ō","o"),"ó","o"),"ǒ","o"),"ò","o"),"ū","u"),"ú","u"),"ǔ","u"),"ù","u"),"ǖ","v"),"ǘ","v"),"ǚ","v"),"ǜ","v") -> |吧|ba|吧|ba|
A7: 6 | B7: 白 | C7: bái | D7: tính từ | E7: trắng | F7: 白; bái; 白色; báisè; bai; baise | G7: =IF(AND(B7="",C7="",F7=""),"","|"&SUBSTITUTE(SUBSTITUTE(SUBSTITUTE(SUBSTITUTE(SUBSTITUTE(SUBSTITUTE(SUBSTITUTE(SUBSTITUTE(SUBSTITUTE(SUBSTITUTE(SUBSTITUTE(SUBSTITUTE(SUBSTITUTE(SUBSTITUTE(SUBSTITUTE(SUBSTITUTE(LOWER(B7&";"&C7&";"&F7)," ",""),"'",""),"’",""),"·",""),"/",""),"-",""),"(",""),")",""),"（",""),"）",""),"ü","v"),";","|"),"；","|"),",","|"),"，","|"),"、","|")&"|") -> |白|bái|白|bái|白色|báisè|bai|baise| | H7: =SUBSTITUTE(SUBSTITUTE(SUBSTITUTE(SUBSTITUTE(SUBSTITUTE(SUBSTITUTE(SUBSTITUTE(SUBSTITUTE(SUBSTITUTE(SUBSTITUTE(SUBSTITUTE(SUBSTITUTE(SUBSTITUTE(SUBSTITUTE(SUBSTITUTE(SUBSTITUTE(SUBSTITUTE(SUBSTITUTE(SUBSTITUTE(SUBSTITUTE(SUBSTITUTE(SUBSTITUTE(SUBSTITUTE(SUBSTITUTE(G7,"ā","a"),"á","a"),"ǎ","a"),"à","a"),"ē","e"),"é","e"),"ě","e"),"è","e"),"ī","i"),"í","i"),"ǐ","i"),"ì","i"),"ō","o"),"ó","o"),"ǒ","o"),"ò","o"),"ū","u"),"ú","u"),"ǔ","u"),"ù","u"),"ǖ","v"),"ǘ","v"),"ǚ","v"),"ǜ","v") -> |白|bai|白|bai|白色|baise|bai|baise|
A8: 7 | B8: 白天 | C8: báitiān | D8: danh từ | E8: ban ngày | F8: 白天; báitiān; baitian | G8: =IF(AND(B8="",C8="",F8=""),"","|"&SUBSTITUTE(SUBSTITUTE(SUBSTITUTE(SUBSTITUTE(SUBSTITUTE(SUBSTITUTE(SUBSTITUTE(SUBSTITUTE(SUBSTITUTE(SUBSTITUTE(SUBSTITUTE(SUBSTITUTE(SUBSTITUTE(SUBSTITUTE(SUBSTITUTE(SUBSTITUTE(LOWER(B8&";"&C8&";"&F8)," ",""),"'",""),"’",""),"·",""),"/",""),"-",""),"(",""),")",""),"（",""),"）",""),"ü","v"),";","|"),"；","|"),",","|"),"，","|"),"、","|")&"|") -> |白天|báitiān|白天|báitiān|baitian| | H8: =SUBSTITUTE(SUBSTITUTE(SUBSTITUTE(SUBSTITUTE(SUBSTITUTE(SUBSTITUTE(SUBSTITUTE(SUBSTITUTE(SUBSTITUTE(SUBSTITUTE(SUBSTITUTE(SUBSTITUTE(SUBSTITUTE(SUBSTITUTE(SUBSTITUTE(SUBSTITUTE(SUBSTITUTE(SUBSTITUTE(SUBSTITUTE(SUBSTITUTE(SUBSTITUTE(SUBSTITUTE(SUBSTITUTE(SUBSTITUTE(G8,"ā","a"),"á","a"),"ǎ","a"),"à","a"),"ē","e"),"é","e"),"ě","e"),"è","e"),"ī","i"),"í","i"),"ǐ","i"),"ì","i"),"ō","o"),"ó","o"),"ǒ","o"),"ò","o"),"ū","u"),"ú","u"),"ǔ","u"),"ù","u"),"ǖ","v"),"ǘ","v"),"ǚ","v"),"ǜ","v") -> |白天|baitian|白天|baitian|baitian|
A9: 8 | B9: 百 | C9: bǎi | D9: số từ | E9: trăm | F9: 百; bǎi; 100; 一百; yìbǎi; bai; yibai | G9: =IF(AND(B9="",C9="",F9=""),"","|"&SUBSTITUTE(SUBSTITUTE(SUBSTITUTE(SUBSTITUTE(SUBSTITUTE(SUBSTITUTE(SUBSTITUTE(SUBSTITUTE(SUBSTITUTE(SUBSTITUTE(SUBSTITUTE(SUBSTITUTE(SUBSTITUTE(SUBSTITUTE(SUBSTITUTE(SUBSTITUTE(LOWER(B9&";"&C9&";"&F9)," ",""),"'",""),"’",""),"·",""),"/",""),"-",""),"(",""),")",""),"（",""),"）",""),"ü","v"),";","|"),"；","|"),",","|"),"，","|"),"、","|")&"|") -> |百|bǎi|百|bǎi|100|一百|yìbǎi|bai|yibai| | H9: =SUBSTITUTE(SUBSTITUTE(SUBSTITUTE(SUBSTITUTE(SUBSTITUTE(SUBSTITUTE(SUBSTITUTE(SUBSTITUTE(SUBSTITUTE(SUBSTITUTE(SUBSTITUTE(SUBSTITUTE(SUBSTITUTE(SUBSTITUTE(SUBSTITUTE(SUBSTITUTE(SUBSTITUTE(SUBSTITUTE(SUBSTITUTE(SUBSTITUTE(SUBSTITUTE(SUBSTITUTE(SUBSTITUTE(SUBSTITUTE(G9,"ā","a"),"á","a"),"ǎ","a"),"à","a"),"ē","e"),"é","e"),"ě","e"),"è","e"),"ī","i"),"í","i"),"ǐ","i"),"ì","i"),"ō","o"),"ó","o"),"ǒ","o"),"ò","o"),"ū","u"),"ú","u"),"ǔ","u"),"ù","u"),"ǖ","v"),"ǘ","v"),"ǚ","v"),"ǜ","v") -> |百|bai|百|bai|100|一百|yibai|bai|yibai|
A10: 9 | B10: 班 | C10: bān | D10: danh từ, lượng từ | E10: lớp học; ca (làm việc) | F10: 班; bān; ban | G10: =IF(AND(B10="",C10="",F10=""),"","|"&SUBSTITUTE(SUBSTITUTE(SUBSTITUTE(SUBSTITUTE(SUBSTITUTE(SUBSTITUTE(SUBSTITUTE(SUBSTITUTE(SUBSTITUTE(SUBSTITUTE(SUBSTITUTE(SUBSTITUTE(SUBSTITUTE(SUBSTITUTE(SUBSTITUTE(SUBSTITUTE(LOWER(B10&";"&C10&";"&F10)," ",""),"'",""),"’",""),"·",""),"/",""),"-",""),"(",""),")",""),"（",""),"）",""),"ü","v"),";","|"),"；","|"),",","|"),"，","|"),"、","|")&"|") -> |班|bān|班|bān|ban| | H10: =SUBSTITUTE(SUBSTITUTE(SUBSTITUTE(SUBSTITUTE(SUBSTITUTE(SUBSTITUTE(SUBSTITUTE(SUBSTITUTE(SUBSTITUTE(SUBSTITUTE(SUBSTITUTE(SUBSTITUTE(SUBSTITUTE(SUBSTITUTE(SUBSTITUTE(SUBSTITUTE(SUBSTITUTE(SUBSTITUTE(SUBSTITUTE(SUBSTITUTE(SUBSTITUTE(SUBSTITUTE(SUBSTITUTE(SUBSTITUTE(G10,"ā","a"),"á","a"),"ǎ","a"),"à","a"),"ē","e"),"é","e"),"ě","e"),"è","e"),"ī","i"),"í","i"),"ǐ","i"),"ì","i"),"ō","o"),"ó","o"),"ǒ","o"),"ò","o"),"ū","u"),"ú","u"),"ǔ","u"),"ù","u"),"ǖ","v"),"ǘ","v"),"ǚ","v"),"ǜ","v") -> |班|ban|班|ban|ban|
A11: 10 | B11: 半 | C11: bàn | D11: số từ | E11: một nửa | F11: 半; bàn; 一半; yíbàn; ban; yiban | G11: =IF(AND(B11="",C11="",F11=""),"","|"&SUBSTITUTE(SUBSTITUTE(SUBSTITUTE(SUBSTITUTE(SUBSTITUTE(SUBSTITUTE(SUBSTITUTE(SUBSTITUTE(SUBSTITUTE(SUBSTITUTE(SUBSTITUTE(SUBSTITUTE(SUBSTITUTE(SUBSTITUTE(SUBSTITUTE(SUBSTITUTE(LOWER(B11&";"&C11&";"&F11)," ",""),"'",""),"’",""),"·",""),"/",""),"-",""),"(",""),")",""),"（",""),"）",""),"ü","v"),";","|"),"；","|"),",","|"),"，","|"),"、","|")&"|") -> |半|bàn|半|bàn|一半|yíbàn|ban|yiban| | H11: =SUBSTITUTE(SUBSTITUTE(SUBSTITUTE(SUBSTITUTE(SUBSTITUTE(SUBSTITUTE(SUBSTITUTE(SUBSTITUTE(SUBSTITUTE(SUBSTITUTE(SUBSTITUTE(SUBSTITUTE(SUBSTITUTE(SUBSTITUTE(SUBSTITUTE(SUBSTITUTE(SUBSTITUTE(SUBSTITUTE(SUBSTITUTE(SUBSTITUTE(SUBSTITUTE(SUBSTITUTE(SUBSTITUTE(SUBSTITUTE(G11,"ā","a"),"á","a"),"ǎ","a"),"à","a"),"ē","e"),"é","e"),"ě","e"),"è","e"),"ī","i"),"í","i"),"ǐ","i"),"ì","i"),"ō","o"),"ó","o"),"ǒ","o"),"ò","o"),"ū","u"),"ú","u"),"ǔ","u"),"ù","u"),"ǖ","v"),"ǘ","v"),"ǚ","v"),"ǜ","v") -> |半|ban|半|ban|一半|yiban|ban|yiban|
A12: 11 | B12: 半年 | C12: bàn nián | D12: cụm từ | E12: nửa năm | F12: 半年; bàn nián; ban nian | G12: =IF(AND(B12="",C12="",F12=""),"","|"&SUBSTITUTE(SUBSTITUTE(SUBSTITUTE(SUBSTITUTE(SUBSTITUTE(SUBSTITUTE(SUBSTITUTE(SUBSTITUTE(SUBSTITUTE(SUBSTITUTE(SUBSTITUTE(SUBSTITUTE(SUBSTITUTE(SUBSTITUTE(SUBSTITUTE(SUBSTITUTE(LOWER(B12&";"&C12&";"&F12)," ",""),"'",""),"’",""),"·",""),"/",""),"-",""),"(",""),")",""),"（",""),"）",""),"ü","v"),";","|"),"；","|"),",","|"),"，","|"),"、","|")&"|") -> |半年|bànnián|半年|bànnián|bannian| | H12: =SUBSTITUTE(SUBSTITUTE(SUBSTITUTE(SUBSTITUTE(SUBSTITUTE(SUBSTITUTE(SUBSTITUTE(SUBSTITUTE(SUBSTITUTE(SUBSTITUTE(SUBSTITUTE(SUBSTITUTE(SUBSTITUTE(SUBSTITUTE(SUBSTITUTE(SUBSTITUTE(SUBSTITUTE(SUBSTITUTE(SUBSTITUTE(SUBSTITUTE(SUBSTITUTE(SUBSTITUTE(SUBSTITUTE(SUBSTITUTE(G12,"ā","a"),"á","a"),"ǎ","a"),"à","a"),"ē","e"),"é","e"),"ě","e"),"è","e"),"ī","i"),"í","i"),"ǐ","i"),"ì","i"),"ō","o"),"ó","o"),"ǒ","o"),"ò","o"),"ū","u"),"ú","u"),"ǔ","u"),"ù","u"),"ǖ","v"),"ǘ","v"),"ǚ","v"),"ǜ","v") -> |半年|bannian|半年|bannian|bannian|
A13: 12 | B13: 半天 | C13: bàntiān | D13: cụm từ | E13: nửa ngày | F13: 半天; bàntiān; bantian | G13: =IF(AND(B13="",C13="",F13=""),"","|"&SUBSTITUTE(SUBSTITUTE(SUBSTITUTE(SUBSTITUTE(SUBSTITUTE(SUBSTITUTE(SUBSTITUTE(SUBSTITUTE(SUBSTITUTE(SUBSTITUTE(SUBSTITUTE(SUBSTITUTE(SUBSTITUTE(SUBSTITUTE(SUBSTITUTE(SUBSTITUTE(LOWER(B13&";"&C13&";"&F13)," ",""),"'",""),"’",""),"·",""),"/",""),"-",""),"(",""),")",""),"（",""),"）",""),"ü","v"),";","|"),"；","|"),",","|"),"，","|"),"、","|")&"|") -> |半天|bàntiān|半天|bàntiān|bantian| | H13: =SUBSTITUTE(SUBSTITUTE(SUBSTITUTE(SUBSTITUTE(SUBSTITUTE(SUBSTITUTE(SUBSTITUTE(SUBSTITUTE(SUBSTITUTE(SUBSTITUTE(SUBSTITUTE(SUBSTITUTE(SUBSTITUTE(SUBSTITUTE(SUBSTITUTE(SUBSTITUTE(SUBSTITUTE(SUBSTITUTE(SUBSTITUTE(SUBSTITUTE(SUBSTITUTE(SUBSTITUTE(SUBSTITUTE(SUBSTITUTE(G13,"ā","a"),"á","a"),"ǎ","a"),"à","a"),"ē","e"),"é","e"),"ě","e"),"è","e"),"ī","i"),"í","i"),"ǐ","i"),"ì","i"),"ō","o"),"ó","o"),"ǒ","o"),"ò","o"),"ū","u"),"ú","u"),"ǔ","u"),"ù","u"),"ǖ","v"),"ǘ","v"),"ǚ","v"),"ǜ","v") -> |半天|bantian|半天|bantian|bantian|
... A501: 500 | B501: 做 | C501: zuò | D501: động từ | E501: làm, chế tạo | F501: 做; zuò; 干; gàn; zuo; gan | G501: =IF(AND(B501="",C501="",F501=""),"","|"&SUBSTITUTE(SUBSTITUTE(SUBSTITUTE(SUBSTITUTE(SUBSTITUTE(SUBSTITUTE(SUBSTITUTE(SUBSTITUTE(SUBSTITUTE(SUBSTITUTE(SUBSTITUTE(SUBSTITUTE(SUBSTITUTE(SUBSTITUTE(SUBSTITUTE(SUBSTITUTE(LOWER(B501&";"&C501&";"&F501)," ",""),"'",""),"’",""),"·",""),"/",""),"-",""),"(",""),")",""),"（",""),"）",""),"ü","v"),";","|"),"；","|"),",","|"),"，","|"),"、","|")&"|") -> |做|zuò|做|zuò|干|gàn|zuo|gan| | H501: =SUBSTITUTE(SUBSTITUTE(SUBSTITUTE(SUBSTITUTE(SUBSTITUTE(SUBSTITUTE(SUBSTITUTE(SUBSTITUTE(SUBSTITUTE(SUBSTITUTE(SUBSTITUTE(SUBSTITUTE(SUBSTITUTE(SUBSTITUTE(SUBSTITUTE(SUBSTITUTE(SUBSTITUTE(SUBSTITUTE(SUBSTITUTE(SUBSTITUTE(SUBSTITUTE(SUBSTITUTE(SUBSTITUTE(SUBSTITUTE(G501,"ā","a"),"á","a"),"ǎ","a"),"à","a"),"ē","e"),"é","e"),"ě","e"),"è","e"),"ī","i"),"í","i"),"ǐ","i"),"ì","i"),"ō","o"),"ó","o"),"ǒ","o"),"ò","o"),"ū","u"),"ú","u"),"ǔ","u"),"ù","u"),"ǖ","v"),"ǘ","v"),"ǚ","v"),"ǜ","v") -> |做|zuo|做|zuo|干|gan|zuo|gan|
G502: =IF(AND(B502="",C502="",F502=""),"","|"&SUBSTITUTE(SUBSTITUTE(SUBSTITUTE(SUBSTITUTE(SUBSTITUTE(SUBSTITUTE(SUBSTITUTE(SUBSTITUTE(SUBSTITUTE(SUBSTITUTE(SUBSTITUTE(SUBSTITUTE(SUBSTITUTE(SUBSTITUTE(SUBSTITUTE(SUBSTITUTE(LOWER(B502&";"&C502&";"&F502)," ",""),"'",""),"’",""),"·",""),"/",""),"-",""),"(",""),")",""),"（",""),"）",""),"ü","v"),";","|"),"；","|"),",","|"),"，","|"),"、","|")&"|") | H502: =SUBSTITUTE(SUBSTITUTE(SUBSTITUTE(SUBSTITUTE(SUBSTITUTE(SUBSTITUTE(SUBSTITUTE(SUBSTITUTE(SUBSTITUTE(SUBSTITUTE(SUBSTITUTE(SUBSTITUTE(SUBSTITUTE(SUBSTITUTE(SUBSTITUTE(SUBSTITUTE(SUBSTITUTE(SUBSTITUTE(SUBSTITUTE(SUBSTITUTE(SUBSTITUTE(SUBSTITUTE(SUBSTITUTE(SUBSTITUTE(G502,"ā","a"),"á","a"),"ǎ","a"),"à","a"),"ē","e"),"é","e"),"ě","e"),"è","e"),"ī","i"),"í","i"),"ǐ","i"),"ì","i"),"ō","o"),"ó","o"),"ǒ","o"),"ò","o"),"ū","u"),"ú","u"),"ǔ","u"),"ù","u"),"ǖ","v"),"ǘ","v"),"ǚ","v"),"ǜ","v")
G503: =IF(AND(B503="",C503="",F503=""),"","|"&SUBSTITUTE(SUBSTITUTE(SUBSTITUTE(SUBSTITUTE(SUBSTITUTE(SUBSTITUTE(SUBSTITUTE(SUBSTITUTE(SUBSTITUTE(SUBSTITUTE(SUBSTITUTE(SUBSTITUTE(SUBSTITUTE(SUBSTITUTE(SUBSTITUTE(SUBSTITUTE(LOWER(B503&";"&C503&";"&F503)," ",""),"'",""),"’",""),"·",""),"/",""),"-",""),"(",""),")",""),"（",""),"）",""),"ü","v"),";","|"),"；","|"),",","|"),"，","|"),"、","|")&"|") | H503: =SUBSTITUTE(SUBSTITUTE(SUBSTITUTE(SUBSTITUTE(SUBSTITUTE(SUBSTITUTE(SUBSTITUTE(SUBSTITUTE(SUBSTITUTE(SUBSTITUTE(SUBSTITUTE(SUBSTITUTE(SUBSTITUTE(SUBSTITUTE(SUBSTITUTE(SUBSTITUTE(SUBSTITUTE(SUBSTITUTE(SUBSTITUTE(SUBSTITUTE(SUBSTITUTE(SUBSTITUTE(SUBSTITUTE(SUBSTITUTE(G503,"ā","a"),"á","a"),"ǎ","a"),"à","a"),"ē","e"),"é","e"),"ě","e"),"è","e"),"ī","i"),"í","i"),"ǐ","i"),"ì","i"),"ō","o"),"ó","o"),"ǒ","o"),"ò","o"),"ū","u"),"ú","u"),"ǔ","u"),"ù","u"),"ǖ","v"),"ǘ","v"),"ǚ","v"),"ǜ","v")
G504: =IF(AND(B504="",C504="",F504=""),"","|"&SUBSTITUTE(SUBSTITUTE(SUBSTITUTE(SUBSTITUTE(SUBSTITUTE(SUBSTITUTE(SUBSTITUTE(SUBSTITUTE(SUBSTITUTE(SUBSTITUTE(SUBSTITUTE(SUBSTITUTE(SUBSTITUTE(SUBSTITUTE(SUBSTITUTE(SUBSTITUTE(LOWER(B504&";"&C504&";"&F504)," ",""),"'",""),"’",""),"·",""),"/",""),"-",""),"(",""),")",""),"（",""),"）",""),"ü","v"),";","|"),"；","|"),",","|"),"，","|"),"、","|")&"|") | H504: =SUBSTITUTE(SUBSTITUTE(SUBSTITUTE(SUBSTITUTE(SUBSTITUTE(SUBSTITUTE(SUBSTITUTE(SUBSTITUTE(SUBSTITUTE(SUBSTITUTE(SUBSTITUTE(SUBSTITUTE(SUBSTITUTE(SUBSTITUTE(SUBSTITUTE(SUBSTITUTE(SUBSTITUTE(SUBSTITUTE(SUBSTITUTE(SUBSTITUTE(SUBSTITUTE(SUBSTITUTE(SUBSTITUTE(SUBSTITUTE(G504,"ā","a"),"á","a"),"ǎ","a"),"à","a"),"ē","e"),"é","e"),"ě","e"),"è","e"),"ī","i"),"í","i"),"ǐ","i"),"ì","i"),"ō","o"),"ó","o"),"ǒ","o"),"ò","o"),"ū","u"),"ú","u"),"ǔ","u"),"ù","u"),"ǖ","v"),"ǘ","v"),"ǚ","v"),"ǜ","v")
G505: =IF(AND(B505="",C505="",F505=""),"","|"&SUBSTITUTE(SUBSTITUTE(SUBSTITUTE(SUBSTITUTE(SUBSTITUTE(SUBSTITUTE(SUBSTITUTE(SUBSTITUTE(SUBSTITUTE(SUBSTITUTE(SUBSTITUTE(SUBSTITUTE(SUBSTITUTE(SUBSTITUTE(SUBSTITUTE(SUBSTITUTE(LOWER(B505&";"&C505&";"&F505)," ",""),"'",""),"’",""),"·",""),"/",""),"-",""),"(",""),")",""),"（",""),"）",""),"ü","v"),";","|"),"；","|"),",","|"),"，","|"),"、","|")&"|") | H505: =SUBSTITUTE(SUBSTITUTE(SUBSTITUTE(SUBSTITUTE(SUBSTITUTE(SUBSTITUTE(SUBSTITUTE(SUBSTITUTE(SUBSTITUTE(SUBSTITUTE(SUBSTITUTE(SUBSTITUTE(SUBSTITUTE(SUBSTITUTE(SUBSTITUTE(SUBSTITUTE(SUBSTITUTE(SUBSTITUTE(SUBSTITUTE(SUBSTITUTE(SUBSTITUTE(SUBSTITUTE(SUBSTITUTE(SUBSTITUTE(G505,"ā","a"),"á","a"),"ǎ","a"),"à","a"),"ē","e"),"é","e"),"ě","e"),"è","e"),"ī","i"),"í","i"),"ǐ","i"),"ì","i"),"ō","o"),"ó","o"),"ǒ","o"),"ò","o"),"ū","u"),"ú","u"),"ǔ","u"),"ù","u"),"ǖ","v"),"ǘ","v"),"ǚ","v"),"ǜ","v")
G506: =IF(AND(B506="",C506="",F506=""),"","|"&SUBSTITUTE(SUBSTITUTE(SUBSTITUTE(SUBSTITUTE(SUBSTITUTE(SUBSTITUTE(SUBSTITUTE(SUBSTITUTE(SUBSTITUTE(SUBSTITUTE(SUBSTITUTE(SUBSTITUTE(SUBSTITUTE(SUBSTITUTE(SUBSTITUTE(SUBSTITUTE(LOWER(B506&";"&C506&";"&F506)," ",""),"'",""),"’",""),"·",""),"/",""),"-",""),"(",""),")",""),"（",""),"）",""),"ü","v"),";","|"),"；","|"),",","|"),"，","|"),"、","|")&"|") | H506: =SUBSTITUTE(SUBSTITUTE(SUBSTITUTE(SUBSTITUTE(SUBSTITUTE(SUBSTITUTE(SUBSTITUTE(SUBSTITUTE(SUBSTITUTE(SUBSTITUTE(SUBSTITUTE(SUBSTITUTE(SUBSTITUTE(SUBSTITUTE(SUBSTITUTE(SUBSTITUTE(SUBSTITUTE(SUBSTITUTE(SUBSTITUTE(SUBSTITUTE(SUBSTITUTE(SUBSTITUTE(SUBSTITUTE(SUBSTITUTE(G506,"ā","a"),"á","a"),"ǎ","a"),"à","a"),"ē","e"),"é","e"),"ě","e"),"è","e"),"ī","i"),"í","i"),"ǐ","i"),"ì","i"),"ō","o"),"ó","o"),"ǒ","o"),"ò","o"),"ū","u"),"ú","u"),"ǔ","u"),"ù","u"),"ǖ","v"),"ǘ","v"),"ǚ","v"),"ǜ","v")
G507: =IF(AND(B507="",C507="",F507=""),"","|"&SUBSTITUTE(SUBSTITUTE(SUBSTITUTE(SUBSTITUTE(SUBSTITUTE(SUBSTITUTE(SUBSTITUTE(SUBSTITUTE(SUBSTITUTE(SUBSTITUTE(SUBSTITUTE(SUBSTITUTE(SUBSTITUTE(SUBSTITUTE(SUBSTITUTE(SUBSTITUTE(LOWER(B507&";"&C507&";"&F507)," ",""),"'",""),"’",""),"·",""),"/",""),"-",""),"(",""),")",""),"（",""),"）",""),"ü","v"),";","|"),"；","|"),",","|"),"，","|"),"、","|")&"|") | H507: =SUBSTITUTE(SUBSTITUTE(SUBSTITUTE(SUBSTITUTE(SUBSTITUTE(SUBSTITUTE(SUBSTITUTE(SUBSTITUTE(SUBSTITUTE(SUBSTITUTE(SUBSTITUTE(SUBSTITUTE(SUBSTITUTE(SUBSTITUTE(SUBSTITUTE(SUBSTITUTE(SUBSTITUTE(SUBSTITUTE(SUBSTITUTE(SUBSTITUTE(SUBSTITUTE(SUBSTITUTE(SUBSTITUTE(SUBSTITUTE(G507,"ā","a"),"á","a"),"ǎ","a"),"à","a"),"ē","e"),"é","e"),"ě","e"),"è","e"),"ī","i"),"í","i"),"ǐ","i"),"ì","i"),"ō","o"),"ó","o"),"ǒ","o"),"ò","o"),"ū","u"),"ú","u"),"ǔ","u"),"ù","u"),"ǖ","v"),"ǘ","v"),"ǚ","v"),"ǜ","v")
G508: =IF(AND(B508="",C508="",F508=""),"","|"&SUBSTITUTE(SUBSTITUTE(SUBSTITUTE(SUBSTITUTE(SUBSTITUTE(SUBSTITUTE(SUBSTITUTE(SUBSTITUTE(SUBSTITUTE(SUBSTITUTE(SUBSTITUTE(SUBSTITUTE(SUBSTITUTE(SUBSTITUTE(SUBSTITUTE(SUBSTITUTE(LOWER(B508&";"&C508&";"&F508)," ",""),"'",""),"’",""),"·",""),"/",""),"-",""),"(",""),")",""),"（",""),"）",""),"ü","v"),";","|"),"；","|"),",","|"),"，","|"),"、","|")&"|") | H508: =SUBSTITUTE(SUBSTITUTE(SUBSTITUTE(SUBSTITUTE(SUBSTITUTE(SUBSTITUTE(SUBSTITUTE(SUBSTITUTE(SUBSTITUTE(SUBSTITUTE(SUBSTITUTE(SUBSTITUTE(SUBSTITUTE(SUBSTITUTE(SUBSTITUTE(SUBSTITUTE(SUBSTITUTE(SUBSTITUTE(SUBSTITUTE(SUBSTITUTE(SUBSTITUTE(SUBSTITUTE(SUBSTITUTE(SUBSTITUTE(G508,"ā","a"),"á","a"),"ǎ","a"),"à","a"),"ē","e"),"é","e"),"ě","e"),"è","e"),"ī","i"),"í","i"),"ǐ","i"),"ì","i"),"ō","o"),"ó","o"),"ǒ","o"),"ò","o"),"ū","u"),"ú","u"),"ǔ","u"),"ù","u"),"ǖ","v"),"ǘ","v"),"ǚ","v"),"ǜ","v")
G509: =IF(AND(B509="",C509="",F509=""),"","|"&SUBSTITUTE(SUBSTITUTE(SUBSTITUTE(SUBSTITUTE(SUBSTITUTE(SUBSTITUTE(SUBSTITUTE(SUBSTITUTE(SUBSTITUTE(SUBSTITUTE(SUBSTITUTE(SUBSTITUTE(SUBSTITUTE(SUBSTITUTE(SUBSTITUTE(SUBSTITUTE(LOWER(B509&";"&C509&";"&F509)," ",""),"'",""),"’",""),"·",""),"/",""),"-",""),"(",""),")",""),"（",""),"）",""),"ü","v"),";","|"),"；","|"),",","|"),"，","|"),"、","|")&"|") | H509: =SUBSTITUTE(SUBSTITUTE(SUBSTITUTE(SUBSTITUTE(SUBSTITUTE(SUBSTITUTE(SUBSTITUTE(SUBSTITUTE(SUBSTITUTE(SUBSTITUTE(SUBSTITUTE(SUBSTITUTE(SUBSTITUTE(SUBSTITUTE(SUBSTITUTE(SUBSTITUTE(SUBSTITUTE(SUBSTITUTE(SUBSTITUTE(SUBSTITUTE(SUBSTITUTE(SUBSTITUTE(SUBSTITUTE(SUBSTITUTE(G509,"ā","a"),"á","a"),"ǎ","a"),"à","a"),"ē","e"),"é","e"),"ě","e"),"è","e"),"ī","i"),"í","i"),"ǐ","i"),"ì","i"),"ō","o"),"ó","o"),"ǒ","o"),"ò","o"),"ū","u"),"ú","u"),"ǔ","u"),"ù","u"),"ǖ","v"),"ǘ","v"),"ǚ","v"),"ǜ","v")
G510: =IF(AND(B510="",C510="",F510=""),"","|"&SUBSTITUTE(SUBSTITUTE(SUBSTITUTE(SUBSTITUTE(SUBSTITUTE(SUBSTITUTE(SUBSTITUTE(SUBSTITUTE(SUBSTITUTE(SUBSTITUTE(SUBSTITUTE(SUBSTITUTE(SUBSTITUTE(SUBSTITUTE(SUBSTITUTE(SUBSTITUTE(LOWER(B510&";"&C510&";"&F510)," ",""),"'",""),"’",""),"·",""),"/",""),"-",""),"(",""),")",""),"（",""),"）",""),"ü","v"),";","|"),"；","|"),",","|"),"，","|"),"、","|")&"|") | H510: =SUBSTITUTE(SUBSTITUTE(SUBSTITUTE(SUBSTITUTE(SUBSTITUTE(SUBSTITUTE(SUBSTITUTE(SUBSTITUTE(SUBSTITUTE(SUBSTITUTE(SUBSTITUTE(SUBSTITUTE(SUBSTITUTE(SUBSTITUTE(SUBSTITUTE(SUBSTITUTE(SUBSTITUTE(SUBSTITUTE(SUBSTITUTE(SUBSTITUTE(SUBSTITUTE(SUBSTITUTE(SUBSTITUTE(SUBSTITUTE(G510,"ā","a"),"á","a"),"ǎ","a"),"à","a"),"ē","e"),"é","e"),"ě","e"),"è","e"),"ī","i"),"í","i"),"ǐ","i"),"ì","i"),"ō","o"),"ó","o"),"ǒ","o"),"ò","o"),"ū","u"),"ú","u"),"ǔ","u"),"ù","u"),"ǖ","v"),"ǘ","v"),"ǚ","v"),"ǜ","v")
G511: =IF(AND(B511="",C511="",F511=""),"","|"&SUBSTITUTE(SUBSTITUTE(SUBSTITUTE(SUBSTITUTE(SUBSTITUTE(SUBSTITUTE(SUBSTITUTE(SUBSTITUTE(SUBSTITUTE(SUBSTITUTE(SUBSTITUTE(SUBSTITUTE(SUBSTITUTE(SUBSTITUTE(SUBSTITUTE(SUBSTITUTE(LOWER(B511&";"&C511&";"&F511)," ",""),"'",""),"’",""),"·",""),"/",""),"-",""),"(",""),")",""),"（",""),"）",""),"ü","v"),";","|"),"；","|"),",","|"),"，","|"),"、","|")&"|") | H511: =SUBSTITUTE(SUBSTITUTE(SUBSTITUTE(SUBSTITUTE(SUBSTITUTE(SUBSTITUTE(SUBSTITUTE(SUBSTITUTE(SUBSTITUTE(SUBSTITUTE(SUBSTITUTE(SUBSTITUTE(SUBSTITUTE(SUBSTITUTE(SUBSTITUTE(SUBSTITUTE(SUBSTITUTE(SUBSTITUTE(SUBSTITUTE(SUBSTITUTE(SUBSTITUTE(SUBSTITUTE(SUBSTITUTE(SUBSTITUTE(G511,"ā","a"),"á","a"),"ǎ","a"),"à","a"),"ē","e"),"é","e"),"ě","e"),"è","e"),"ī","i"),"í","i"),"ǐ","i"),"ì","i"),"ō","o"),"ó","o"),"ǒ","o"),"ò","o"),"ū","u"),"ú","u"),"ǔ","u"),"ù","u"),"ǖ","v"),"ǘ","v"),"ǚ","v"),"ǜ","v")
G512: =IF(AND(B512="",C512="",F512=""),"","|"&SUBSTITUTE(SUBSTITUTE(SUBSTITUTE(SUBSTITUTE(SUBSTITUTE(SUBSTITUTE(SUBSTITUTE(SUBSTITUTE(SUBSTITUTE(SUBSTITUTE(SUBSTITUTE(SUBSTITUTE(SUBSTITUTE(SUBSTITUTE(SUBSTITUTE(SUBSTITUTE(LOWER(B512&";"&C512&";"&F512)," ",""),"'",""),"’",""),"·",""),"/",""),"-",""),"(",""),")",""),"（",""),"）",""),"ü","v"),";","|"),"；","|"),",","|"),"，","|"),"、","|")&"|") | H512: =SUBSTITUTE(SUBSTITUTE(SUBSTITUTE(SUBSTITUTE(SUBSTITUTE(SUBSTITUTE(SUBSTITUTE(SUBSTITUTE(SUBSTITUTE(SUBSTITUTE(SUBSTITUTE(SUBSTITUTE(SUBSTITUTE(SUBSTITUTE(SUBSTITUTE(SUBSTITUTE(SUBSTITUTE(SUBSTITUTE(SUBSTITUTE(SUBSTITUTE(SUBSTITUTE(SUBSTITUTE(SUBSTITUTE(SUBSTITUTE(G512,"ā","a"),"á","a"),"ǎ","a"),"à","a"),"ē","e"),"é","e"),"ě","e"),"è","e"),"ī","i"),"í","i"),"ǐ","i"),"ì","i"),"ō","o"),"ó","o"),"ǒ","o"),"ò","o"),"ū","u"),"ú","u"),"ǔ","u"),"ù","u"),"ǖ","v"),"ǘ","v"),"ǚ","v"),"ǜ","v")
G513: =IF(AND(B513="",C513="",F513=""),"","|"&SUBSTITUTE(SUBSTITUTE(SUBSTITUTE(SUBSTITUTE(SUBSTITUTE(SUBSTITUTE(SUBSTITUTE(SUBSTITUTE(SUBSTITUTE(SUBSTITUTE(SUBSTITUTE(SUBSTITUTE(SUBSTITUTE(SUBSTITUTE(SUBSTITUTE(SUBSTITUTE(LOWER(B513&";"&C513&";"&F513)," ",""),"'",""),"’",""),"·",""),"/",""),"-",""),"(",""),")",""),"（",""),"）",""),"ü","v"),";","|"),"；","|"),",","|"),"，","|"),"、","|")&"|") | H513: =SUBSTITUTE(SUBSTITUTE(SUBSTITUTE(SUBSTITUTE(SUBSTITUTE(SUBSTITUTE(SUBSTITUTE(SUBSTITUTE(SUBSTITUTE(SUBSTITUTE(SUBSTITUTE(SUBSTITUTE(SUBSTITUTE(SUBSTITUTE(SUBSTITUTE(SUBSTITUTE(SUBSTITUTE(SUBSTITUTE(SUBSTITUTE(SUBSTITUTE(SUBSTITUTE(SUBSTITUTE(SUBSTITUTE(SUBSTITUTE(G513,"ā","a"),"á","a"),"ǎ","a"),"à","a"),"ē","e"),"é","e"),"ě","e"),"è","e"),"ī","i"),"í","i"),"ǐ","i"),"ì","i"),"ō","o"),"ó","o"),"ǒ","o"),"ò","o"),"ū","u"),"ú","u"),"ǔ","u"),"ù","u"),"ǖ","v"),"ǘ","v"),"ǚ","v"),"ǜ","v")
... G701: =IF(AND(B701="",C701="",F701=""),"","|"&SUBSTITUTE(SUBSTITUTE(SUBSTITUTE(SUBSTITUTE(SUBSTITUTE(SUBSTITUTE(SUBSTITUTE(SUBSTITUTE(SUBSTITUTE(SUBSTITUTE(SUBSTITUTE(SUBSTITUTE(SUBSTITUTE(SUBSTITUTE(SUBSTITUTE(SUBSTITUTE(LOWER(B701&";"&C701&";"&F701)," ",""),"'",""),"’",""),"·",""),"/",""),"-",""),"(",""),")",""),"（",""),"）",""),"ü","v"),";","|"),"；","|"),",","|"),"，","|"),"、","|")&"|") | H701: =SUBSTITUTE(SUBSTITUTE(SUBSTITUTE(SUBSTITUTE(SUBSTITUTE(SUBSTITUTE(SUBSTITUTE(SUBSTITUTE(SUBSTITUTE(SUBSTITUTE(SUBSTITUTE(SUBSTITUTE(SUBSTITUTE(SUBSTITUTE(SUBSTITUTE(SUBSTITUTE(SUBSTITUTE(SUBSTITUTE(SUBSTITUTE(SUBSTITUTE(SUBSTITUTE(SUBSTITUTE(SUBSTITUTE(SUBSTITUTE(G701,"ā","a"),"á","a"),"ǎ","a"),"à","a"),"ē","e"),"é","e"),"ě","e"),"è","e"),"ī","i"),"í","i"),"ǐ","i"),"ì","i"),"ō","o"),"ó","o"),"ǒ","o"),"ò","o"),"ū","u"),"ú","u"),"ǔ","u"),"ù","u"),"ǖ","v"),"ǘ","v"),"ǚ","v"),"ǜ","v")

Sheet Data_HSK2
A1: STT | B1: Chữ Hán | C1: Pinyin | D1: Từ loại | E1: Nghĩa tiếng Việt | F1: Đáp án chấp nhận (cách nhau bằng dấu ;) — có thể thêm tùy ý | G1: Chuẩn hóa có dấu (tự động) | H1: Chuẩn hóa không dấu (tự động)
A2: 1 | B2: 啊 | C2: a | D2: trợ từ | E2: à, nhé, nhỉ (trợ từ ngữ khí) | F2: 啊; a | G2: =IF(AND(B2="",C2="",F2=""),"","|"&SUBSTITUTE(SUBSTITUTE(SUBSTITUTE(SUBSTITUTE(SUBSTITUTE(SUBSTITUTE(SUBSTITUTE(SUBSTITUTE(SUBSTITUTE(SUBSTITUTE(SUBSTITUTE(SUBSTITUTE(SUBSTITUTE(SUBSTITUTE(SUBSTITUTE(SUBSTITUTE(LOWER(B2&";"&C2&";"&F2)," ",""),"'",""),"’",""),"·",""),"/",""),"-",""),"(",""),")",""),"（",""),"）",""),"ü","v"),";","|"),"；","|"),",","|"),"，","|"),"、","|")&"|") -> |啊|a|啊|a| | H2: =SUBSTITUTE(SUBSTITUTE(SUBSTITUTE(SUBSTITUTE(SUBSTITUTE(SUBSTITUTE(SUBSTITUTE(SUBSTITUTE(SUBSTITUTE(SUBSTITUTE(SUBSTITUTE(SUBSTITUTE(SUBSTITUTE(SUBSTITUTE(SUBSTITUTE(SUBSTITUTE(SUBSTITUTE(SUBSTITUTE(SUBSTITUTE(SUBSTITUTE(SUBSTITUTE(SUBSTITUTE(SUBSTITUTE(SUBSTITUTE(G2,"ā","a"),"á","a"),"ǎ","a"),"à","a"),"ē","e"),"é","e"),"ě","e"),"è","e"),"ī","i"),"í","i"),"ǐ","i"),"ì","i"),"ō","o"),"ó","o"),"ǒ","o"),"ò","o"),"ū","u"),"ú","u"),"ǔ","u"),"ù","u"),"ǖ","v"),"ǘ","v"),"ǚ","v"),"ǜ","v") -> |啊|a|啊|a|
A3: 2 | B3: 爱情 | C3: àiqíng | D3: danh từ | E3: tình yêu (tình cảm lứa đôi) | F3: 爱情; àiqíng; aiqing | G3: =IF(AND(B3="",C3="",F3=""),"","|"&SUBSTITUTE(SUBSTITUTE(SUBSTITUTE(SUBSTITUTE(SUBSTITUTE(SUBSTITUTE(SUBSTITUTE(SUBSTITUTE(SUBSTITUTE(SUBSTITUTE(SUBSTITUTE(SUBSTITUTE(SUBSTITUTE(SUBSTITUTE(SUBSTITUTE(SUBSTITUTE(LOWER(B3&";"&C3&";"&F3)," ",""),"'",""),"’",""),"·",""),"/",""),"-",""),"(",""),")",""),"（",""),"）",""),"ü","v"),";","|"),"；","|"),",","|"),"，","|"),"、","|")&"|") -> |爱情|àiqíng|爱情|àiqíng|aiqing| | H3: =SUBSTITUTE(SUBSTITUTE(SUBSTITUTE(SUBSTITUTE(SUBSTITUTE(SUBSTITUTE(SUBSTITUTE(SUBSTITUTE(SUBSTITUTE(SUBSTITUTE(SUBSTITUTE(SUBSTITUTE(SUBSTITUTE(SUBSTITUTE(SUBSTITUTE(SUBSTITUTE(SUBSTITUTE(SUBSTITUTE(SUBSTITUTE(SUBSTITUTE(SUBSTITUTE(SUBSTITUTE(SUBSTITUTE(SUBSTITUTE(G3,"ā","a"),"á","a"),"ǎ","a"),"à","a"),"ē","e"),"é","e"),"ě","e"),"è","e"),"ī","i"),"í","i"),"ǐ","i"),"ì","i"),"ō","o"),"ó","o"),"ǒ","o"),"ò","o"),"ū","u"),"ú","u"),"ǔ","u"),"ù","u"),"ǖ","v"),"ǘ","v"),"ǚ","v"),"ǜ","v") -> |爱情|aiqing|爱情|aiqing|aiqing|
A4: 3 | B4: 爱人 | C4: àiren | D4: danh từ | E4: vợ hoặc chồng, người yêu | F4: 爱人; àiren; airen | G4: =IF(AND(B4="",C4="",F4=""),"","|"&SUBSTITUTE(SUBSTITUTE(SUBSTITUTE(SUBSTITUTE(SUBSTITUTE(SUBSTITUTE(SUBSTITUTE(SUBSTITUTE(SUBSTITUTE(SUBSTITUTE(SUBSTITUTE(SUBSTITUTE(SUBSTITUTE(SUBSTITUTE(SUBSTITUTE(SUBSTITUTE(LOWER(B4&";"&C4&";"&F4)," ",""),"'",""),"’",""),"·",""),"/",""),"-",""),"(",""),")",""),"（",""),"）",""),"ü","v"),";","|"),"；","|"),",","|"),"，","|"),"、","|")&"|") -> |爱人|àiren|爱人|àiren|airen| | H4: =SUBSTITUTE(SUBSTITUTE(SUBSTITUTE(SUBSTITUTE(SUBSTITUTE(SUBSTITUTE(SUBSTITUTE(SUBSTITUTE(SUBSTITUTE(SUBSTITUTE(SUBSTITUTE(SUBSTITUTE(SUBSTITUTE(SUBSTITUTE(SUBSTITUTE(SUBSTITUTE(SUBSTITUTE(SUBSTITUTE(SUBSTITUTE(SUBSTITUTE(SUBSTITUTE(SUBSTITUTE(SUBSTITUTE(SUBSTITUTE(G4,"ā","a"),"á","a"),"ǎ","a"),"à","a"),"ē","e"),"é","e"),"ě","e"),"è","e"),"ī","i"),"í","i"),"ǐ","i"),"ì","i"),"ō","o"),"ó","o"),"ǒ","o"),"ò","o"),"ū","u"),"ú","u"),"ǔ","u"),"ù","u"),"ǖ","v"),"ǘ","v"),"ǚ","v"),"ǜ","v") -> |爱人|airen|爱人|airen|airen|
A5: 4 | B5: 安静 | C5: ānjìng | D5: tính từ, động từ | E5: yên tĩnh | F5: 安静; ānjìng; anjing | G5: =IF(AND(B5="",C5="",F5=""),"","|"&SUBSTITUTE(SUBSTITUTE(SUBSTITUTE(SUBSTITUTE(SUBSTITUTE(SUBSTITUTE(SUBSTITUTE(SUBSTITUTE(SUBSTITUTE(SUBSTITUTE(SUBSTITUTE(SUBSTITUTE(SUBSTITUTE(SUBSTITUTE(SUBSTITUTE(SUBSTITUTE(LOWER(B5&";"&C5&";"&F5)," ",""),"'",""),"’",""),"·",""),"/",""),"-",""),"(",""),")",""),"（",""),"）",""),"ü","v"),";","|"),"；","|"),",","|"),"，","|"),"、","|")&"|") -> |安静|ānjìng|安静|ānjìng|anjing| | H5: =SUBSTITUTE(SUBSTITUTE(SUBSTITUTE(SUBSTITUTE(SUBSTITUTE(SUBSTITUTE(SUBSTITUTE(SUBSTITUTE(SUBSTITUTE(SUBSTITUTE(SUBSTITUTE(SUBSTITUTE(SUBSTITUTE(SUBSTITUTE(SUBSTITUTE(SUBSTITUTE(SUBSTITUTE(SUBSTITUTE(SUBSTITUTE(SUBSTITUTE(SUBSTITUTE(SUBSTITUTE(SUBSTITUTE(SUBSTITUTE(G5,"ā","a"),"á","a"),"ǎ","a"),"à","a"),"ē","e"),"é","e"),"ě","e"),"è","e"),"ī","i"),"í","i"),"ǐ","i"),"ì","i"),"ō","o"),"ó","o"),"ǒ","o"),"ò","o"),"ū","u"),"ú","u"),"ǔ","u"),"ù","u"),"ǖ","v"),"ǘ","v"),"ǚ","v"),"ǜ","v") -> |安静|anjing|安静|anjing|anjing|
A6: 5 | B6: 安全 | C6: ānquán | D6: tính từ, danh từ | E6: an toàn | F6: 安全; ānquán; anquan | G6: =IF(AND(B6="",C6="",F6=""),"","|"&SUBSTITUTE(SUBSTITUTE(SUBSTITUTE(SUBSTITUTE(SUBSTITUTE(SUBSTITUTE(SUBSTITUTE(SUBSTITUTE(SUBSTITUTE(SUBSTITUTE(SUBSTITUTE(SUBSTITUTE(SUBSTITUTE(SUBSTITUTE(SUBSTITUTE(SUBSTITUTE(LOWER(B6&";"&C6&";"&F6)," ",""),"'",""),"’",""),"·",""),"/",""),"-",""),"(",""),")",""),"（",""),"）",""),"ü","v"),";","|"),"；","|"),",","|"),"，","|"),"、","|")&"|") -> |安全|ānquán|安全|ānquán|anquan| | H6: =SUBSTITUTE(SUBSTITUTE(SUBSTITUTE(SUBSTITUTE(SUBSTITUTE(SUBSTITUTE(SUBSTITUTE(SUBSTITUTE(SUBSTITUTE(SUBSTITUTE(SUBSTITUTE(SUBSTITUTE(SUBSTITUTE(SUBSTITUTE(SUBSTITUTE(SUBSTITUTE(SUBSTITUTE(SUBSTITUTE(SUBSTITUTE(SUBSTITUTE(SUBSTITUTE(SUBSTITUTE(SUBSTITUTE(SUBSTITUTE(G6,"ā","a"),"á","a"),"ǎ","a"),"à","a"),"ē","e"),"é","e"),"ě","e"),"è","e"),"ī","i"),"í","i"),"ǐ","i"),"ì","i"),"ō","o"),"ó","o"),"ǒ","o"),"ò","o"),"ū","u"),"ú","u"),"ǔ","u"),"ù","u"),"ǖ","v"),"ǘ","v"),"ǚ","v"),"ǜ","v") -> |安全|anquan|安全|anquan|anquan|
A7: 6 | B7: 白色 | C7: báisè | D7: danh từ | E7: màu trắng | F7: 白色; báisè; 白; bái; baise; bai | G7: =IF(AND(B7="",C7="",F7=""),"","|"&SUBSTITUTE(SUBSTITUTE(SUBSTITUTE(SUBSTITUTE(SUBSTITUTE(SUBSTITUTE(SUBSTITUTE(SUBSTITUTE(SUBSTITUTE(SUBSTITUTE(SUBSTITUTE(SUBSTITUTE(SUBSTITUTE(SUBSTITUTE(SUBSTITUTE(SUBSTITUTE(LOWER(B7&";"&C7&";"&F7)," ",""),"'",""),"’",""),"·",""),"/",""),"-",""),"(",""),")",""),"（",""),"）",""),"ü","v"),";","|"),"；","|"),",","|"),"，","|"),"、","|")&"|") -> |白色|báisè|白色|báisè|白|bái|baise|bai| | H7: =SUBSTITUTE(SUBSTITUTE(SUBSTITUTE(SUBSTITUTE(SUBSTITUTE(SUBSTITUTE(SUBSTITUTE(SUBSTITUTE(SUBSTITUTE(SUBSTITUTE(SUBSTITUTE(SUBSTITUTE(SUBSTITUTE(SUBSTITUTE(SUBSTITUTE(SUBSTITUTE(SUBSTITUTE(SUBSTITUTE(SUBSTITUTE(SUBSTITUTE(SUBSTITUTE(SUBSTITUTE(SUBSTITUTE(SUBSTITUTE(G7,"ā","a"),"á","a"),"ǎ","a"),"à","a"),"ē","e"),"é","e"),"ě","e"),"è","e"),"ī","i"),"í","i"),"ǐ","i"),"ì","i"),"ō","o"),"ó","o"),"ǒ","o"),"ò","o"),"ū","u"),"ú","u"),"ǔ","u"),"ù","u"),"ǖ","v"),"ǘ","v"),"ǚ","v"),"ǜ","v") -> |白色|baise|白色|baise|白|bai|baise|bai|
A8: 7 | B8: 班长 | C8: bānzhǎng | D8: danh từ | E8: lớp trưởng | F8: 班长; bānzhǎng; banzhang | G8: =IF(AND(B8="",C8="",F8=""),"","|"&SUBSTITUTE(SUBSTITUTE(SUBSTITUTE(SUBSTITUTE(SUBSTITUTE(SUBSTITUTE(SUBSTITUTE(SUBSTITUTE(SUBSTITUTE(SUBSTITUTE(SUBSTITUTE(SUBSTITUTE(SUBSTITUTE(SUBSTITUTE(SUBSTITUTE(SUBSTITUTE(LOWER(B8&";"&C8&";"&F8)," ",""),"'",""),"’",""),"·",""),"/",""),"-",""),"(",""),")",""),"（",""),"）",""),"ü","v"),";","|"),"；","|"),",","|"),"，","|"),"、","|")&"|") -> |班长|bānzhǎng|班长|bānzhǎng|banzhang| | H8: =SUBSTITUTE(SUBSTITUTE(SUBSTITUTE(SUBSTITUTE(SUBSTITUTE(SUBSTITUTE(SUBSTITUTE(SUBSTITUTE(SUBSTITUTE(SUBSTITUTE(SUBSTITUTE(SUBSTITUTE(SUBSTITUTE(SUBSTITUTE(SUBSTITUTE(SUBSTITUTE(SUBSTITUTE(SUBSTITUTE(SUBSTITUTE(SUBSTITUTE(SUBSTITUTE(SUBSTITUTE(SUBSTITUTE(SUBSTITUTE(G8,"ā","a"),"á","a"),"ǎ","a"),"à","a"),"ē","e"),"é","e"),"ě","e"),"è","e"),"ī","i"),"í","i"),"ǐ","i"),"ì","i"),"ō","o"),"ó","o"),"ǒ","o"),"ò","o"),"ū","u"),"ú","u"),"ǔ","u"),"ù","u"),"ǖ","v"),"ǘ","v"),"ǚ","v"),"ǜ","v") -> |班长|banzhang|班长|banzhang|banzhang|
A9: 8 | B9: 办 | C9: bàn | D9: động từ | E9: làm, xử lý (công việc) | F9: 办; bàn; ban | G9: =IF(AND(B9="",C9="",F9=""),"","|"&SUBSTITUTE(SUBSTITUTE(SUBSTITUTE(SUBSTITUTE(SUBSTITUTE(SUBSTITUTE(SUBSTITUTE(SUBSTITUTE(SUBSTITUTE(SUBSTITUTE(SUBSTITUTE(SUBSTITUTE(SUBSTITUTE(SUBSTITUTE(SUBSTITUTE(SUBSTITUTE(LOWER(B9&";"&C9&";"&F9)," ",""),"'",""),"’",""),"·",""),"/",""),"-",""),"(",""),")",""),"（",""),"）",""),"ü","v"),";","|"),"；","|"),",","|"),"，","|"),"、","|")&"|") -> |办|bàn|办|bàn|ban| | H9: =SUBSTITUTE(SUBSTITUTE(SUBSTITUTE(SUBSTITUTE(SUBSTITUTE(SUBSTITUTE(SUBSTITUTE(SUBSTITUTE(SUBSTITUTE(SUBSTITUTE(SUBSTITUTE(SUBSTITUTE(SUBSTITUTE(SUBSTITUTE(SUBSTITUTE(SUBSTITUTE(SUBSTITUTE(SUBSTITUTE(SUBSTITUTE(SUBSTITUTE(SUBSTITUTE(SUBSTITUTE(SUBSTITUTE(SUBSTITUTE(G9,"ā","a"),"á","a"),"ǎ","a"),"à","a"),"ē","e"),"é","e"),"ě","e"),"è","e"),"ī","i"),"í","i"),"ǐ","i"),"ì","i"),"ō","o"),"ó","o"),"ǒ","o"),"ò","o"),"ū","u"),"ú","u"),"ǔ","u"),"ù","u"),"ǖ","v"),"ǘ","v"),"ǚ","v"),"ǜ","v") -> |办|ban|办|ban|ban|
A10: 9 | B10: 办法 | C10: bànfǎ | D10: danh từ | E10: biện pháp, cách | F10: 办法; bànfǎ; 方法; fāngfǎ; banfa; fangfa | G10: =IF(AND(B10="",C10="",F10=""),"","|"&SUBSTITUTE(SUBSTITUTE(SUBSTITUTE(SUBSTITUTE(SUBSTITUTE(SUBSTITUTE(SUBSTITUTE(SUBSTITUTE(SUBSTITUTE(SUBSTITUTE(SUBSTITUTE(SUBSTITUTE(SUBSTITUTE(SUBSTITUTE(SUBSTITUTE(SUBSTITUTE(LOWER(B10&";"&C10&";"&F10)," ",""),"'",""),"’",""),"·",""),"/",""),"-",""),"(",""),")",""),"（",""),"）",""),"ü","v"),";","|"),"；","|"),",","|"),"，","|"),"、","|")&"|") -> |办法|bànfǎ|办法|bànfǎ|方法|fāngfǎ|banfa|fangfa| | H10: =SUBSTITUTE(SUBSTITUTE(SUBSTITUTE(SUBSTITUTE(SUBSTITUTE(SUBSTITUTE(SUBSTITUTE(SUBSTITUTE(SUBSTITUTE(SUBSTITUTE(SUBSTITUTE(SUBSTITUTE(SUBSTITUTE(SUBSTITUTE(SUBSTITUTE(SUBSTITUTE(SUBSTITUTE(SUBSTITUTE(SUBSTITUTE(SUBSTITUTE(SUBSTITUTE(SUBSTITUTE(SUBSTITUTE(SUBSTITUTE(G10,"ā","a"),"á","a"),"ǎ","a"),"à","a"),"ē","e"),"é","e"),"ě","e"),"è","e"),"ī","i"),"í","i"),"ǐ","i"),"ì","i"),"ō","o"),"ó","o"),"ǒ","o"),"ò","o"),"ū","u"),"ú","u"),"ǔ","u"),"ù","u"),"ǖ","v"),"ǘ","v"),"ǚ","v"),"ǜ","v") -> |办法|banfa|办法|banfa|方法|fangfa|banfa|fangfa|
A11: 10 | B11: 办公室 | C11: bàngōngshì | D11: danh từ | E11: văn phòng | F11: 办公室; bàngōngshì; bangongshi | G11: =IF(AND(B11="",C11="",F11=""),"","|"&SUBSTITUTE(SUBSTITUTE(SUBSTITUTE(SUBSTITUTE(SUBSTITUTE(SUBSTITUTE(SUBSTITUTE(SUBSTITUTE(SUBSTITUTE(SUBSTITUTE(SUBSTITUTE(SUBSTITUTE(SUBSTITUTE(SUBSTITUTE(SUBSTITUTE(SUBSTITUTE(LOWER(B11&";"&C11&";"&F11)," ",""),"'",""),"’",""),"·",""),"/",""),"-",""),"(",""),")",""),"（",""),"）",""),"ü","v"),";","|"),"；","|"),",","|"),"，","|"),"、","|")&"|") -> |办公室|bàngōngshì|办公室|bàngōngshì|bangongshi| | H11: =SUBSTITUTE(SUBSTITUTE(SUBSTITUTE(SUBSTITUTE(SUBSTITUTE(SUBSTITUTE(SUBSTITUTE(SUBSTITUTE(SUBSTITUTE(SUBSTITUTE(SUBSTITUTE(SUBSTITUTE(SUBSTITUTE(SUBSTITUTE(SUBSTITUTE(SUBSTITUTE(SUBSTITUTE(SUBSTITUTE(SUBSTITUTE(SUBSTITUTE(SUBSTITUTE(SUBSTITUTE(SUBSTITUTE(SUBSTITUTE(G11,"ā","a"),"á","a"),"ǎ","a"),"à","a"),"ē","e"),"é","e"),"ě","e"),"è","e"),"ī","i"),"í","i"),"ǐ","i"),"ì","i"),"ō","o"),"ó","o"),"ǒ","o"),"ò","o"),"ū","u"),"ú","u"),"ǔ","u"),"ù","u"),"ǖ","v"),"ǘ","v"),"ǚ","v"),"ǜ","v") -> |办公室|bangongshi|办公室|bangongshi|bangongshi|
A12: 11 | B12: 半夜 | C12: bànyè | D12: danh từ | E12: nửa đêm | F12: 半夜; bànyè; banye | G12: =IF(AND(B12="",C12="",F12=""),"","|"&SUBSTITUTE(SUBSTITUTE(SUBSTITUTE(SUBSTITUTE(SUBSTITUTE(SUBSTITUTE(SUBSTITUTE(SUBSTITUTE(SUBSTITUTE(SUBSTITUTE(SUBSTITUTE(SUBSTITUTE(SUBSTITUTE(SUBSTITUTE(SUBSTITUTE(SUBSTITUTE(LOWER(B12&";"&C12&";"&F12)," ",""),"'",""),"’",""),"·",""),"/",""),"-",""),"(",""),")",""),"（",""),"）",""),"ü","v"),";","|"),"；","|"),",","|"),"，","|"),"、","|")&"|") -> |半夜|bànyè|半夜|bànyè|banye| | H12: =SUBSTITUTE(SUBSTITUTE(SUBSTITUTE(SUBSTITUTE(SUBSTITUTE(SUBSTITUTE(SUBSTITUTE(SUBSTITUTE(SUBSTITUTE(SUBSTITUTE(SUBSTITUTE(SUBSTITUTE(SUBSTITUTE(SUBSTITUTE(SUBSTITUTE(SUBSTITUTE(SUBSTITUTE(SUBSTITUTE(SUBSTITUTE(SUBSTITUTE(SUBSTITUTE(SUBSTITUTE(SUBSTITUTE(SUBSTITUTE(G12,"ā","a"),"á","a"),"ǎ","a"),"à","a"),"ē","e"),"é","e"),"ě","e"),"è","e"),"ī","i"),"í","i"),"ǐ","i"),"ì","i"),"ō","o"),"ó","o"),"ǒ","o"),"ò","o"),"ū","u"),"ú","u"),"ǔ","u"),"ù","u"),"ǖ","v"),"ǘ","v"),"ǚ","v"),"ǜ","v") -> |半夜|banye|半夜|banye|banye|
A13: 12 | B13: 帮助 | C13: bāngzhù | D13: động từ | E13: giúp đỡ (帮助) | F13: 帮助; bāngzhù; 帮; bāng; 帮忙; bāngmáng; bangzhu; bang; bangmang | G13: =IF(AND(B13="",C13="",F13=""),"","|"&SUBSTITUTE(SUBSTITUTE(SUBSTITUTE(SUBSTITUTE(SUBSTITUTE(SUBSTITUTE(SUBSTITUTE(SUBSTITUTE(SUBSTITUTE(SUBSTITUTE(SUBSTITUTE(SUBSTITUTE(SUBSTITUTE(SUBSTITUTE(SUBSTITUTE(SUBSTITUTE(LOWER(B13&";"&C13&";"&F13)," ",""),"'",""),"’",""),"·",""),"/",""),"-",""),"(",""),")",""),"（",""),"）",""),"ü","v"),";","|"),"；","|"),",","|"),"，","|"),"、","|")&"|") -> |帮助|bāngzhù|帮助|bāngzhù|帮|bāng|帮忙|bāngmáng|bangzhu|bang|bangmang| | H13: =SUBSTITUTE(SUBSTITUTE(SUBSTITUTE(SUBSTITUTE(SUBSTITUTE(SUBSTITUTE(SUBSTITUTE(SUBSTITUTE(SUBSTITUTE(SUBSTITUTE(SUBSTITUTE(SUBSTITUTE(SUBSTITUTE(SUBSTITUTE(SUBSTITUTE(SUBSTITUTE(SUBSTITUTE(SUBSTITUTE(SUBSTITUTE(SUBSTITUTE(SUBSTITUTE(SUBSTITUTE(SUBSTITUTE(SUBSTITUTE(G13,"ā","a"),"á","a"),"ǎ","a"),"à","a"),"ē","e"),"é","e"),"ě","e"),"è","e"),"ī","i"),"í","i"),"ǐ","i"),"ì","i"),"ō","o"),"ó","o"),"ǒ","o"),"ò","o"),"ū","u"),"ú","u"),"ǔ","u"),"ù","u"),"ǖ","v"),"ǘ","v"),"ǚ","v"),"ǜ","v") -> |帮助|bangzhu|帮助|bangzhu|帮|bang|帮忙|bangmang|bangzhu|bang|bangmang|
... A773: 772 | B773: 做饭 | C773: zuòfàn | D773: cụm từ | E773: nấu cơm, nấu ăn | F773: 做饭; zuòfàn; 煮饭; zhǔfàn; zuofan; zhufan | G773: =IF(AND(B773="",C773="",F773=""),"","|"&SUBSTITUTE(SUBSTITUTE(SUBSTITUTE(SUBSTITUTE(SUBSTITUTE(SUBSTITUTE(SUBSTITUTE(SUBSTITUTE(SUBSTITUTE(SUBSTITUTE(SUBSTITUTE(SUBSTITUTE(SUBSTITUTE(SUBSTITUTE(SUBSTITUTE(SUBSTITUTE(LOWER(B773&";"&C773&";"&F773)," ",""),"'",""),"’",""),"·",""),"/",""),"-",""),"(",""),")",""),"（",""),"）",""),"ü","v"),";","|"),"；","|"),",","|"),"，","|"),"、","|")&"|") -> |做饭|zuòfàn|做饭|zuòfàn|煮饭|zhǔfàn|zuofan|zhufan| | H773: =SUBSTITUTE(SUBSTITUTE(SUBSTITUTE(SUBSTITUTE(SUBSTITUTE(SUBSTITUTE(SUBSTITUTE(SUBSTITUTE(SUBSTITUTE(SUBSTITUTE(SUBSTITUTE(SUBSTITUTE(SUBSTITUTE(SUBSTITUTE(SUBSTITUTE(SUBSTITUTE(SUBSTITUTE(SUBSTITUTE(SUBSTITUTE(SUBSTITUTE(SUBSTITUTE(SUBSTITUTE(SUBSTITUTE(SUBSTITUTE(G773,"ā","a"),"á","a"),"ǎ","a"),"à","a"),"ē","e"),"é","e"),"ě","e"),"è","e"),"ī","i"),"í","i"),"ǐ","i"),"ì","i"),"ō","o"),"ó","o"),"ǒ","o"),"ò","o"),"ū","u"),"ú","u"),"ǔ","u"),"ù","u"),"ǖ","v"),"ǘ","v"),"ǚ","v"),"ǜ","v") -> |做饭|zuofan|做饭|zuofan|煮饭|zhufan|zuofan|zhufan|
G774: =IF(AND(B774="",C774="",F774=""),"","|"&SUBSTITUTE(SUBSTITUTE(SUBSTITUTE(SUBSTITUTE(SUBSTITUTE(SUBSTITUTE(SUBSTITUTE(SUBSTITUTE(SUBSTITUTE(SUBSTITUTE(SUBSTITUTE(SUBSTITUTE(SUBSTITUTE(SUBSTITUTE(SUBSTITUTE(SUBSTITUTE(LOWER(B774&";"&C774&";"&F774)," ",""),"'",""),"’",""),"·",""),"/",""),"-",""),"(",""),")",""),"（",""),"）",""),"ü","v"),";","|"),"；","|"),",","|"),"，","|"),"、","|")&"|") | H774: =SUBSTITUTE(SUBSTITUTE(SUBSTITUTE(SUBSTITUTE(SUBSTITUTE(SUBSTITUTE(SUBSTITUTE(SUBSTITUTE(SUBSTITUTE(SUBSTITUTE(SUBSTITUTE(SUBSTITUTE(SUBSTITUTE(SUBSTITUTE(SUBSTITUTE(SUBSTITUTE(SUBSTITUTE(SUBSTITUTE(SUBSTITUTE(SUBSTITUTE(SUBSTITUTE(SUBSTITUTE(SUBSTITUTE(SUBSTITUTE(G774,"ā","a"),"á","a"),"ǎ","a"),"à","a"),"ē","e"),"é","e"),"ě","e"),"è","e"),"ī","i"),"í","i"),"ǐ","i"),"ì","i"),"ō","o"),"ó","o"),"ǒ","o"),"ò","o"),"ū","u"),"ú","u"),"ǔ","u"),"ù","u"),"ǖ","v"),"ǘ","v"),"ǚ","v"),"ǜ","v")
G775: =IF(AND(B775="",C775="",F775=""),"","|"&SUBSTITUTE(SUBSTITUTE(SUBSTITUTE(SUBSTITUTE(SUBSTITUTE(SUBSTITUTE(SUBSTITUTE(SUBSTITUTE(SUBSTITUTE(SUBSTITUTE(SUBSTITUTE(SUBSTITUTE(SUBSTITUTE(SUBSTITUTE(SUBSTITUTE(SUBSTITUTE(LOWER(B775&";"&C775&";"&F775)," ",""),"'",""),"’",""),"·",""),"/",""),"-",""),"(",""),")",""),"（",""),"）",""),"ü","v"),";","|"),"；","|"),",","|"),"，","|"),"、","|")&"|") | H775: =SUBSTITUTE(SUBSTITUTE(SUBSTITUTE(SUBSTITUTE(SUBSTITUTE(SUBSTITUTE(SUBSTITUTE(SUBSTITUTE(SUBSTITUTE(SUBSTITUTE(SUBSTITUTE(SUBSTITUTE(SUBSTITUTE(SUBSTITUTE(SUBSTITUTE(SUBSTITUTE(SUBSTITUTE(SUBSTITUTE(SUBSTITUTE(SUBSTITUTE(SUBSTITUTE(SUBSTITUTE(SUBSTITUTE(SUBSTITUTE(G775,"ā","a"),"á","a"),"ǎ","a"),"à","a"),"ē","e"),"é","e"),"ě","e"),"è","e"),"ī","i"),"í","i"),"ǐ","i"),"ì","i"),"ō","o"),"ó","o"),"ǒ","o"),"ò","o"),"ū","u"),"ú","u"),"ǔ","u"),"ù","u"),"ǖ","v"),"ǘ","v"),"ǚ","v"),"ǜ","v")
G776: =IF(AND(B776="",C776="",F776=""),"","|"&SUBSTITUTE(SUBSTITUTE(SUBSTITUTE(SUBSTITUTE(SUBSTITUTE(SUBSTITUTE(SUBSTITUTE(SUBSTITUTE(SUBSTITUTE(SUBSTITUTE(SUBSTITUTE(SUBSTITUTE(SUBSTITUTE(SUBSTITUTE(SUBSTITUTE(SUBSTITUTE(LOWER(B776&";"&C776&";"&F776)," ",""),"'",""),"’",""),"·",""),"/",""),"-",""),"(",""),")",""),"（",""),"）",""),"ü","v"),";","|"),"；","|"),",","|"),"，","|"),"、","|")&"|") | H776: =SUBSTITUTE(SUBSTITUTE(SUBSTITUTE(SUBSTITUTE(SUBSTITUTE(SUBSTITUTE(SUBSTITUTE(SUBSTITUTE(SUBSTITUTE(SUBSTITUTE(SUBSTITUTE(SUBSTITUTE(SUBSTITUTE(SUBSTITUTE(SUBSTITUTE(SUBSTITUTE(SUBSTITUTE(SUBSTITUTE(SUBSTITUTE(SUBSTITUTE(SUBSTITUTE(SUBSTITUTE(SUBSTITUTE(SUBSTITUTE(G776,"ā","a"),"á","a"),"ǎ","a"),"à","a"),"ē","e"),"é","e"),"ě","e"),"è","e"),"ī","i"),"í","i"),"ǐ","i"),"ì","i"),"ō","o"),"ó","o"),"ǒ","o"),"ò","o"),"ū","u"),"ú","u"),"ǔ","u"),"ù","u"),"ǖ","v"),"ǘ","v"),"ǚ","v"),"ǜ","v")
G777: =IF(AND(B777="",C777="",F777=""),"","|"&SUBSTITUTE(SUBSTITUTE(SUBSTITUTE(SUBSTITUTE(SUBSTITUTE(SUBSTITUTE(SUBSTITUTE(SUBSTITUTE(SUBSTITUTE(SUBSTITUTE(SUBSTITUTE(SUBSTITUTE(SUBSTITUTE(SUBSTITUTE(SUBSTITUTE(SUBSTITUTE(LOWER(B777&";"&C777&";"&F777)," ",""),"'",""),"’",""),"·",""),"/",""),"-",""),"(",""),")",""),"（",""),"）",""),"ü","v"),";","|"),"；","|"),",","|"),"，","|"),"、","|")&"|") | H777: =SUBSTITUTE(SUBSTITUTE(SUBSTITUTE(SUBSTITUTE(SUBSTITUTE(SUBSTITUTE(SUBSTITUTE(SUBSTITUTE(SUBSTITUTE(SUBSTITUTE(SUBSTITUTE(SUBSTITUTE(SUBSTITUTE(SUBSTITUTE(SUBSTITUTE(SUBSTITUTE(SUBSTITUTE(SUBSTITUTE(SUBSTITUTE(SUBSTITUTE(SUBSTITUTE(SUBSTITUTE(SUBSTITUTE(SUBSTITUTE(G777,"ā","a"),"á","a"),"ǎ","a"),"à","a"),"ē","e"),"é","e"),"ě","e"),"è","e"),"ī","i"),"í","i"),"ǐ","i"),"ì","i"),"ō","o"),"ó","o"),"ǒ","o"),"ò","o"),"ū","u"),"ú","u"),"ǔ","u"),"ù","u"),"ǖ","v"),"ǘ","v"),"ǚ","v"),"ǜ","v")
G778: =IF(AND(B778="",C778="",F778=""),"","|"&SUBSTITUTE(SUBSTITUTE(SUBSTITUTE(SUBSTITUTE(SUBSTITUTE(SUBSTITUTE(SUBSTITUTE(SUBSTITUTE(SUBSTITUTE(SUBSTITUTE(SUBSTITUTE(SUBSTITUTE(SUBSTITUTE(SUBSTITUTE(SUBSTITUTE(SUBSTITUTE(LOWER(B778&";"&C778&";"&F778)," ",""),"'",""),"’",""),"·",""),"/",""),"-",""),"(",""),")",""),"（",""),"）",""),"ü","v"),";","|"),"；","|"),",","|"),"，","|"),"、","|")&"|") | H778: =SUBSTITUTE(SUBSTITUTE(SUBSTITUTE(SUBSTITUTE(SUBSTITUTE(SUBSTITUTE(SUBSTITUTE(SUBSTITUTE(SUBSTITUTE(SUBSTITUTE(SUBSTITUTE(SUBSTITUTE(SUBSTITUTE(SUBSTITUTE(SUBSTITUTE(SUBSTITUTE(SUBSTITUTE(SUBSTITUTE(SUBSTITUTE(SUBSTITUTE(SUBSTITUTE(SUBSTITUTE(SUBSTITUTE(SUBSTITUTE(G778,"ā","a"),"á","a"),"ǎ","a"),"à","a"),"ē","e"),"é","e"),"ě","e"),"è","e"),"ī","i"),"í","i"),"ǐ","i"),"ì","i"),"ō","o"),"ó","o"),"ǒ","o"),"ò","o"),"ū","u"),"ú","u"),"ǔ","u"),"ù","u"),"ǖ","v"),"ǘ","v"),"ǚ","v"),"ǜ","v")
G779: =IF(AND(B779="",C779="",F779=""),"","|"&SUBSTITUTE(SUBSTITUTE(SUBSTITUTE(SUBSTITUTE(SUBSTITUTE(SUBSTITUTE(SUBSTITUTE(SUBSTITUTE(SUBSTITUTE(SUBSTITUTE(SUBSTITUTE(SUBSTITUTE(SUBSTITUTE(SUBSTITUTE(SUBSTITUTE(SUBSTITUTE(LOWER(B779&";"&C779&";"&F779)," ",""),"'",""),"’",""),"·",""),"/",""),"-",""),"(",""),")",""),"（",""),"）",""),"ü","v"),";","|"),"；","|"),",","|"),"，","|"),"、","|")&"|") | H779: =SUBSTITUTE(SUBSTITUTE(SUBSTITUTE(SUBSTITUTE(SUBSTITUTE(SUBSTITUTE(SUBSTITUTE(SUBSTITUTE(SUBSTITUTE(SUBSTITUTE(SUBSTITUTE(SUBSTITUTE(SUBSTITUTE(SUBSTITUTE(SUBSTITUTE(SUBSTITUTE(SUBSTITUTE(SUBSTITUTE(SUBSTITUTE(SUBSTITUTE(SUBSTITUTE(SUBSTITUTE(SUBSTITUTE(SUBSTITUTE(G779,"ā","a"),"á","a"),"ǎ","a"),"à","a"),"ē","e"),"é","e"),"ě","e"),"è","e"),"ī","i"),"í","i"),"ǐ","i"),"ì","i"),"ō","o"),"ó","o"),"ǒ","o"),"ò","o"),"ū","u"),"ú","u"),"ǔ","u"),"ù","u"),"ǖ","v"),"ǘ","v"),"ǚ","v"),"ǜ","v")
G780: =IF(AND(B780="",C780="",F780=""),"","|"&SUBSTITUTE(SUBSTITUTE(SUBSTITUTE(SUBSTITUTE(SUBSTITUTE(SUBSTITUTE(SUBSTITUTE(SUBSTITUTE(SUBSTITUTE(SUBSTITUTE(SUBSTITUTE(SUBSTITUTE(SUBSTITUTE(SUBSTITUTE(SUBSTITUTE(SUBSTITUTE(LOWER(B780&";"&C780&";"&F780)," ",""),"'",""),"’",""),"·",""),"/",""),"-",""),"(",""),")",""),"（",""),"）",""),"ü","v"),";","|"),"；","|"),",","|"),"，","|"),"、","|")&"|") | H780: =SUBSTITUTE(SUBSTITUTE(SUBSTITUTE(SUBSTITUTE(SUBSTITUTE(SUBSTITUTE(SUBSTITUTE(SUBSTITUTE(SUBSTITUTE(SUBSTITUTE(SUBSTITUTE(SUBSTITUTE(SUBSTITUTE(SUBSTITUTE(SUBSTITUTE(SUBSTITUTE(SUBSTITUTE(SUBSTITUTE(SUBSTITUTE(SUBSTITUTE(SUBSTITUTE(SUBSTITUTE(SUBSTITUTE(SUBSTITUTE(G780,"ā","a"),"á","a"),"ǎ","a"),"à","a"),"ē","e"),"é","e"),"ě","e"),"è","e"),"ī","i"),"í","i"),"ǐ","i"),"ì","i"),"ō","o"),"ó","o"),"ǒ","o"),"ò","o"),"ū","u"),"ú","u"),"ǔ","u"),"ù","u"),"ǖ","v"),"ǘ","v"),"ǚ","v"),"ǜ","v")
G781: =IF(AND(B781="",C781="",F781=""),"","|"&SUBSTITUTE(SUBSTITUTE(SUBSTITUTE(SUBSTITUTE(SUBSTITUTE(SUBSTITUTE(SUBSTITUTE(SUBSTITUTE(SUBSTITUTE(SUBSTITUTE(SUBSTITUTE(SUBSTITUTE(SUBSTITUTE(SUBSTITUTE(SUBSTITUTE(SUBSTITUTE(LOWER(B781&";"&C781&";"&F781)," ",""),"'",""),"’",""),"·",""),"/",""),"-",""),"(",""),")",""),"（",""),"）",""),"ü","v"),";","|"),"；","|"),",","|"),"，","|"),"、","|")&"|") | H781: =SUBSTITUTE(SUBSTITUTE(SUBSTITUTE(SUBSTITUTE(SUBSTITUTE(SUBSTITUTE(SUBSTITUTE(SUBSTITUTE(SUBSTITUTE(SUBSTITUTE(SUBSTITUTE(SUBSTITUTE(SUBSTITUTE(SUBSTITUTE(SUBSTITUTE(SUBSTITUTE(SUBSTITUTE(SUBSTITUTE(SUBSTITUTE(SUBSTITUTE(SUBSTITUTE(SUBSTITUTE(SUBSTITUTE(SUBSTITUTE(G781,"ā","a"),"á","a"),"ǎ","a"),"à","a"),"ē","e"),"é","e"),"ě","e"),"è","e"),"ī","i"),"í","i"),"ǐ","i"),"ì","i"),"ō","o"),"ó","o"),"ǒ","o"),"ò","o"),"ū","u"),"ú","u"),"ǔ","u"),"ù","u"),"ǖ","v"),"ǘ","v"),"ǚ","v"),"ǜ","v")
G782: =IF(AND(B782="",C782="",F782=""),"","|"&SUBSTITUTE(SUBSTITUTE(SUBSTITUTE(SUBSTITUTE(SUBSTITUTE(SUBSTITUTE(SUBSTITUTE(SUBSTITUTE(SUBSTITUTE(SUBSTITUTE(SUBSTITUTE(SUBSTITUTE(SUBSTITUTE(SUBSTITUTE(SUBSTITUTE(SUBSTITUTE(LOWER(B782&";"&C782&";"&F782)," ",""),"'",""),"’",""),"·",""),"/",""),"-",""),"(",""),")",""),"（",""),"）",""),"ü","v"),";","|"),"；","|"),",","|"),"，","|"),"、","|")&"|") | H782: =SUBSTITUTE(SUBSTITUTE(SUBSTITUTE(SUBSTITUTE(SUBSTITUTE(SUBSTITUTE(SUBSTITUTE(SUBSTITUTE(SUBSTITUTE(SUBSTITUTE(SUBSTITUTE(SUBSTITUTE(SUBSTITUTE(SUBSTITUTE(SUBSTITUTE(SUBSTITUTE(SUBSTITUTE(SUBSTITUTE(SUBSTITUTE(SUBSTITUTE(SUBSTITUTE(SUBSTITUTE(SUBSTITUTE(SUBSTITUTE(G782,"ā","a"),"á","a"),"ǎ","a"),"à","a"),"ē","e"),"é","e"),"ě","e"),"è","e"),"ī","i"),"í","i"),"ǐ","i"),"ì","i"),"ō","o"),"ó","o"),"ǒ","o"),"ò","o"),"ū","u"),"ú","u"),"ǔ","u"),"ù","u"),"ǖ","v"),"ǘ","v"),"ǚ","v"),"ǜ","v")
G783: =IF(AND(B783="",C783="",F783=""),"","|"&SUBSTITUTE(SUBSTITUTE(SUBSTITUTE(SUBSTITUTE(SUBSTITUTE(SUBSTITUTE(SUBSTITUTE(SUBSTITUTE(SUBSTITUTE(SUBSTITUTE(SUBSTITUTE(SUBSTITUTE(SUBSTITUTE(SUBSTITUTE(SUBSTITUTE(SUBSTITUTE(LOWER(B783&";"&C783&";"&F783)," ",""),"'",""),"’",""),"·",""),"/",""),"-",""),"(",""),")",""),"（",""),"）",""),"ü","v"),";","|"),"；","|"),",","|"),"，","|"),"、","|")&"|") | H783: =SUBSTITUTE(SUBSTITUTE(SUBSTITUTE(SUBSTITUTE(SUBSTITUTE(SUBSTITUTE(SUBSTITUTE(SUBSTITUTE(SUBSTITUTE(SUBSTITUTE(SUBSTITUTE(SUBSTITUTE(SUBSTITUTE(SUBSTITUTE(SUBSTITUTE(SUBSTITUTE(SUBSTITUTE(SUBSTITUTE(SUBSTITUTE(SUBSTITUTE(SUBSTITUTE(SUBSTITUTE(SUBSTITUTE(SUBSTITUTE(G783,"ā","a"),"á","a"),"ǎ","a"),"à","a"),"ē","e"),"é","e"),"ě","e"),"è","e"),"ī","i"),"í","i"),"ǐ","i"),"ì","i"),"ō","o"),"ó","o"),"ǒ","o"),"ò","o"),"ū","u"),"ú","u"),"ǔ","u"),"ù","u"),"ǖ","v"),"ǘ","v"),"ǚ","v"),"ǜ","v")
G784: =IF(AND(B784="",C784="",F784=""),"","|"&SUBSTITUTE(SUBSTITUTE(SUBSTITUTE(SUBSTITUTE(SUBSTITUTE(SUBSTITUTE(SUBSTITUTE(SUBSTITUTE(SUBSTITUTE(SUBSTITUTE(SUBSTITUTE(SUBSTITUTE(SUBSTITUTE(SUBSTITUTE(SUBSTITUTE(SUBSTITUTE(LOWER(B784&";"&C784&";"&F784)," ",""),"'",""),"’",""),"·",""),"/",""),"-",""),"(",""),")",""),"（",""),"）",""),"ü","v"),";","|"),"；","|"),",","|"),"，","|"),"、","|")&"|") | H784: =SUBSTITUTE(SUBSTITUTE(SUBSTITUTE(SUBSTITUTE(SUBSTITUTE(SUBSTITUTE(SUBSTITUTE(SUBSTITUTE(SUBSTITUTE(SUBSTITUTE(SUBSTITUTE(SUBSTITUTE(SUBSTITUTE(SUBSTITUTE(SUBSTITUTE(SUBSTITUTE(SUBSTITUTE(SUBSTITUTE(SUBSTITUTE(SUBSTITUTE(SUBSTITUTE(SUBSTITUTE(SUBSTITUTE(SUBSTITUTE(G784,"ā","a"),"á","a"),"ǎ","a"),"à","a"),"ē","e"),"é","e"),"ě","e"),"è","e"),"ī","i"),"í","i"),"ǐ","i"),"ì","i"),"ō","o"),"ó","o"),"ǒ","o"),"ò","o"),"ū","u"),"ú","u"),"ǔ","u"),"ù","u"),"ǖ","v"),"ǘ","v"),"ǚ","v"),"ǜ","v")
G785: =IF(AND(B785="",C785="",F785=""),"","|"&SUBSTITUTE(SUBSTITUTE(SUBSTITUTE(SUBSTITUTE(SUBSTITUTE(SUBSTITUTE(SUBSTITUTE(SUBSTITUTE(SUBSTITUTE(SUBSTITUTE(SUBSTITUTE(SUBSTITUTE(SUBSTITUTE(SUBSTITUTE(SUBSTITUTE(SUBSTITUTE(LOWER(B785&";"&C785&";"&F785)," ",""),"'",""),"’",""),"·",""),"/",""),"-",""),"(",""),")",""),"（",""),"）",""),"ü","v"),";","|"),"；","|"),",","|"),"，","|"),"、","|")&"|") | H785: =SUBSTITUTE(SUBSTITUTE(SUBSTITUTE(SUBSTITUTE(SUBSTITUTE(SUBSTITUTE(SUBSTITUTE(SUBSTITUTE(SUBSTITUTE(SUBSTITUTE(SUBSTITUTE(SUBSTITUTE(SUBSTITUTE(SUBSTITUTE(SUBSTITUTE(SUBSTITUTE(SUBSTITUTE(SUBSTITUTE(SUBSTITUTE(SUBSTITUTE(SUBSTITUTE(SUBSTITUTE(SUBSTITUTE(SUBSTITUTE(G785,"ā","a"),"á","a"),"ǎ","a"),"à","a"),"ē","e"),"é","e"),"ě","e"),"è","e"),"ī","i"),"í","i"),"ǐ","i"),"ì","i"),"ō","o"),"ó","o"),"ǒ","o"),"ò","o"),"ū","u"),"ú","u"),"ǔ","u"),"ù","u"),"ǖ","v"),"ǘ","v"),"ǚ","v"),"ǜ","v")
... G1001: =IF(AND(B1001="",C1001="",F1001=""),"","|"&SUBSTITUTE(SUBSTITUTE(SUBSTITUTE(SUBSTITUTE(SUBSTITUTE(SUBSTITUTE(SUBSTITUTE(SUBSTITUTE(SUBSTITUTE(SUBSTITUTE(SUBSTITUTE(SUBSTITUTE(SUBSTITUTE(SUBSTITUTE(SUBSTITUTE(SUBSTITUTE(LOWER(B1001&";"&C1001&";"&F1001)," ",""),"'",""),"’",""),"·",""),"/",""),"-",""),"(",""),")",""),"（",""),"）",""),"ü","v"),";","|"),"；","|"),",","|"),"，","|"),"、","|")&"|") | H1001: =SUBSTITUTE(SUBSTITUTE(SUBSTITUTE(SUBSTITUTE(SUBSTITUTE(SUBSTITUTE(SUBSTITUTE(SUBSTITUTE(SUBSTITUTE(SUBSTITUTE(SUBSTITUTE(SUBSTITUTE(SUBSTITUTE(SUBSTITUTE(SUBSTITUTE(SUBSTITUTE(SUBSTITUTE(SUBSTITUTE(SUBSTITUTE(SUBSTITUTE(SUBSTITUTE(SUBSTITUTE(SUBSTITUTE(SUBSTITUTE(G1001,"ā","a"),"á","a"),"ǎ","a"),"à","a"),"ē","e"),"é","e"),"ě","e"),"è","e"),"ī","i"),"í","i"),"ǐ","i"),"ì","i"),"ō","o"),"ó","o"),"ǒ","o"),"ò","o"),"ū","u"),"ú","u"),"ǔ","u"),"ù","u"),"ǖ","v"),"ǘ","v"),"ǚ","v"),"ǜ","v")

Sheet Data_HSK3
A1: STT | B1: Chữ Hán | C1: Pinyin | D1: Từ loại | E1: Nghĩa tiếng Việt | F1: Đáp án chấp nhận (cách nhau bằng dấu ;) — có thể thêm tùy ý | G1: Chuẩn hóa có dấu (tự động) | H1: Chuẩn hóa không dấu (tự động)
A2: 1 | B2: 爱心 | C2: àixīn | D2: danh từ | E2: lòng yêu thương | F2: 爱心; àixīn; aixin | G2: =IF(AND(B2="",C2="",F2=""),"","|"&SUBSTITUTE(SUBSTITUTE(SUBSTITUTE(SUBSTITUTE(SUBSTITUTE(SUBSTITUTE(SUBSTITUTE(SUBSTITUTE(SUBSTITUTE(SUBSTITUTE(SUBSTITUTE(SUBSTITUTE(SUBSTITUTE(SUBSTITUTE(SUBSTITUTE(SUBSTITUTE(LOWER(B2&";"&C2&";"&F2)," ",""),"'",""),"’",""),"·",""),"/",""),"-",""),"(",""),")",""),"（",""),"）",""),"ü","v"),";","|"),"；","|"),",","|"),"，","|"),"、","|")&"|") -> |爱心|àixīn|爱心|àixīn|aixin| | H2: =SUBSTITUTE(SUBSTITUTE(SUBSTITUTE(SUBSTITUTE(SUBSTITUTE(SUBSTITUTE(SUBSTITUTE(SUBSTITUTE(SUBSTITUTE(SUBSTITUTE(SUBSTITUTE(SUBSTITUTE(SUBSTITUTE(SUBSTITUTE(SUBSTITUTE(SUBSTITUTE(SUBSTITUTE(SUBSTITUTE(SUBSTITUTE(SUBSTITUTE(SUBSTITUTE(SUBSTITUTE(SUBSTITUTE(SUBSTITUTE(G2,"ā","a"),"á","a"),"ǎ","a"),"à","a"),"ē","e"),"é","e"),"ě","e"),"è","e"),"ī","i"),"í","i"),"ǐ","i"),"ì","i"),"ō","o"),"ó","o"),"ǒ","o"),"ò","o"),"ū","u"),"ú","u"),"ǔ","u"),"ù","u"),"ǖ","v"),"ǘ","v"),"ǚ","v"),"ǜ","v") -> |爱心|aixin|爱心|aixin|aixin|
A3: 2 | B3: 安排 | C3: ānpái | D3: động từ, danh từ | E3: sắp xếp, bố trí | F3: 安排; ānpái; anpai | G3: =IF(AND(B3="",C3="",F3=""),"","|"&SUBSTITUTE(SUBSTITUTE(SUBSTITUTE(SUBSTITUTE(SUBSTITUTE(SUBSTITUTE(SUBSTITUTE(SUBSTITUTE(SUBSTITUTE(SUBSTITUTE(SUBSTITUTE(SUBSTITUTE(SUBSTITUTE(SUBSTITUTE(SUBSTITUTE(SUBSTITUTE(LOWER(B3&";"&C3&";"&F3)," ",""),"'",""),"’",""),"·",""),"/",""),"-",""),"(",""),")",""),"（",""),"）",""),"ü","v"),";","|"),"；","|"),",","|"),"，","|"),"、","|")&"|") -> |安排|ānpái|安排|ānpái|anpai| | H3: =SUBSTITUTE(SUBSTITUTE(SUBSTITUTE(SUBSTITUTE(SUBSTITUTE(SUBSTITUTE(SUBSTITUTE(SUBSTITUTE(SUBSTITUTE(SUBSTITUTE(SUBSTITUTE(SUBSTITUTE(SUBSTITUTE(SUBSTITUTE(SUBSTITUTE(SUBSTITUTE(SUBSTITUTE(SUBSTITUTE(SUBSTITUTE(SUBSTITUTE(SUBSTITUTE(SUBSTITUTE(SUBSTITUTE(SUBSTITUTE(G3,"ā","a"),"á","a"),"ǎ","a"),"à","a"),"ē","e"),"é","e"),"ě","e"),"è","e"),"ī","i"),"í","i"),"ǐ","i"),"ì","i"),"ō","o"),"ó","o"),"ǒ","o"),"ò","o"),"ū","u"),"ú","u"),"ǔ","u"),"ù","u"),"ǖ","v"),"ǘ","v"),"ǚ","v"),"ǜ","v") -> |安排|anpai|安排|anpai|anpai|
A4: 3 | B4: 安装 | C4: ānzhuāng | D4: động từ | E4: lắp đặt, cài đặt | F4: 安装; ānzhuāng; 装; zhuāng; anzhuang; zhuang | G4: =IF(AND(B4="",C4="",F4=""),"","|"&SUBSTITUTE(SUBSTITUTE(SUBSTITUTE(SUBSTITUTE(SUBSTITUTE(SUBSTITUTE(SUBSTITUTE(SUBSTITUTE(SUBSTITUTE(SUBSTITUTE(SUBSTITUTE(SUBSTITUTE(SUBSTITUTE(SUBSTITUTE(SUBSTITUTE(SUBSTITUTE(LOWER(B4&";"&C4&";"&F4)," ",""),"'",""),"’",""),"·",""),"/",""),"-",""),"(",""),")",""),"（",""),"）",""),"ü","v"),";","|"),"；","|"),",","|"),"，","|"),"、","|")&"|") -> |安装|ānzhuāng|安装|ānzhuāng|装|zhuāng|anzhuang|zhuang| | H4: =SUBSTITUTE(SUBSTITUTE(SUBSTITUTE(SUBSTITUTE(SUBSTITUTE(SUBSTITUTE(SUBSTITUTE(SUBSTITUTE(SUBSTITUTE(SUBSTITUTE(SUBSTITUTE(SUBSTITUTE(SUBSTITUTE(SUBSTITUTE(SUBSTITUTE(SUBSTITUTE(SUBSTITUTE(SUBSTITUTE(SUBSTITUTE(SUBSTITUTE(SUBSTITUTE(SUBSTITUTE(SUBSTITUTE(SUBSTITUTE(G4,"ā","a"),"á","a"),"ǎ","a"),"à","a"),"ē","e"),"é","e"),"ě","e"),"è","e"),"ī","i"),"í","i"),"ǐ","i"),"ì","i"),"ō","o"),"ó","o"),"ǒ","o"),"ò","o"),"ū","u"),"ú","u"),"ǔ","u"),"ù","u"),"ǖ","v"),"ǘ","v"),"ǚ","v"),"ǜ","v") -> |安装|anzhuang|安装|anzhuang|装|zhuang|anzhuang|zhuang|
A5: 4 | B5: 按 | C5: àn | D5: động từ, giới từ | E5: ấn, bấm; theo (1 chữ) | F5: 按; àn; 按照; ànzhào; an; anzhao | G5: =IF(AND(B5="",C5="",F5=""),"","|"&SUBSTITUTE(SUBSTITUTE(SUBSTITUTE(SUBSTITUTE(SUBSTITUTE(SUBSTITUTE(SUBSTITUTE(SUBSTITUTE(SUBSTITUTE(SUBSTITUTE(SUBSTITUTE(SUBSTITUTE(SUBSTITUTE(SUBSTITUTE(SUBSTITUTE(SUBSTITUTE(LOWER(B5&";"&C5&";"&F5)," ",""),"'",""),"’",""),"·",""),"/",""),"-",""),"(",""),")",""),"（",""),"）",""),"ü","v"),";","|"),"；","|"),",","|"),"，","|"),"、","|")&"|") -> |按|àn|按|àn|按照|ànzhào|an|anzhao| | H5: =SUBSTITUTE(SUBSTITUTE(SUBSTITUTE(SUBSTITUTE(SUBSTITUTE(SUBSTITUTE(SUBSTITUTE(SUBSTITUTE(SUBSTITUTE(SUBSTITUTE(SUBSTITUTE(SUBSTITUTE(SUBSTITUTE(SUBSTITUTE(SUBSTITUTE(SUBSTITUTE(SUBSTITUTE(SUBSTITUTE(SUBSTITUTE(SUBSTITUTE(SUBSTITUTE(SUBSTITUTE(SUBSTITUTE(SUBSTITUTE(G5,"ā","a"),"á","a"),"ǎ","a"),"à","a"),"ē","e"),"é","e"),"ě","e"),"è","e"),"ī","i"),"í","i"),"ǐ","i"),"ì","i"),"ō","o"),"ó","o"),"ǒ","o"),"ò","o"),"ū","u"),"ú","u"),"ǔ","u"),"ù","u"),"ǖ","v"),"ǘ","v"),"ǚ","v"),"ǜ","v") -> |按|an|按|an|按照|anzhao|an|anzhao|
A6: 5 | B6: 按照 | C6: ànzhào | D6: giới từ | E6: theo, căn cứ theo | F6: 按照; ànzhào; 按; àn; anzhao; an | G6: =IF(AND(B6="",C6="",F6=""),"","|"&SUBSTITUTE(SUBSTITUTE(SUBSTITUTE(SUBSTITUTE(SUBSTITUTE(SUBSTITUTE(SUBSTITUTE(SUBSTITUTE(SUBSTITUTE(SUBSTITUTE(SUBSTITUTE(SUBSTITUTE(SUBSTITUTE(SUBSTITUTE(SUBSTITUTE(SUBSTITUTE(LOWER(B6&";"&C6&";"&F6)," ",""),"'",""),"’",""),"·",""),"/",""),"-",""),"(",""),")",""),"（",""),"）",""),"ü","v"),";","|"),"；","|"),",","|"),"，","|"),"、","|")&"|") -> |按照|ànzhào|按照|ànzhào|按|àn|anzhao|an| | H6: =SUBSTITUTE(SUBSTITUTE(SUBSTITUTE(SUBSTITUTE(SUBSTITUTE(SUBSTITUTE(SUBSTITUTE(SUBSTITUTE(SUBSTITUTE(SUBSTITUTE(SUBSTITUTE(SUBSTITUTE(SUBSTITUTE(SUBSTITUTE(SUBSTITUTE(SUBSTITUTE(SUBSTITUTE(SUBSTITUTE(SUBSTITUTE(SUBSTITUTE(SUBSTITUTE(SUBSTITUTE(SUBSTITUTE(SUBSTITUTE(G6,"ā","a"),"á","a"),"ǎ","a"),"à","a"),"ē","e"),"é","e"),"ě","e"),"è","e"),"ī","i"),"í","i"),"ǐ","i"),"ì","i"),"ō","o"),"ó","o"),"ǒ","o"),"ò","o"),"ū","u"),"ú","u"),"ǔ","u"),"ù","u"),"ǖ","v"),"ǘ","v"),"ǚ","v"),"ǜ","v") -> |按照|anzhao|按照|anzhao|按|an|anzhao|an|
A7: 6 | B7: 把 | C7: bǎ | D7: giới từ | E7: đem, lấy (giới từ câu chữ 把) | F7: 把; bǎ; ba | G7: =IF(AND(B7="",C7="",F7=""),"","|"&SUBSTITUTE(SUBSTITUTE(SUBSTITUTE(SUBSTITUTE(SUBSTITUTE(SUBSTITUTE(SUBSTITUTE(SUBSTITUTE(SUBSTITUTE(SUBSTITUTE(SUBSTITUTE(SUBSTITUTE(SUBSTITUTE(SUBSTITUTE(SUBSTITUTE(SUBSTITUTE(LOWER(B7&";"&C7&";"&F7)," ",""),"'",""),"’",""),"·",""),"/",""),"-",""),"(",""),")",""),"（",""),"）",""),"ü","v"),";","|"),"；","|"),",","|"),"，","|"),"、","|")&"|") -> |把|bǎ|把|bǎ|ba| | H7: =SUBSTITUTE(SUBSTITUTE(SUBSTITUTE(SUBSTITUTE(SUBSTITUTE(SUBSTITUTE(SUBSTITUTE(SUBSTITUTE(SUBSTITUTE(SUBSTITUTE(SUBSTITUTE(SUBSTITUTE(SUBSTITUTE(SUBSTITUTE(SUBSTITUTE(SUBSTITUTE(SUBSTITUTE(SUBSTITUTE(SUBSTITUTE(SUBSTITUTE(SUBSTITUTE(SUBSTITUTE(SUBSTITUTE(SUBSTITUTE(G7,"ā","a"),"á","a"),"ǎ","a"),"à","a"),"ē","e"),"é","e"),"ě","e"),"è","e"),"ī","i"),"í","i"),"ǐ","i"),"ì","i"),"ō","o"),"ó","o"),"ǒ","o"),"ò","o"),"ū","u"),"ú","u"),"ǔ","u"),"ù","u"),"ǖ","v"),"ǘ","v"),"ǚ","v"),"ǜ","v") -> |把|ba|把|ba|ba|
A8: 7 | B8: 把 | C8: bǎ | D8: lượng từ | E8: cái, chiếc (vật có tay cầm); nắm | F8: 把; bǎ; ba | G8: =IF(AND(B8="",C8="",F8=""),"","|"&SUBSTITUTE(SUBSTITUTE(SUBSTITUTE(SUBSTITUTE(SUBSTITUTE(SUBSTITUTE(SUBSTITUTE(SUBSTITUTE(SUBSTITUTE(SUBSTITUTE(SUBSTITUTE(SUBSTITUTE(SUBSTITUTE(SUBSTITUTE(SUBSTITUTE(SUBSTITUTE(LOWER(B8&";"&C8&";"&F8)," ",""),"'",""),"’",""),"·",""),"/",""),"-",""),"(",""),")",""),"（",""),"）",""),"ü","v"),";","|"),"；","|"),",","|"),"，","|"),"、","|")&"|") -> |把|bǎ|把|bǎ|ba| | H8: =SUBSTITUTE(SUBSTITUTE(SUBSTITUTE(SUBSTITUTE(SUBSTITUTE(SUBSTITUTE(SUBSTITUTE(SUBSTITUTE(SUBSTITUTE(SUBSTITUTE(SUBSTITUTE(SUBSTITUTE(SUBSTITUTE(SUBSTITUTE(SUBSTITUTE(SUBSTITUTE(SUBSTITUTE(SUBSTITUTE(SUBSTITUTE(SUBSTITUTE(SUBSTITUTE(SUBSTITUTE(SUBSTITUTE(SUBSTITUTE(G8,"ā","a"),"á","a"),"ǎ","a"),"à","a"),"ē","e"),"é","e"),"ě","e"),"è","e"),"ī","i"),"í","i"),"ǐ","i"),"ì","i"),"ō","o"),"ó","o"),"ǒ","o"),"ò","o"),"ū","u"),"ú","u"),"ǔ","u"),"ù","u"),"ǖ","v"),"ǘ","v"),"ǚ","v"),"ǜ","v") -> |把|ba|把|ba|ba|
A9: 8 | B9: 把握 | C9: bǎwò | D9: động từ, danh từ | E9: nắm chắc; sự chắc chắn | F9: 把握; bǎwò; bawo | G9: =IF(AND(B9="",C9="",F9=""),"","|"&SUBSTITUTE(SUBSTITUTE(SUBSTITUTE(SUBSTITUTE(SUBSTITUTE(SUBSTITUTE(SUBSTITUTE(SUBSTITUTE(SUBSTITUTE(SUBSTITUTE(SUBSTITUTE(SUBSTITUTE(SUBSTITUTE(SUBSTITUTE(SUBSTITUTE(SUBSTITUTE(LOWER(B9&";"&C9&";"&F9)," ",""),"'",""),"’",""),"·",""),"/",""),"-",""),"(",""),")",""),"（",""),"）",""),"ü","v"),";","|"),"；","|"),",","|"),"，","|"),"、","|")&"|") -> |把握|bǎwò|把握|bǎwò|bawo| | H9: =SUBSTITUTE(SUBSTITUTE(SUBSTITUTE(SUBSTITUTE(SUBSTITUTE(SUBSTITUTE(SUBSTITUTE(SUBSTITUTE(SUBSTITUTE(SUBSTITUTE(SUBSTITUTE(SUBSTITUTE(SUBSTITUTE(SUBSTITUTE(SUBSTITUTE(SUBSTITUTE(SUBSTITUTE(SUBSTITUTE(SUBSTITUTE(SUBSTITUTE(SUBSTITUTE(SUBSTITUTE(SUBSTITUTE(SUBSTITUTE(G9,"ā","a"),"á","a"),"ǎ","a"),"à","a"),"ē","e"),"é","e"),"ě","e"),"è","e"),"ī","i"),"í","i"),"ǐ","i"),"ì","i"),"ō","o"),"ó","o"),"ǒ","o"),"ò","o"),"ū","u"),"ú","u"),"ǔ","u"),"ù","u"),"ǖ","v"),"ǘ","v"),"ǚ","v"),"ǜ","v") -> |把握|bawo|把握|bawo|bawo|
A10: 9 | B10: 白 | C10: bái | D10: phó từ | E10: uổng công, vô ích (phó từ) | F10: 白; bái; 白白; báibái; bai; baibai | G10: =IF(AND(B10="",C10="",F10=""),"","|"&SUBSTITUTE(SUBSTITUTE(SUBSTITUTE(SUBSTITUTE(SUBSTITUTE(SUBSTITUTE(SUBSTITUTE(SUBSTITUTE(SUBSTITUTE(SUBSTITUTE(SUBSTITUTE(SUBSTITUTE(SUBSTITUTE(SUBSTITUTE(SUBSTITUTE(SUBSTITUTE(LOWER(B10&";"&C10&";"&F10)," ",""),"'",""),"’",""),"·",""),"/",""),"-",""),"(",""),")",""),"（",""),"）",""),"ü","v"),";","|"),"；","|"),",","|"),"，","|"),"、","|")&"|") -> |白|bái|白|bái|白白|báibái|bai|baibai| | H10: =SUBSTITUTE(SUBSTITUTE(SUBSTITUTE(SUBSTITUTE(SUBSTITUTE(SUBSTITUTE(SUBSTITUTE(SUBSTITUTE(SUBSTITUTE(SUBSTITUTE(SUBSTITUTE(SUBSTITUTE(SUBSTITUTE(SUBSTITUTE(SUBSTITUTE(SUBSTITUTE(SUBSTITUTE(SUBSTITUTE(SUBSTITUTE(SUBSTITUTE(SUBSTITUTE(SUBSTITUTE(SUBSTITUTE(SUBSTITUTE(G10,"ā","a"),"á","a"),"ǎ","a"),"à","a"),"ē","e"),"é","e"),"ě","e"),"è","e"),"ī","i"),"í","i"),"ǐ","i"),"ì","i"),"ō","o"),"ó","o"),"ǒ","o"),"ò","o"),"ū","u"),"ú","u"),"ǔ","u"),"ù","u"),"ǖ","v"),"ǘ","v"),"ǚ","v"),"ǜ","v") -> |白|bai|白|bai|白白|baibai|bai|baibai|
A11: 10 | B11: 白菜 | C11: báicài | D11: danh từ | E11: cải thảo | F11: 白菜; báicài; baicai | G11: =IF(AND(B11="",C11="",F11=""),"","|"&SUBSTITUTE(SUBSTITUTE(SUBSTITUTE(SUBSTITUTE(SUBSTITUTE(SUBSTITUTE(SUBSTITUTE(SUBSTITUTE(SUBSTITUTE(SUBSTITUTE(SUBSTITUTE(SUBSTITUTE(SUBSTITUTE(SUBSTITUTE(SUBSTITUTE(SUBSTITUTE(LOWER(B11&";"&C11&";"&F11)," ",""),"'",""),"’",""),"·",""),"/",""),"-",""),"(",""),")",""),"（",""),"）",""),"ü","v"),";","|"),"；","|"),",","|"),"，","|"),"、","|")&"|") -> |白菜|báicài|白菜|báicài|baicai| | H11: =SUBSTITUTE(SUBSTITUTE(SUBSTITUTE(SUBSTITUTE(SUBSTITUTE(SUBSTITUTE(SUBSTITUTE(SUBSTITUTE(SUBSTITUTE(SUBSTITUTE(SUBSTITUTE(SUBSTITUTE(SUBSTITUTE(SUBSTITUTE(SUBSTITUTE(SUBSTITUTE(SUBSTITUTE(SUBSTITUTE(SUBSTITUTE(SUBSTITUTE(SUBSTITUTE(SUBSTITUTE(SUBSTITUTE(SUBSTITUTE(G11,"ā","a"),"á","a"),"ǎ","a"),"à","a"),"ē","e"),"é","e"),"ě","e"),"è","e"),"ī","i"),"í","i"),"ǐ","i"),"ì","i"),"ō","o"),"ó","o"),"ǒ","o"),"ò","o"),"ū","u"),"ú","u"),"ǔ","u"),"ù","u"),"ǖ","v"),"ǘ","v"),"ǚ","v"),"ǜ","v") -> |白菜|baicai|白菜|baicai|baicai|
A12: 11 | B12: 班级 | C12: bānjí | D12: danh từ | E12: lớp học, khối lớp (班级) | F12: 班级; bānjí; 班; bān; banji; ban | G12: =IF(AND(B12="",C12="",F12=""),"","|"&SUBSTITUTE(SUBSTITUTE(SUBSTITUTE(SUBSTITUTE(SUBSTITUTE(SUBSTITUTE(SUBSTITUTE(SUBSTITUTE(SUBSTITUTE(SUBSTITUTE(SUBSTITUTE(SUBSTITUTE(SUBSTITUTE(SUBSTITUTE(SUBSTITUTE(SUBSTITUTE(LOWER(B12&";"&C12&";"&F12)," ",""),"'",""),"’",""),"·",""),"/",""),"-",""),"(",""),")",""),"（",""),"）",""),"ü","v"),";","|"),"；","|"),",","|"),"，","|"),"、","|")&"|") -> |班级|bānjí|班级|bānjí|班|bān|banji|ban| | H12: =SUBSTITUTE(SUBSTITUTE(SUBSTITUTE(SUBSTITUTE(SUBSTITUTE(SUBSTITUTE(SUBSTITUTE(SUBSTITUTE(SUBSTITUTE(SUBSTITUTE(SUBSTITUTE(SUBSTITUTE(SUBSTITUTE(SUBSTITUTE(SUBSTITUTE(SUBSTITUTE(SUBSTITUTE(SUBSTITUTE(SUBSTITUTE(SUBSTITUTE(SUBSTITUTE(SUBSTITUTE(SUBSTITUTE(SUBSTITUTE(G12,"ā","a"),"á","a"),"ǎ","a"),"à","a"),"ē","e"),"é","e"),"ě","e"),"è","e"),"ī","i"),"í","i"),"ǐ","i"),"ì","i"),"ō","o"),"ó","o"),"ǒ","o"),"ò","o"),"ū","u"),"ú","u"),"ǔ","u"),"ù","u"),"ǖ","v"),"ǘ","v"),"ǚ","v"),"ǜ","v") -> |班级|banji|班级|banji|班|ban|banji|ban|
A13: 12 | B13: 搬 | C13: bān | D13: động từ | E13: chuyển, khuân, dọn | F13: 搬; bān; ban | G13: =IF(AND(B13="",C13="",F13=""),"","|"&SUBSTITUTE(SUBSTITUTE(SUBSTITUTE(SUBSTITUTE(SUBSTITUTE(SUBSTITUTE(SUBSTITUTE(SUBSTITUTE(SUBSTITUTE(SUBSTITUTE(SUBSTITUTE(SUBSTITUTE(SUBSTITUTE(SUBSTITUTE(SUBSTITUTE(SUBSTITUTE(LOWER(B13&";"&C13&";"&F13)," ",""),"'",""),"’",""),"·",""),"/",""),"-",""),"(",""),")",""),"（",""),"）",""),"ü","v"),";","|"),"；","|"),",","|"),"，","|"),"、","|")&"|") -> |搬|bān|搬|bān|ban| | H13: =SUBSTITUTE(SUBSTITUTE(SUBSTITUTE(SUBSTITUTE(SUBSTITUTE(SUBSTITUTE(SUBSTITUTE(SUBSTITUTE(SUBSTITUTE(SUBSTITUTE(SUBSTITUTE(SUBSTITUTE(SUBSTITUTE(SUBSTITUTE(SUBSTITUTE(SUBSTITUTE(SUBSTITUTE(SUBSTITUTE(SUBSTITUTE(SUBSTITUTE(SUBSTITUTE(SUBSTITUTE(SUBSTITUTE(SUBSTITUTE(G13,"ā","a"),"á","a"),"ǎ","a"),"à","a"),"ē","e"),"é","e"),"ě","e"),"è","e"),"ī","i"),"í","i"),"ǐ","i"),"ì","i"),"ō","o"),"ó","o"),"ǒ","o"),"ò","o"),"ū","u"),"ú","u"),"ǔ","u"),"ù","u"),"ǖ","v"),"ǘ","v"),"ǚ","v"),"ǜ","v") -> |搬|ban|搬|ban|ban|
... A974: 973 | B974: 做客 | C974: zuòkè | D974: cụm từ | E974: làm khách | F974: 做客; zuòkè; zuoke | G974: =IF(AND(B974="",C974="",F974=""),"","|"&SUBSTITUTE(SUBSTITUTE(SUBSTITUTE(SUBSTITUTE(SUBSTITUTE(SUBSTITUTE(SUBSTITUTE(SUBSTITUTE(SUBSTITUTE(SUBSTITUTE(SUBSTITUTE(SUBSTITUTE(SUBSTITUTE(SUBSTITUTE(SUBSTITUTE(SUBSTITUTE(LOWER(B974&";"&C974&";"&F974)," ",""),"'",""),"’",""),"·",""),"/",""),"-",""),"(",""),")",""),"（",""),"）",""),"ü","v"),";","|"),"；","|"),",","|"),"，","|"),"、","|")&"|") -> |做客|zuòkè|做客|zuòkè|zuoke| | H974: =SUBSTITUTE(SUBSTITUTE(SUBSTITUTE(SUBSTITUTE(SUBSTITUTE(SUBSTITUTE(SUBSTITUTE(SUBSTITUTE(SUBSTITUTE(SUBSTITUTE(SUBSTITUTE(SUBSTITUTE(SUBSTITUTE(SUBSTITUTE(SUBSTITUTE(SUBSTITUTE(SUBSTITUTE(SUBSTITUTE(SUBSTITUTE(SUBSTITUTE(SUBSTITUTE(SUBSTITUTE(SUBSTITUTE(SUBSTITUTE(G974,"ā","a"),"á","a"),"ǎ","a"),"à","a"),"ē","e"),"é","e"),"ě","e"),"è","e"),"ī","i"),"í","i"),"ǐ","i"),"ì","i"),"ō","o"),"ó","o"),"ǒ","o"),"ò","o"),"ū","u"),"ú","u"),"ǔ","u"),"ù","u"),"ǖ","v"),"ǘ","v"),"ǚ","v"),"ǜ","v") -> |做客|zuoke|做客|zuoke|zuoke|
G975: =IF(AND(B975="",C975="",F975=""),"","|"&SUBSTITUTE(SUBSTITUTE(SUBSTITUTE(SUBSTITUTE(SUBSTITUTE(SUBSTITUTE(SUBSTITUTE(SUBSTITUTE(SUBSTITUTE(SUBSTITUTE(SUBSTITUTE(SUBSTITUTE(SUBSTITUTE(SUBSTITUTE(SUBSTITUTE(SUBSTITUTE(LOWER(B975&";"&C975&";"&F975)," ",""),"'",""),"’",""),"·",""),"/",""),"-",""),"(",""),")",""),"（",""),"）",""),"ü","v"),";","|"),"；","|"),",","|"),"，","|"),"、","|")&"|") | H975: =SUBSTITUTE(SUBSTITUTE(SUBSTITUTE(SUBSTITUTE(SUBSTITUTE(SUBSTITUTE(SUBSTITUTE(SUBSTITUTE(SUBSTITUTE(SUBSTITUTE(SUBSTITUTE(SUBSTITUTE(SUBSTITUTE(SUBSTITUTE(SUBSTITUTE(SUBSTITUTE(SUBSTITUTE(SUBSTITUTE(SUBSTITUTE(SUBSTITUTE(SUBSTITUTE(SUBSTITUTE(SUBSTITUTE(SUBSTITUTE(G975,"ā","a"),"á","a"),"ǎ","a"),"à","a"),"ē","e"),"é","e"),"ě","e"),"è","e"),"ī","i"),"í","i"),"ǐ","i"),"ì","i"),"ō","o"),"ó","o"),"ǒ","o"),"ò","o"),"ū","u"),"ú","u"),"ǔ","u"),"ù","u"),"ǖ","v"),"ǘ","v"),"ǚ","v"),"ǜ","v")
G976: =IF(AND(B976="",C976="",F976=""),"","|"&SUBSTITUTE(SUBSTITUTE(SUBSTITUTE(SUBSTITUTE(SUBSTITUTE(SUBSTITUTE(SUBSTITUTE(SUBSTITUTE(SUBSTITUTE(SUBSTITUTE(SUBSTITUTE(SUBSTITUTE(SUBSTITUTE(SUBSTITUTE(SUBSTITUTE(SUBSTITUTE(LOWER(B976&";"&C976&";"&F976)," ",""),"'",""),"’",""),"·",""),"/",""),"-",""),"(",""),")",""),"（",""),"）",""),"ü","v"),";","|"),"；","|"),",","|"),"，","|"),"、","|")&"|") | H976: =SUBSTITUTE(SUBSTITUTE(SUBSTITUTE(SUBSTITUTE(SUBSTITUTE(SUBSTITUTE(SUBSTITUTE(SUBSTITUTE(SUBSTITUTE(SUBSTITUTE(SUBSTITUTE(SUBSTITUTE(SUBSTITUTE(SUBSTITUTE(SUBSTITUTE(SUBSTITUTE(SUBSTITUTE(SUBSTITUTE(SUBSTITUTE(SUBSTITUTE(SUBSTITUTE(SUBSTITUTE(SUBSTITUTE(SUBSTITUTE(G976,"ā","a"),"á","a"),"ǎ","a"),"à","a"),"ē","e"),"é","e"),"ě","e"),"è","e"),"ī","i"),"í","i"),"ǐ","i"),"ì","i"),"ō","o"),"ó","o"),"ǒ","o"),"ò","o"),"ū","u"),"ú","u"),"ǔ","u"),"ù","u"),"ǖ","v"),"ǘ","v"),"ǚ","v"),"ǜ","v")
G977: =IF(AND(B977="",C977="",F977=""),"","|"&SUBSTITUTE(SUBSTITUTE(SUBSTITUTE(SUBSTITUTE(SUBSTITUTE(SUBSTITUTE(SUBSTITUTE(SUBSTITUTE(SUBSTITUTE(SUBSTITUTE(SUBSTITUTE(SUBSTITUTE(SUBSTITUTE(SUBSTITUTE(SUBSTITUTE(SUBSTITUTE(LOWER(B977&";"&C977&";"&F977)," ",""),"'",""),"’",""),"·",""),"/",""),"-",""),"(",""),")",""),"（",""),"）",""),"ü","v"),";","|"),"；","|"),",","|"),"，","|"),"、","|")&"|") | H977: =SUBSTITUTE(SUBSTITUTE(SUBSTITUTE(SUBSTITUTE(SUBSTITUTE(SUBSTITUTE(SUBSTITUTE(SUBSTITUTE(SUBSTITUTE(SUBSTITUTE(SUBSTITUTE(SUBSTITUTE(SUBSTITUTE(SUBSTITUTE(SUBSTITUTE(SUBSTITUTE(SUBSTITUTE(SUBSTITUTE(SUBSTITUTE(SUBSTITUTE(SUBSTITUTE(SUBSTITUTE(SUBSTITUTE(SUBSTITUTE(G977,"ā","a"),"á","a"),"ǎ","a"),"à","a"),"ē","e"),"é","e"),"ě","e"),"è","e"),"ī","i"),"í","i"),"ǐ","i"),"ì","i"),"ō","o"),"ó","o"),"ǒ","o"),"ò","o"),"ū","u"),"ú","u"),"ǔ","u"),"ù","u"),"ǖ","v"),"ǘ","v"),"ǚ","v"),"ǜ","v")
G978: =IF(AND(B978="",C978="",F978=""),"","|"&SUBSTITUTE(SUBSTITUTE(SUBSTITUTE(SUBSTITUTE(SUBSTITUTE(SUBSTITUTE(SUBSTITUTE(SUBSTITUTE(SUBSTITUTE(SUBSTITUTE(SUBSTITUTE(SUBSTITUTE(SUBSTITUTE(SUBSTITUTE(SUBSTITUTE(SUBSTITUTE(LOWER(B978&";"&C978&";"&F978)," ",""),"'",""),"’",""),"·",""),"/",""),"-",""),"(",""),")",""),"（",""),"）",""),"ü","v"),";","|"),"；","|"),",","|"),"，","|"),"、","|")&"|") | H978: =SUBSTITUTE(SUBSTITUTE(SUBSTITUTE(SUBSTITUTE(SUBSTITUTE(SUBSTITUTE(SUBSTITUTE(SUBSTITUTE(SUBSTITUTE(SUBSTITUTE(SUBSTITUTE(SUBSTITUTE(SUBSTITUTE(SUBSTITUTE(SUBSTITUTE(SUBSTITUTE(SUBSTITUTE(SUBSTITUTE(SUBSTITUTE(SUBSTITUTE(SUBSTITUTE(SUBSTITUTE(SUBSTITUTE(SUBSTITUTE(G978,"ā","a"),"á","a"),"ǎ","a"),"à","a"),"ē","e"),"é","e"),"ě","e"),"è","e"),"ī","i"),"í","i"),"ǐ","i"),"ì","i"),"ō","o"),"ó","o"),"ǒ","o"),"ò","o"),"ū","u"),"ú","u"),"ǔ","u"),"ù","u"),"ǖ","v"),"ǘ","v"),"ǚ","v"),"ǜ","v")
G979: =IF(AND(B979="",C979="",F979=""),"","|"&SUBSTITUTE(SUBSTITUTE(SUBSTITUTE(SUBSTITUTE(SUBSTITUTE(SUBSTITUTE(SUBSTITUTE(SUBSTITUTE(SUBSTITUTE(SUBSTITUTE(SUBSTITUTE(SUBSTITUTE(SUBSTITUTE(SUBSTITUTE(SUBSTITUTE(SUBSTITUTE(LOWER(B979&";"&C979&";"&F979)," ",""),"'",""),"’",""),"·",""),"/",""),"-",""),"(",""),")",""),"（",""),"）",""),"ü","v"),";","|"),"；","|"),",","|"),"，","|"),"、","|")&"|") | H979: =SUBSTITUTE(SUBSTITUTE(SUBSTITUTE(SUBSTITUTE(SUBSTITUTE(SUBSTITUTE(SUBSTITUTE(SUBSTITUTE(SUBSTITUTE(SUBSTITUTE(SUBSTITUTE(SUBSTITUTE(SUBSTITUTE(SUBSTITUTE(SUBSTITUTE(SUBSTITUTE(SUBSTITUTE(SUBSTITUTE(SUBSTITUTE(SUBSTITUTE(SUBSTITUTE(SUBSTITUTE(SUBSTITUTE(SUBSTITUTE(G979,"ā","a"),"á","a"),"ǎ","a"),"à","a"),"ē","e"),"é","e"),"ě","e"),"è","e"),"ī","i"),"í","i"),"ǐ","i"),"ì","i"),"ō","o"),"ó","o"),"ǒ","o"),"ò","o"),"ū","u"),"ú","u"),"ǔ","u"),"ù","u"),"ǖ","v"),"ǘ","v"),"ǚ","v"),"ǜ","v")
G980: =IF(AND(B980="",C980="",F980=""),"","|"&SUBSTITUTE(SUBSTITUTE(SUBSTITUTE(SUBSTITUTE(SUBSTITUTE(SUBSTITUTE(SUBSTITUTE(SUBSTITUTE(SUBSTITUTE(SUBSTITUTE(SUBSTITUTE(SUBSTITUTE(SUBSTITUTE(SUBSTITUTE(SUBSTITUTE(SUBSTITUTE(LOWER(B980&";"&C980&";"&F980)," ",""),"'",""),"’",""),"·",""),"/",""),"-",""),"(",""),")",""),"（",""),"）",""),"ü","v"),";","|"),"；","|"),",","|"),"，","|"),"、","|")&"|") | H980: =SUBSTITUTE(SUBSTITUTE(SUBSTITUTE(SUBSTITUTE(SUBSTITUTE(SUBSTITUTE(SUBSTITUTE(SUBSTITUTE(SUBSTITUTE(SUBSTITUTE(SUBSTITUTE(SUBSTITUTE(SUBSTITUTE(SUBSTITUTE(SUBSTITUTE(SUBSTITUTE(SUBSTITUTE(SUBSTITUTE(SUBSTITUTE(SUBSTITUTE(SUBSTITUTE(SUBSTITUTE(SUBSTITUTE(SUBSTITUTE(G980,"ā","a"),"á","a"),"ǎ","a"),"à","a"),"ē","e"),"é","e"),"ě","e"),"è","e"),"ī","i"),"í","i"),"ǐ","i"),"ì","i"),"ō","o"),"ó","o"),"ǒ","o"),"ò","o"),"ū","u"),"ú","u"),"ǔ","u"),"ù","u"),"ǖ","v"),"ǘ","v"),"ǚ","v"),"ǜ","v")
G981: =IF(AND(B981="",C981="",F981=""),"","|"&SUBSTITUTE(SUBSTITUTE(SUBSTITUTE(SUBSTITUTE(SUBSTITUTE(SUBSTITUTE(SUBSTITUTE(SUBSTITUTE(SUBSTITUTE(SUBSTITUTE(SUBSTITUTE(SUBSTITUTE(SUBSTITUTE(SUBSTITUTE(SUBSTITUTE(SUBSTITUTE(LOWER(B981&";"&C981&";"&F981)," ",""),"'",""),"’",""),"·",""),"/",""),"-",""),"(",""),")",""),"（",""),"）",""),"ü","v"),";","|"),"；","|"),",","|"),"，","|"),"、","|")&"|") | H981: =SUBSTITUTE(SUBSTITUTE(SUBSTITUTE(SUBSTITUTE(SUBSTITUTE(SUBSTITUTE(SUBSTITUTE(SUBSTITUTE(SUBSTITUTE(SUBSTITUTE(SUBSTITUTE(SUBSTITUTE(SUBSTITUTE(SUBSTITUTE(SUBSTITUTE(SUBSTITUTE(SUBSTITUTE(SUBSTITUTE(SUBSTITUTE(SUBSTITUTE(SUBSTITUTE(SUBSTITUTE(SUBSTITUTE(SUBSTITUTE(G981,"ā","a"),"á","a"),"ǎ","a"),"à","a"),"ē","e"),"é","e"),"ě","e"),"è","e"),"ī","i"),"í","i"),"ǐ","i"),"ì","i"),"ō","o"),"ó","o"),"ǒ","o"),"ò","o"),"ū","u"),"ú","u"),"ǔ","u"),"ù","u"),"ǖ","v"),"ǘ","v"),"ǚ","v"),"ǜ","v")
G982: =IF(AND(B982="",C982="",F982=""),"","|"&SUBSTITUTE(SUBSTITUTE(SUBSTITUTE(SUBSTITUTE(SUBSTITUTE(SUBSTITUTE(SUBSTITUTE(SUBSTITUTE(SUBSTITUTE(SUBSTITUTE(SUBSTITUTE(SUBSTITUTE(SUBSTITUTE(SUBSTITUTE(SUBSTITUTE(SUBSTITUTE(LOWER(B982&";"&C982&";"&F982)," ",""),"'",""),"’",""),"·",""),"/",""),"-",""),"(",""),")",""),"（",""),"）",""),"ü","v"),";","|"),"；","|"),",","|"),"，","|"),"、","|")&"|") | H982: =SUBSTITUTE(SUBSTITUTE(SUBSTITUTE(SUBSTITUTE(SUBSTITUTE(SUBSTITUTE(SUBSTITUTE(SUBSTITUTE(SUBSTITUTE(SUBSTITUTE(SUBSTITUTE(SUBSTITUTE(SUBSTITUTE(SUBSTITUTE(SUBSTITUTE(SUBSTITUTE(SUBSTITUTE(SUBSTITUTE(SUBSTITUTE(SUBSTITUTE(SUBSTITUTE(SUBSTITUTE(SUBSTITUTE(SUBSTITUTE(G982,"ā","a"),"á","a"),"ǎ","a"),"à","a"),"ē","e"),"é","e"),"ě","e"),"è","e"),"ī","i"),"í","i"),"ǐ","i"),"ì","i"),"ō","o"),"ó","o"),"ǒ","o"),"ò","o"),"ū","u"),"ú","u"),"ǔ","u"),"ù","u"),"ǖ","v"),"ǘ","v"),"ǚ","v"),"ǜ","v")
G983: =IF(AND(B983="",C983="",F983=""),"","|"&SUBSTITUTE(SUBSTITUTE(SUBSTITUTE(SUBSTITUTE(SUBSTITUTE(SUBSTITUTE(SUBSTITUTE(SUBSTITUTE(SUBSTITUTE(SUBSTITUTE(SUBSTITUTE(SUBSTITUTE(SUBSTITUTE(SUBSTITUTE(SUBSTITUTE(SUBSTITUTE(LOWER(B983&";"&C983&";"&F983)," ",""),"'",""),"’",""),"·",""),"/",""),"-",""),"(",""),")",""),"（",""),"）",""),"ü","v"),";","|"),"；","|"),",","|"),"，","|"),"、","|")&"|") | H983: =SUBSTITUTE(SUBSTITUTE(SUBSTITUTE(SUBSTITUTE(SUBSTITUTE(SUBSTITUTE(SUBSTITUTE(SUBSTITUTE(SUBSTITUTE(SUBSTITUTE(SUBSTITUTE(SUBSTITUTE(SUBSTITUTE(SUBSTITUTE(SUBSTITUTE(SUBSTITUTE(SUBSTITUTE(SUBSTITUTE(SUBSTITUTE(SUBSTITUTE(SUBSTITUTE(SUBSTITUTE(SUBSTITUTE(SUBSTITUTE(G983,"ā","a"),"á","a"),"ǎ","a"),"à","a"),"ē","e"),"é","e"),"ě","e"),"è","e"),"ī","i"),"í","i"),"ǐ","i"),"ì","i"),"ō","o"),"ó","o"),"ǒ","o"),"ò","o"),"ū","u"),"ú","u"),"ǔ","u"),"ù","u"),"ǖ","v"),"ǘ","v"),"ǚ","v"),"ǜ","v")
G984: =IF(AND(B984="",C984="",F984=""),"","|"&SUBSTITUTE(SUBSTITUTE(SUBSTITUTE(SUBSTITUTE(SUBSTITUTE(SUBSTITUTE(SUBSTITUTE(SUBSTITUTE(SUBSTITUTE(SUBSTITUTE(SUBSTITUTE(SUBSTITUTE(SUBSTITUTE(SUBSTITUTE(SUBSTITUTE(SUBSTITUTE(LOWER(B984&";"&C984&";"&F984)," ",""),"'",""),"’",""),"·",""),"/",""),"-",""),"(",""),")",""),"（",""),"）",""),"ü","v"),";","|"),"；","|"),",","|"),"，","|"),"、","|")&"|") | H984: =SUBSTITUTE(SUBSTITUTE(SUBSTITUTE(SUBSTITUTE(SUBSTITUTE(SUBSTITUTE(SUBSTITUTE(SUBSTITUTE(SUBSTITUTE(SUBSTITUTE(SUBSTITUTE(SUBSTITUTE(SUBSTITUTE(SUBSTITUTE(SUBSTITUTE(SUBSTITUTE(SUBSTITUTE(SUBSTITUTE(SUBSTITUTE(SUBSTITUTE(SUBSTITUTE(SUBSTITUTE(SUBSTITUTE(SUBSTITUTE(G984,"ā","a"),"á","a"),"ǎ","a"),"à","a"),"ē","e"),"é","e"),"ě","e"),"è","e"),"ī","i"),"í","i"),"ǐ","i"),"ì","i"),"ō","o"),"ó","o"),"ǒ","o"),"ò","o"),"ū","u"),"ú","u"),"ǔ","u"),"ù","u"),"ǖ","v"),"ǘ","v"),"ǚ","v"),"ǜ","v")
G985: =IF(AND(B985="",C985="",F985=""),"","|"&SUBSTITUTE(SUBSTITUTE(SUBSTITUTE(SUBSTITUTE(SUBSTITUTE(SUBSTITUTE(SUBSTITUTE(SUBSTITUTE(SUBSTITUTE(SUBSTITUTE(SUBSTITUTE(SUBSTITUTE(SUBSTITUTE(SUBSTITUTE(SUBSTITUTE(SUBSTITUTE(LOWER(B985&";"&C985&";"&F985)," ",""),"'",""),"’",""),"·",""),"/",""),"-",""),"(",""),")",""),"（",""),"）",""),"ü","v"),";","|"),"；","|"),",","|"),"，","|"),"、","|")&"|") | H985: =SUBSTITUTE(SUBSTITUTE(SUBSTITUTE(SUBSTITUTE(SUBSTITUTE(SUBSTITUTE(SUBSTITUTE(SUBSTITUTE(SUBSTITUTE(SUBSTITUTE(SUBSTITUTE(SUBSTITUTE(SUBSTITUTE(SUBSTITUTE(SUBSTITUTE(SUBSTITUTE(SUBSTITUTE(SUBSTITUTE(SUBSTITUTE(SUBSTITUTE(SUBSTITUTE(SUBSTITUTE(SUBSTITUTE(SUBSTITUTE(G985,"ā","a"),"á","a"),"ǎ","a"),"à","a"),"ē","e"),"é","e"),"ě","e"),"è","e"),"ī","i"),"í","i"),"ǐ","i"),"ì","i"),"ō","o"),"ó","o"),"ǒ","o"),"ò","o"),"ū","u"),"ú","u"),"ǔ","u"),"ù","u"),"ǖ","v"),"ǘ","v"),"ǚ","v"),"ǜ","v")
G986: =IF(AND(B986="",C986="",F986=""),"","|"&SUBSTITUTE(SUBSTITUTE(SUBSTITUTE(SUBSTITUTE(SUBSTITUTE(SUBSTITUTE(SUBSTITUTE(SUBSTITUTE(SUBSTITUTE(SUBSTITUTE(SUBSTITUTE(SUBSTITUTE(SUBSTITUTE(SUBSTITUTE(SUBSTITUTE(SUBSTITUTE(LOWER(B986&";"&C986&";"&F986)," ",""),"'",""),"’",""),"·",""),"/",""),"-",""),"(",""),")",""),"（",""),"）",""),"ü","v"),";","|"),"；","|"),",","|"),"，","|"),"、","|")&"|") | H986: =SUBSTITUTE(SUBSTITUTE(SUBSTITUTE(SUBSTITUTE(SUBSTITUTE(SUBSTITUTE(SUBSTITUTE(SUBSTITUTE(SUBSTITUTE(SUBSTITUTE(SUBSTITUTE(SUBSTITUTE(SUBSTITUTE(SUBSTITUTE(SUBSTITUTE(SUBSTITUTE(SUBSTITUTE(SUBSTITUTE(SUBSTITUTE(SUBSTITUTE(SUBSTITUTE(SUBSTITUTE(SUBSTITUTE(SUBSTITUTE(G986,"ā","a"),"á","a"),"ǎ","a"),"à","a"),"ē","e"),"é","e"),"ě","e"),"è","e"),"ī","i"),"í","i"),"ǐ","i"),"ì","i"),"ō","o"),"ó","o"),"ǒ","o"),"ò","o"),"ū","u"),"ú","u"),"ǔ","u"),"ù","u"),"ǖ","v"),"ǘ","v"),"ǚ","v"),"ǜ","v")
... G1201: =IF(AND(B1201="",C1201="",F1201=""),"","|"&SUBSTITUTE(SUBSTITUTE(SUBSTITUTE(SUBSTITUTE(SUBSTITUTE(SUBSTITUTE(SUBSTITUTE(SUBSTITUTE(SUBSTITUTE(SUBSTITUTE(SUBSTITUTE(SUBSTITUTE(SUBSTITUTE(SUBSTITUTE(SUBSTITUTE(SUBSTITUTE(LOWER(B1201&";"&C1201&";"&F1201)," ",""),"'",""),"’",""),"·",""),"/",""),"-",""),"(",""),")",""),"（",""),"）",""),"ü","v"),";","|"),"；","|"),",","|"),"，","|"),"、","|")&"|") | H1201: =SUBSTITUTE(SUBSTITUTE(SUBSTITUTE(SUBSTITUTE(SUBSTITUTE(SUBSTITUTE(SUBSTITUTE(SUBSTITUTE(SUBSTITUTE(SUBSTITUTE(SUBSTITUTE(SUBSTITUTE(SUBSTITUTE(SUBSTITUTE(SUBSTITUTE(SUBSTITUTE(SUBSTITUTE(SUBSTITUTE(SUBSTITUTE(SUBSTITUTE(SUBSTITUTE(SUBSTITUTE(SUBSTITUTE(SUBSTITUTE(G1201,"ā","a"),"á","a"),"ǎ","a"),"à","a"),"ē","e"),"é","e"),"ě","e"),"è","e"),"ī","i"),"í","i"),"ǐ","i"),"ì","i"),"ō","o"),"ó","o"),"ǒ","o"),"ò","o"),"ū","u"),"ú","u"),"ǔ","u"),"ù","u"),"ǖ","v"),"ǘ","v"),"ǚ","v"),"ǜ","v")

Sheet Data_HSK4
A1: STT | B1: Chữ Hán | C1: Pinyin | D1: Từ loại | E1: Nghĩa tiếng Việt | F1: Đáp án chấp nhận (cách nhau bằng dấu ;) — có thể thêm tùy ý | G1: Chuẩn hóa có dấu (tự động) | H1: Chuẩn hóa không dấu (tự động)
A2: 1 | B2: 阿姨 | C2: āyí | E2: cô, dì, thím | F2: 阿姨; āyí; ayi | G2: =IF(AND(B2="",C2="",F2=""),"","|"&SUBSTITUTE(SUBSTITUTE(SUBSTITUTE(SUBSTITUTE(SUBSTITUTE(SUBSTITUTE(SUBSTITUTE(SUBSTITUTE(SUBSTITUTE(SUBSTITUTE(SUBSTITUTE(SUBSTITUTE(SUBSTITUTE(SUBSTITUTE(SUBSTITUTE(SUBSTITUTE(LOWER(B2&";"&C2&";"&F2)," ",""),"'",""),"’",""),"·",""),"/",""),"-",""),"(",""),")",""),"（",""),"）",""),"ü","v"),";","|"),"；","|"),",","|"),"，","|"),"、","|")&"|") -> |阿姨|āyí|阿姨|āyí|ayi| | H2: =SUBSTITUTE(SUBSTITUTE(SUBSTITUTE(SUBSTITUTE(SUBSTITUTE(SUBSTITUTE(SUBSTITUTE(SUBSTITUTE(SUBSTITUTE(SUBSTITUTE(SUBSTITUTE(SUBSTITUTE(SUBSTITUTE(SUBSTITUTE(SUBSTITUTE(SUBSTITUTE(SUBSTITUTE(SUBSTITUTE(SUBSTITUTE(SUBSTITUTE(SUBSTITUTE(SUBSTITUTE(SUBSTITUTE(SUBSTITUTE(G2,"ā","a"),"á","a"),"ǎ","a"),"à","a"),"ē","e"),"é","e"),"ě","e"),"è","e"),"ī","i"),"í","i"),"ǐ","i"),"ì","i"),"ō","o"),"ó","o"),"ǒ","o"),"ò","o"),"ū","u"),"ú","u"),"ǔ","u"),"ù","u"),"ǖ","v"),"ǘ","v"),"ǚ","v"),"ǜ","v") -> |阿姨|ayi|阿姨|ayi|ayi|
A3: 2 | B3: 啊 | C3: a | E3: a, à (thán từ) | F3: 啊; a; 呀; ya | G3: =IF(AND(B3="",C3="",F3=""),"","|"&SUBSTITUTE(SUBSTITUTE(SUBSTITUTE(SUBSTITUTE(SUBSTITUTE(SUBSTITUTE(SUBSTITUTE(SUBSTITUTE(SUBSTITUTE(SUBSTITUTE(SUBSTITUTE(SUBSTITUTE(SUBSTITUTE(SUBSTITUTE(SUBSTITUTE(SUBSTITUTE(LOWER(B3&";"&C3&";"&F3)," ",""),"'",""),"’",""),"·",""),"/",""),"-",""),"(",""),")",""),"（",""),"）",""),"ü","v"),";","|"),"；","|"),",","|"),"，","|"),"、","|")&"|") -> |啊|a|啊|a|呀|ya| | H3: =SUBSTITUTE(SUBSTITUTE(SUBSTITUTE(SUBSTITUTE(SUBSTITUTE(SUBSTITUTE(SUBSTITUTE(SUBSTITUTE(SUBSTITUTE(SUBSTITUTE(SUBSTITUTE(SUBSTITUTE(SUBSTITUTE(SUBSTITUTE(SUBSTITUTE(SUBSTITUTE(SUBSTITUTE(SUBSTITUTE(SUBSTITUTE(SUBSTITUTE(SUBSTITUTE(SUBSTITUTE(SUBSTITUTE(SUBSTITUTE(G3,"ā","a"),"á","a"),"ǎ","a"),"à","a"),"ē","e"),"é","e"),"ě","e"),"è","e"),"ī","i"),"í","i"),"ǐ","i"),"ì","i"),"ō","o"),"ó","o"),"ǒ","o"),"ò","o"),"ū","u"),"ú","u"),"ǔ","u"),"ù","u"),"ǖ","v"),"ǘ","v"),"ǚ","v"),"ǜ","v") -> |啊|a|啊|a|呀|ya|
A4: 3 | B4: 矮 | C4: ǎi | E4: thấp | F4: 矮; ǎi; ai | G4: =IF(AND(B4="",C4="",F4=""),"","|"&SUBSTITUTE(SUBSTITUTE(SUBSTITUTE(SUBSTITUTE(SUBSTITUTE(SUBSTITUTE(SUBSTITUTE(SUBSTITUTE(SUBSTITUTE(SUBSTITUTE(SUBSTITUTE(SUBSTITUTE(SUBSTITUTE(SUBSTITUTE(SUBSTITUTE(SUBSTITUTE(LOWER(B4&";"&C4&";"&F4)," ",""),"'",""),"’",""),"·",""),"/",""),"-",""),"(",""),")",""),"（",""),"）",""),"ü","v"),";","|"),"；","|"),",","|"),"，","|"),"、","|")&"|") -> |矮|ǎi|矮|ǎi|ai| | H4: =SUBSTITUTE(SUBSTITUTE(SUBSTITUTE(SUBSTITUTE(SUBSTITUTE(SUBSTITUTE(SUBSTITUTE(SUBSTITUTE(SUBSTITUTE(SUBSTITUTE(SUBSTITUTE(SUBSTITUTE(SUBSTITUTE(SUBSTITUTE(SUBSTITUTE(SUBSTITUTE(SUBSTITUTE(SUBSTITUTE(SUBSTITUTE(SUBSTITUTE(SUBSTITUTE(SUBSTITUTE(SUBSTITUTE(SUBSTITUTE(G4,"ā","a"),"á","a"),"ǎ","a"),"à","a"),"ē","e"),"é","e"),"ě","e"),"è","e"),"ī","i"),"í","i"),"ǐ","i"),"ì","i"),"ō","o"),"ó","o"),"ǒ","o"),"ò","o"),"ū","u"),"ú","u"),"ǔ","u"),"ù","u"),"ǖ","v"),"ǘ","v"),"ǚ","v"),"ǜ","v") -> |矮|ai|矮|ai|ai|
A5: 4 | B5: 矮小 | C5: ǎixiǎo | E5: thấp bé | F5: 矮小; ǎixiǎo; aixiao | G5: =IF(AND(B5="",C5="",F5=""),"","|"&SUBSTITUTE(SUBSTITUTE(SUBSTITUTE(SUBSTITUTE(SUBSTITUTE(SUBSTITUTE(SUBSTITUTE(SUBSTITUTE(SUBSTITUTE(SUBSTITUTE(SUBSTITUTE(SUBSTITUTE(SUBSTITUTE(SUBSTITUTE(SUBSTITUTE(SUBSTITUTE(LOWER(B5&";"&C5&";"&F5)," ",""),"'",""),"’",""),"·",""),"/",""),"-",""),"(",""),")",""),"（",""),"）",""),"ü","v"),";","|"),"；","|"),",","|"),"，","|"),"、","|")&"|") -> |矮小|ǎixiǎo|矮小|ǎixiǎo|aixiao| | H5: =SUBSTITUTE(SUBSTITUTE(SUBSTITUTE(SUBSTITUTE(SUBSTITUTE(SUBSTITUTE(SUBSTITUTE(SUBSTITUTE(SUBSTITUTE(SUBSTITUTE(SUBSTITUTE(SUBSTITUTE(SUBSTITUTE(SUBSTITUTE(SUBSTITUTE(SUBSTITUTE(SUBSTITUTE(SUBSTITUTE(SUBSTITUTE(SUBSTITUTE(SUBSTITUTE(SUBSTITUTE(SUBSTITUTE(SUBSTITUTE(G5,"ā","a"),"á","a"),"ǎ","a"),"à","a"),"ē","e"),"é","e"),"ě","e"),"è","e"),"ī","i"),"í","i"),"ǐ","i"),"ì","i"),"ō","o"),"ó","o"),"ǒ","o"),"ò","o"),"ū","u"),"ú","u"),"ǔ","u"),"ù","u"),"ǖ","v"),"ǘ","v"),"ǚ","v"),"ǜ","v") -> |矮小|aixiao|矮小|aixiao|aixiao|
A6: 5 | B6: 爱国 | C6: àiguó | E6: yêu nước | F6: 爱国; àiguó; aiguo | G6: =IF(AND(B6="",C6="",F6=""),"","|"&SUBSTITUTE(SUBSTITUTE(SUBSTITUTE(SUBSTITUTE(SUBSTITUTE(SUBSTITUTE(SUBSTITUTE(SUBSTITUTE(SUBSTITUTE(SUBSTITUTE(SUBSTITUTE(SUBSTITUTE(SUBSTITUTE(SUBSTITUTE(SUBSTITUTE(SUBSTITUTE(LOWER(B6&";"&C6&";"&F6)," ",""),"'",""),"’",""),"·",""),"/",""),"-",""),"(",""),")",""),"（",""),"）",""),"ü","v"),";","|"),"；","|"),",","|"),"，","|"),"、","|")&"|") -> |爱国|àiguó|爱国|àiguó|aiguo| | H6: =SUBSTITUTE(SUBSTITUTE(SUBSTITUTE(SUBSTITUTE(SUBSTITUTE(SUBSTITUTE(SUBSTITUTE(SUBSTITUTE(SUBSTITUTE(SUBSTITUTE(SUBSTITUTE(SUBSTITUTE(SUBSTITUTE(SUBSTITUTE(SUBSTITUTE(SUBSTITUTE(SUBSTITUTE(SUBSTITUTE(SUBSTITUTE(SUBSTITUTE(SUBSTITUTE(SUBSTITUTE(SUBSTITUTE(SUBSTITUTE(G6,"ā","a"),"á","a"),"ǎ","a"),"à","a"),"ē","e"),"é","e"),"ě","e"),"è","e"),"ī","i"),"í","i"),"ǐ","i"),"ì","i"),"ō","o"),"ó","o"),"ǒ","o"),"ò","o"),"ū","u"),"ú","u"),"ǔ","u"),"ù","u"),"ǖ","v"),"ǘ","v"),"ǚ","v"),"ǜ","v") -> |爱国|aiguo|爱国|aiguo|aiguo|
A7: 6 | B7: 爱护 | C7: àihù | E7: yêu quý, chăm sóc | F7: 爱护; àihù; aihu | G7: =IF(AND(B7="",C7="",F7=""),"","|"&SUBSTITUTE(SUBSTITUTE(SUBSTITUTE(SUBSTITUTE(SUBSTITUTE(SUBSTITUTE(SUBSTITUTE(SUBSTITUTE(SUBSTITUTE(SUBSTITUTE(SUBSTITUTE(SUBSTITUTE(SUBSTITUTE(SUBSTITUTE(SUBSTITUTE(SUBSTITUTE(LOWER(B7&";"&C7&";"&F7)," ",""),"'",""),"’",""),"·",""),"/",""),"-",""),"(",""),")",""),"（",""),"）",""),"ü","v"),";","|"),"；","|"),",","|"),"，","|"),"、","|")&"|") -> |爱护|àihù|爱护|àihù|aihu| | H7: =SUBSTITUTE(SUBSTITUTE(SUBSTITUTE(SUBSTITUTE(SUBSTITUTE(SUBSTITUTE(SUBSTITUTE(SUBSTITUTE(SUBSTITUTE(SUBSTITUTE(SUBSTITUTE(SUBSTITUTE(SUBSTITUTE(SUBSTITUTE(SUBSTITUTE(SUBSTITUTE(SUBSTITUTE(SUBSTITUTE(SUBSTITUTE(SUBSTITUTE(SUBSTITUTE(SUBSTITUTE(SUBSTITUTE(SUBSTITUTE(G7,"ā","a"),"á","a"),"ǎ","a"),"à","a"),"ē","e"),"é","e"),"ě","e"),"è","e"),"ī","i"),"í","i"),"ǐ","i"),"ì","i"),"ō","o"),"ó","o"),"ǒ","o"),"ò","o"),"ū","u"),"ú","u"),"ǔ","u"),"ù","u"),"ǖ","v"),"ǘ","v"),"ǚ","v"),"ǜ","v") -> |爱护|aihu|爱护|aihu|aihu|
A8: 7 | B8: 安 | C8: ān | E8: yên ổn; lắp đặt | F8: 安; ān; an | G8: =IF(AND(B8="",C8="",F8=""),"","|"&SUBSTITUTE(SUBSTITUTE(SUBSTITUTE(SUBSTITUTE(SUBSTITUTE(SUBSTITUTE(SUBSTITUTE(SUBSTITUTE(SUBSTITUTE(SUBSTITUTE(SUBSTITUTE(SUBSTITUTE(SUBSTITUTE(SUBSTITUTE(SUBSTITUTE(SUBSTITUTE(LOWER(B8&";"&C8&";"&F8)," ",""),"'",""),"’",""),"·",""),"/",""),"-",""),"(",""),")",""),"（",""),"）",""),"ü","v"),";","|"),"；","|"),",","|"),"，","|"),"、","|")&"|") -> |安|ān|安|ān|an| | H8: =SUBSTITUTE(SUBSTITUTE(SUBSTITUTE(SUBSTITUTE(SUBSTITUTE(SUBSTITUTE(SUBSTITUTE(SUBSTITUTE(SUBSTITUTE(SUBSTITUTE(SUBSTITUTE(SUBSTITUTE(SUBSTITUTE(SUBSTITUTE(SUBSTITUTE(SUBSTITUTE(SUBSTITUTE(SUBSTITUTE(SUBSTITUTE(SUBSTITUTE(SUBSTITUTE(SUBSTITUTE(SUBSTITUTE(SUBSTITUTE(G8,"ā","a"),"á","a"),"ǎ","a"),"à","a"),"ē","e"),"é","e"),"ě","e"),"è","e"),"ī","i"),"í","i"),"ǐ","i"),"ì","i"),"ō","o"),"ó","o"),"ǒ","o"),"ò","o"),"ū","u"),"ú","u"),"ǔ","u"),"ù","u"),"ǖ","v"),"ǘ","v"),"ǚ","v"),"ǜ","v") -> |安|an|安|an|an|
A9: 8 | B9: 安置 | C9: ānzhì | E9: bố trí, sắp xếp | F9: 安置; ānzhì; 布置; bùzhì; anzhi; buzhi | G9: =IF(AND(B9="",C9="",F9=""),"","|"&SUBSTITUTE(SUBSTITUTE(SUBSTITUTE(SUBSTITUTE(SUBSTITUTE(SUBSTITUTE(SUBSTITUTE(SUBSTITUTE(SUBSTITUTE(SUBSTITUTE(SUBSTITUTE(SUBSTITUTE(SUBSTITUTE(SUBSTITUTE(SUBSTITUTE(SUBSTITUTE(LOWER(B9&";"&C9&";"&F9)," ",""),"'",""),"’",""),"·",""),"/",""),"-",""),"(",""),")",""),"（",""),"）",""),"ü","v"),";","|"),"；","|"),",","|"),"，","|"),"、","|")&"|") -> |安置|ānzhì|安置|ānzhì|布置|bùzhì|anzhi|buzhi| | H9: =SUBSTITUTE(SUBSTITUTE(SUBSTITUTE(SUBSTITUTE(SUBSTITUTE(SUBSTITUTE(SUBSTITUTE(SUBSTITUTE(SUBSTITUTE(SUBSTITUTE(SUBSTITUTE(SUBSTITUTE(SUBSTITUTE(SUBSTITUTE(SUBSTITUTE(SUBSTITUTE(SUBSTITUTE(SUBSTITUTE(SUBSTITUTE(SUBSTITUTE(SUBSTITUTE(SUBSTITUTE(SUBSTITUTE(SUBSTITUTE(G9,"ā","a"),"á","a"),"ǎ","a"),"à","a"),"ē","e"),"é","e"),"ě","e"),"è","e"),"ī","i"),"í","i"),"ǐ","i"),"ì","i"),"ō","o"),"ó","o"),"ǒ","o"),"ò","o"),"ū","u"),"ú","u"),"ǔ","u"),"ù","u"),"ǖ","v"),"ǘ","v"),"ǚ","v"),"ǜ","v") -> |安置|anzhi|安置|anzhi|布置|buzhi|anzhi|buzhi|
A10: 9 | B10: 按时 | C10: ànshí | E10: đúng giờ | F10: 按时; ànshí; 准时; zhǔnshí; anshi; zhunshi | G10: =IF(AND(B10="",C10="",F10=""),"","|"&SUBSTITUTE(SUBSTITUTE(SUBSTITUTE(SUBSTITUTE(SUBSTITUTE(SUBSTITUTE(SUBSTITUTE(SUBSTITUTE(SUBSTITUTE(SUBSTITUTE(SUBSTITUTE(SUBSTITUTE(SUBSTITUTE(SUBSTITUTE(SUBSTITUTE(SUBSTITUTE(LOWER(B10&";"&C10&";"&F10)," ",""),"'",""),"’",""),"·",""),"/",""),"-",""),"(",""),")",""),"（",""),"）",""),"ü","v"),";","|"),"；","|"),",","|"),"，","|"),"、","|")&"|") -> |按时|ànshí|按时|ànshí|准时|zhǔnshí|anshi|zhunshi| | H10: =SUBSTITUTE(SUBSTITUTE(SUBSTITUTE(SUBSTITUTE(SUBSTITUTE(SUBSTITUTE(SUBSTITUTE(SUBSTITUTE(SUBSTITUTE(SUBSTITUTE(SUBSTITUTE(SUBSTITUTE(SUBSTITUTE(SUBSTITUTE(SUBSTITUTE(SUBSTITUTE(SUBSTITUTE(SUBSTITUTE(SUBSTITUTE(SUBSTITUTE(SUBSTITUTE(SUBSTITUTE(SUBSTITUTE(SUBSTITUTE(G10,"ā","a"),"á","a"),"ǎ","a"),"à","a"),"ē","e"),"é","e"),"ě","e"),"è","e"),"ī","i"),"í","i"),"ǐ","i"),"ì","i"),"ō","o"),"ó","o"),"ǒ","o"),"ò","o"),"ū","u"),"ú","u"),"ǔ","u"),"ù","u"),"ǖ","v"),"ǘ","v"),"ǚ","v"),"ǜ","v") -> |按时|anshi|按时|anshi|准时|zhunshi|anshi|zhunshi|
A11: 10 | B11: 暗 | C11: àn | E11: tối | F11: 暗; àn; an | G11: =IF(AND(B11="",C11="",F11=""),"","|"&SUBSTITUTE(SUBSTITUTE(SUBSTITUTE(SUBSTITUTE(SUBSTITUTE(SUBSTITUTE(SUBSTITUTE(SUBSTITUTE(SUBSTITUTE(SUBSTITUTE(SUBSTITUTE(SUBSTITUTE(SUBSTITUTE(SUBSTITUTE(SUBSTITUTE(SUBSTITUTE(LOWER(B11&";"&C11&";"&F11)," ",""),"'",""),"’",""),"·",""),"/",""),"-",""),"(",""),")",""),"（",""),"）",""),"ü","v"),";","|"),"；","|"),",","|"),"，","|"),"、","|")&"|") -> |暗|àn|暗|àn|an| | H11: =SUBSTITUTE(SUBSTITUTE(SUBSTITUTE(SUBSTITUTE(SUBSTITUTE(SUBSTITUTE(SUBSTITUTE(SUBSTITUTE(SUBSTITUTE(SUBSTITUTE(SUBSTITUTE(SUBSTITUTE(SUBSTITUTE(SUBSTITUTE(SUBSTITUTE(SUBSTITUTE(SUBSTITUTE(SUBSTITUTE(SUBSTITUTE(SUBSTITUTE(SUBSTITUTE(SUBSTITUTE(SUBSTITUTE(SUBSTITUTE(G11,"ā","a"),"á","a"),"ǎ","a"),"à","a"),"ē","e"),"é","e"),"ě","e"),"è","e"),"ī","i"),"í","i"),"ǐ","i"),"ì","i"),"ō","o"),"ó","o"),"ǒ","o"),"ò","o"),"ū","u"),"ú","u"),"ǔ","u"),"ù","u"),"ǖ","v"),"ǘ","v"),"ǚ","v"),"ǜ","v") -> |暗|an|暗|an|an|
A12: 11 | B12: 暗示 | C12: ànshì | E12: ám chỉ, gợi ý | F12: 暗示; ànshì; anshi | G12: =IF(AND(B12="",C12="",F12=""),"","|"&SUBSTITUTE(SUBSTITUTE(SUBSTITUTE(SUBSTITUTE(SUBSTITUTE(SUBSTITUTE(SUBSTITUTE(SUBSTITUTE(SUBSTITUTE(SUBSTITUTE(SUBSTITUTE(SUBSTITUTE(SUBSTITUTE(SUBSTITUTE(SUBSTITUTE(SUBSTITUTE(LOWER(B12&";"&C12&";"&F12)," ",""),"'",""),"’",""),"·",""),"/",""),"-",""),"(",""),")",""),"（",""),"）",""),"ü","v"),";","|"),"；","|"),",","|"),"，","|"),"、","|")&"|") -> |暗示|ànshì|暗示|ànshì|anshi| | H12: =SUBSTITUTE(SUBSTITUTE(SUBSTITUTE(SUBSTITUTE(SUBSTITUTE(SUBSTITUTE(SUBSTITUTE(SUBSTITUTE(SUBSTITUTE(SUBSTITUTE(SUBSTITUTE(SUBSTITUTE(SUBSTITUTE(SUBSTITUTE(SUBSTITUTE(SUBSTITUTE(SUBSTITUTE(SUBSTITUTE(SUBSTITUTE(SUBSTITUTE(SUBSTITUTE(SUBSTITUTE(SUBSTITUTE(SUBSTITUTE(G12,"ā","a"),"á","a"),"ǎ","a"),"à","a"),"ē","e"),"é","e"),"ě","e"),"è","e"),"ī","i"),"í","i"),"ǐ","i"),"ì","i"),"ō","o"),"ó","o"),"ǒ","o"),"ò","o"),"ū","u"),"ú","u"),"ǔ","u"),"ù","u"),"ǖ","v"),"ǘ","v"),"ǚ","v"),"ǜ","v") -> |暗示|anshi|暗示|anshi|anshi|
A13: 12 | B13: 巴士 | C13: bāshì | E13: xe buýt | F13: 巴士; bāshì; 公交车; 公共汽车; bashi | G13: =IF(AND(B13="",C13="",F13=""),"","|"&SUBSTITUTE(SUBSTITUTE(SUBSTITUTE(SUBSTITUTE(SUBSTITUTE(SUBSTITUTE(SUBSTITUTE(SUBSTITUTE(SUBSTITUTE(SUBSTITUTE(SUBSTITUTE(SUBSTITUTE(SUBSTITUTE(SUBSTITUTE(SUBSTITUTE(SUBSTITUTE(LOWER(B13&";"&C13&";"&F13)," ",""),"'",""),"’",""),"·",""),"/",""),"-",""),"(",""),")",""),"（",""),"）",""),"ü","v"),";","|"),"；","|"),",","|"),"，","|"),"、","|")&"|") -> |巴士|bāshì|巴士|bāshì|公交车|公共汽车|bashi| | H13: =SUBSTITUTE(SUBSTITUTE(SUBSTITUTE(SUBSTITUTE(SUBSTITUTE(SUBSTITUTE(SUBSTITUTE(SUBSTITUTE(SUBSTITUTE(SUBSTITUTE(SUBSTITUTE(SUBSTITUTE(SUBSTITUTE(SUBSTITUTE(SUBSTITUTE(SUBSTITUTE(SUBSTITUTE(SUBSTITUTE(SUBSTITUTE(SUBSTITUTE(SUBSTITUTE(SUBSTITUTE(SUBSTITUTE(SUBSTITUTE(G13,"ā","a"),"á","a"),"ǎ","a"),"à","a"),"ē","e"),"é","e"),"ě","e"),"è","e"),"ī","i"),"í","i"),"ǐ","i"),"ì","i"),"ō","o"),"ó","o"),"ǒ","o"),"ò","o"),"ū","u"),"ú","u"),"ǔ","u"),"ù","u"),"ǖ","v"),"ǘ","v"),"ǚ","v"),"ǜ","v") -> |巴士|bashi|巴士|bashi|公交车|公共汽车|bashi|
... A46: 45 | B46: 表扬 | C46: biǎoyáng | E46: khen ngợi | F46: 表扬; biǎoyáng; 称赞; chēngzàn; biaoyang; chengzan | G46: =IF(AND(B46="",C46="",F46=""),"","|"&SUBSTITUTE(SUBSTITUTE(SUBSTITUTE(SUBSTITUTE(SUBSTITUTE(SUBSTITUTE(SUBSTITUTE(SUBSTITUTE(SUBSTITUTE(SUBSTITUTE(SUBSTITUTE(SUBSTITUTE(SUBSTITUTE(SUBSTITUTE(SUBSTITUTE(SUBSTITUTE(LOWER(B46&";"&C46&";"&F46)," ",""),"'",""),"’",""),"·",""),"/",""),"-",""),"(",""),")",""),"（",""),"）",""),"ü","v"),";","|"),"；","|"),",","|"),"，","|"),"、","|")&"|") -> |表扬|biǎoyáng|表扬|biǎoyáng|称赞|chēngzàn|biaoyang|chengzan| | H46: =SUBSTITUTE(SUBSTITUTE(SUBSTITUTE(SUBSTITUTE(SUBSTITUTE(SUBSTITUTE(SUBSTITUTE(SUBSTITUTE(SUBSTITUTE(SUBSTITUTE(SUBSTITUTE(SUBSTITUTE(SUBSTITUTE(SUBSTITUTE(SUBSTITUTE(SUBSTITUTE(SUBSTITUTE(SUBSTITUTE(SUBSTITUTE(SUBSTITUTE(SUBSTITUTE(SUBSTITUTE(SUBSTITUTE(SUBSTITUTE(G46,"ā","a"),"á","a"),"ǎ","a"),"à","a"),"ē","e"),"é","e"),"ě","e"),"è","e"),"ī","i"),"í","i"),"ǐ","i"),"ì","i"),"ō","o"),"ó","o"),"ǒ","o"),"ò","o"),"ū","u"),"ú","u"),"ǔ","u"),"ù","u"),"ǖ","v"),"ǘ","v"),"ǚ","v"),"ǜ","v") -> |表扬|biaoyang|表扬|biaoyang|称赞|chengzan|biaoyang|chengzan|
A47: 46 | B47: 别 | C47: bié | D47: động từ | E47: đừng; chia ra (động từ) | F47: 别; bié; bie | G47: =IF(AND(B47="",C47="",F47=""),"","|"&SUBSTITUTE(SUBSTITUTE(SUBSTITUTE(SUBSTITUTE(SUBSTITUTE(SUBSTITUTE(SUBSTITUTE(SUBSTITUTE(SUBSTITUTE(SUBSTITUTE(SUBSTITUTE(SUBSTITUTE(SUBSTITUTE(SUBSTITUTE(SUBSTITUTE(SUBSTITUTE(LOWER(B47&";"&C47&";"&F47)," ",""),"'",""),"’",""),"·",""),"/",""),"-",""),"(",""),")",""),"（",""),"）",""),"ü","v"),";","|"),"；","|"),",","|"),"，","|"),"、","|")&"|") -> |别|bié|别|bié|bie| | H47: =SUBSTITUTE(SUBSTITUTE(SUBSTITUTE(SUBSTITUTE(SUBSTITUTE(SUBSTITUTE(SUBSTITUTE(SUBSTITUTE(SUBSTITUTE(SUBSTITUTE(SUBSTITUTE(SUBSTITUTE(SUBSTITUTE(SUBSTITUTE(SUBSTITUTE(SUBSTITUTE(SUBSTITUTE(SUBSTITUTE(SUBSTITUTE(SUBSTITUTE(SUBSTITUTE(SUBSTITUTE(SUBSTITUTE(SUBSTITUTE(G47,"ā","a"),"á","a"),"ǎ","a"),"à","a"),"ē","e"),"é","e"),"ě","e"),"è","e"),"ī","i"),"í","i"),"ǐ","i"),"ì","i"),"ō","o"),"ó","o"),"ǒ","o"),"ò","o"),"ū","u"),"ú","u"),"ǔ","u"),"ù","u"),"ǖ","v"),"ǘ","v"),"ǚ","v"),"ǜ","v") -> |别|bie|别|bie|bie|
A48: 47 | B48: 冰 | C48: bīng | E48: đá (lạnh) | F48: 冰; bīng; 冰块; bīngkuài; bing; bingkuai | G48: =IF(AND(B48="",C48="",F48=""),"","|"&SUBSTITUTE(SUBSTITUTE(SUBSTITUTE(SUBSTITUTE(SUBSTITUTE(SUBSTITUTE(SUBSTITUTE(SUBSTITUTE(SUBSTITUTE(SUBSTITUTE(SUBSTITUTE(SUBSTITUTE(SUBSTITUTE(SUBSTITUTE(SUBSTITUTE(SUBSTITUTE(LOWER(B48&";"&C48&";"&F48)," ",""),"'",""),"’",""),"·",""),"/",""),"-",""),"(",""),")",""),"（",""),"）",""),"ü","v"),";","|"),"；","|"),",","|"),"，","|"),"、","|")&"|") -> |冰|bīng|冰|bīng|冰块|bīngkuài|bing|bingkuai| | H48: =SUBSTITUTE(SUBSTITUTE(SUBSTITUTE(SUBSTITUTE(SUBSTITUTE(SUBSTITUTE(SUBSTITUTE(SUBSTITUTE(SUBSTITUTE(SUBSTITUTE(SUBSTITUTE(SUBSTITUTE(SUBSTITUTE(SUBSTITUTE(SUBSTITUTE(SUBSTITUTE(SUBSTITUTE(SUBSTITUTE(SUBSTITUTE(SUBSTITUTE(SUBSTITUTE(SUBSTITUTE(SUBSTITUTE(SUBSTITUTE(G48,"ā","a"),"á","a"),"ǎ","a"),"à","a"),"ē","e"),"é","e"),"ě","e"),"è","e"),"ī","i"),"í","i"),"ǐ","i"),"ì","i"),"ō","o"),"ó","o"),"ǒ","o"),"ò","o"),"ū","u"),"ú","u"),"ǔ","u"),"ù","u"),"ǖ","v"),"ǘ","v"),"ǚ","v"),"ǜ","v") -> |冰|bing|冰|bing|冰块|bingkuai|bing|bingkuai|
A49: 48 | B49: 冰箱 | C49: bīngxiāng | E49: tủ lạnh | F49: 冰箱; bīngxiāng; bingxiang | G49: =IF(AND(B49="",C49="",F49=""),"","|"&SUBSTITUTE(SUBSTITUTE(SUBSTITUTE(SUBSTITUTE(SUBSTITUTE(SUBSTITUTE(SUBSTITUTE(SUBSTITUTE(SUBSTITUTE(SUBSTITUTE(SUBSTITUTE(SUBSTITUTE(SUBSTITUTE(SUBSTITUTE(SUBSTITUTE(SUBSTITUTE(LOWER(B49&";"&C49&";"&F49)," ",""),"'",""),"’",""),"·",""),"/",""),"-",""),"(",""),")",""),"（",""),"）",""),"ü","v"),";","|"),"；","|"),",","|"),"，","|"),"、","|")&"|") -> |冰箱|bīngxiāng|冰箱|bīngxiāng|bingxiang| | H49: =SUBSTITUTE(SUBSTITUTE(SUBSTITUTE(SUBSTITUTE(SUBSTITUTE(SUBSTITUTE(SUBSTITUTE(SUBSTITUTE(SUBSTITUTE(SUBSTITUTE(SUBSTITUTE(SUBSTITUTE(SUBSTITUTE(SUBSTITUTE(SUBSTITUTE(SUBSTITUTE(SUBSTITUTE(SUBSTITUTE(SUBSTITUTE(SUBSTITUTE(SUBSTITUTE(SUBSTITUTE(SUBSTITUTE(SUBSTITUTE(G49,"ā","a"),"á","a"),"ǎ","a"),"à","a"),"ē","e"),"é","e"),"ě","e"),"è","e"),"ī","i"),"í","i"),"ǐ","i"),"ì","i"),"ō","o"),"ó","o"),"ǒ","o"),"ò","o"),"ū","u"),"ú","u"),"ǔ","u"),"ù","u"),"ǖ","v"),"ǘ","v"),"ǚ","v"),"ǜ","v") -> |冰箱|bingxiang|冰箱|bingxiang|bingxiang|
A50: 49 | B50: 冰雪 | C50: bīngxuě | E50: băng tuyết | F50: 冰雪; bīngxuě; bingxue | G50: =IF(AND(B50="",C50="",F50=""),"","|"&SUBSTITUTE(SUBSTITUTE(SUBSTITUTE(SUBSTITUTE(SUBSTITUTE(SUBSTITUTE(SUBSTITUTE(SUBSTITUTE(SUBSTITUTE(SUBSTITUTE(SUBSTITUTE(SUBSTITUTE(SUBSTITUTE(SUBSTITUTE(SUBSTITUTE(SUBSTITUTE(LOWER(B50&";"&C50&";"&F50)," ",""),"'",""),"’",""),"·",""),"/",""),"-",""),"(",""),")",""),"（",""),"）",""),"ü","v"),";","|"),"；","|"),",","|"),"，","|"),"、","|")&"|") -> |冰雪|bīngxuě|冰雪|bīngxuě|bingxue| | H50: =SUBSTITUTE(SUBSTITUTE(SUBSTITUTE(SUBSTITUTE(SUBSTITUTE(SUBSTITUTE(SUBSTITUTE(SUBSTITUTE(SUBSTITUTE(SUBSTITUTE(SUBSTITUTE(SUBSTITUTE(SUBSTITUTE(SUBSTITUTE(SUBSTITUTE(SUBSTITUTE(SUBSTITUTE(SUBSTITUTE(SUBSTITUTE(SUBSTITUTE(SUBSTITUTE(SUBSTITUTE(SUBSTITUTE(SUBSTITUTE(G50,"ā","a"),"á","a"),"ǎ","a"),"à","a"),"ē","e"),"é","e"),"ě","e"),"è","e"),"ī","i"),"í","i"),"ǐ","i"),"ì","i"),"ō","o"),"ó","o"),"ǒ","o"),"ò","o"),"ū","u"),"ú","u"),"ǔ","u"),"ù","u"),"ǖ","v"),"ǘ","v"),"ǚ","v"),"ǜ","v") -> |冰雪|bingxue|冰雪|bingxue|bingxue|
A51: 50 | B51: 兵 | C51: bīng | E51: binh lính | F51: 兵; bīng; 士兵; shìbīng; bing; shibing | G51: =IF(AND(B51="",C51="",F51=""),"","|"&SUBSTITUTE(SUBSTITUTE(SUBSTITUTE(SUBSTITUTE(SUBSTITUTE(SUBSTITUTE(SUBSTITUTE(SUBSTITUTE(SUBSTITUTE(SUBSTITUTE(SUBSTITUTE(SUBSTITUTE(SUBSTITUTE(SUBSTITUTE(SUBSTITUTE(SUBSTITUTE(LOWER(B51&";"&C51&";"&F51)," ",""),"'",""),"’",""),"·",""),"/",""),"-",""),"(",""),")",""),"（",""),"）",""),"ü","v"),";","|"),"；","|"),",","|"),"，","|"),"、","|")&"|") -> |兵|bīng|兵|bīng|士兵|shìbīng|bing|shibing| | H51: =SUBSTITUTE(SUBSTITUTE(SUBSTITUTE(SUBSTITUTE(SUBSTITUTE(SUBSTITUTE(SUBSTITUTE(SUBSTITUTE(SUBSTITUTE(SUBSTITUTE(SUBSTITUTE(SUBSTITUTE(SUBSTITUTE(SUBSTITUTE(SUBSTITUTE(SUBSTITUTE(SUBSTITUTE(SUBSTITUTE(SUBSTITUTE(SUBSTITUTE(SUBSTITUTE(SUBSTITUTE(SUBSTITUTE(SUBSTITUTE(G51,"ā","a"),"á","a"),"ǎ","a"),"à","a"),"ē","e"),"é","e"),"ě","e"),"è","e"),"ī","i"),"í","i"),"ǐ","i"),"ì","i"),"ō","o"),"ó","o"),"ǒ","o"),"ò","o"),"ū","u"),"ú","u"),"ǔ","u"),"ù","u"),"ǖ","v"),"ǘ","v"),"ǚ","v"),"ǜ","v") -> |兵|bing|兵|bing|士兵|shibing|bing|shibing|
A52: 51 | B52: 并 | C52: bìng | D52: động từ | E52: kết hợp, sáp nhập (động từ) | F52: 并; bìng; bing | G52: =IF(AND(B52="",C52="",F52=""),"","|"&SUBSTITUTE(SUBSTITUTE(SUBSTITUTE(SUBSTITUTE(SUBSTITUTE(SUBSTITUTE(SUBSTITUTE(SUBSTITUTE(SUBSTITUTE(SUBSTITUTE(SUBSTITUTE(SUBSTITUTE(SUBSTITUTE(SUBSTITUTE(SUBSTITUTE(SUBSTITUTE(LOWER(B52&";"&C52&";"&F52)," ",""),"'",""),"’",""),"·",""),"/",""),"-",""),"(",""),")",""),"（",""),"）",""),"ü","v"),";","|"),"；","|"),",","|"),"，","|"),"、","|")&"|") -> |并|bìng|并|bìng|bing| | H52: =SUBSTITUTE(SUBSTITUTE(SUBSTITUTE(SUBSTITUTE(SUBSTITUTE(SUBSTITUTE(SUBSTITUTE(SUBSTITUTE(SUBSTITUTE(SUBSTITUTE(SUBSTITUTE(SUBSTITUTE(SUBSTITUTE(SUBSTITUTE(SUBSTITUTE(SUBSTITUTE(SUBSTITUTE(SUBSTITUTE(SUBSTITUTE(SUBSTITUTE(SUBSTITUTE(SUBSTITUTE(SUBSTITUTE(SUBSTITUTE(G52,"ā","a"),"á","a"),"ǎ","a"),"à","a"),"ē","e"),"é","e"),"ě","e"),"è","e"),"ī","i"),"í","i"),"ǐ","i"),"ì","i"),"ō","o"),"ó","o"),"ǒ","o"),"ò","o"),"ū","u"),"ú","u"),"ǔ","u"),"ù","u"),"ǖ","v"),"ǘ","v"),"ǚ","v"),"ǜ","v") -> |并|bing|并|bing|bing|
A53: 52 | B53: 不要紧 | C53: búyàojǐn | E53: không sao | F53: 不要紧; búyàojǐn; buyaojin | G53: =IF(AND(B53="",C53="",F53=""),"","|"&SUBSTITUTE(SUBSTITUTE(SUBSTITUTE(SUBSTITUTE(SUBSTITUTE(SUBSTITUTE(SUBSTITUTE(SUBSTITUTE(SUBSTITUTE(SUBSTITUTE(SUBSTITUTE(SUBSTITUTE(SUBSTITUTE(SUBSTITUTE(SUBSTITUTE(SUBSTITUTE(LOWER(B53&";"&C53&";"&F53)," ",""),"'",""),"’",""),"·",""),"/",""),"-",""),"(",""),")",""),"（",""),"）",""),"ü","v"),";","|"),"；","|"),",","|"),"，","|"),"、","|")&"|") -> |不要紧|búyàojǐn|不要紧|búyàojǐn|buyaojin| | H53: =SUBSTITUTE(SUBSTITUTE(SUBSTITUTE(SUBSTITUTE(SUBSTITUTE(SUBSTITUTE(SUBSTITUTE(SUBSTITUTE(SUBSTITUTE(SUBSTITUTE(SUBSTITUTE(SUBSTITUTE(SUBSTITUTE(SUBSTITUTE(SUBSTITUTE(SUBSTITUTE(SUBSTITUTE(SUBSTITUTE(SUBSTITUTE(SUBSTITUTE(SUBSTITUTE(SUBSTITUTE(SUBSTITUTE(SUBSTITUTE(G53,"ā","a"),"á","a"),"ǎ","a"),"à","a"),"ē","e"),"é","e"),"ě","e"),"è","e"),"ī","i"),"í","i"),"ǐ","i"),"ì","i"),"ō","o"),"ó","o"),"ǒ","o"),"ò","o"),"ū","u"),"ú","u"),"ǔ","u"),"ù","u"),"ǖ","v"),"ǘ","v"),"ǚ","v"),"ǜ","v") -> |不要紧|buyaojin|不要紧|buyaojin|buyaojin|
A54: 53 | B54: 不在乎 | C54: bú zàihu | E54: không để ý, không quan tâm | F54: 不在乎; bú zàihu; bu zaihu | G54: =IF(AND(B54="",C54="",F54=""),"","|"&SUBSTITUTE(SUBSTITUTE(SUBSTITUTE(SUBSTITUTE(SUBSTITUTE(SUBSTITUTE(SUBSTITUTE(SUBSTITUTE(SUBSTITUTE(SUBSTITUTE(SUBSTITUTE(SUBSTITUTE(SUBSTITUTE(SUBSTITUTE(SUBSTITUTE(SUBSTITUTE(LOWER(B54&";"&C54&";"&F54)," ",""),"'",""),"’",""),"·",""),"/",""),"-",""),"(",""),")",""),"（",""),"）",""),"ü","v"),";","|"),"；","|"),",","|"),"，","|"),"、","|")&"|") -> |不在乎|búzàihu|不在乎|búzàihu|buzaihu| | H54: =SUBSTITUTE(SUBSTITUTE(SUBSTITUTE(SUBSTITUTE(SUBSTITUTE(SUBSTITUTE(SUBSTITUTE(SUBSTITUTE(SUBSTITUTE(SUBSTITUTE(SUBSTITUTE(SUBSTITUTE(SUBSTITUTE(SUBSTITUTE(SUBSTITUTE(SUBSTITUTE(SUBSTITUTE(SUBSTITUTE(SUBSTITUTE(SUBSTITUTE(SUBSTITUTE(SUBSTITUTE(SUBSTITUTE(SUBSTITUTE(G54,"ā","a"),"á","a"),"ǎ","a"),"à","a"),"ē","e"),"é","e"),"ě","e"),"è","e"),"ī","i"),"í","i"),"ǐ","i"),"ì","i"),"ō","o"),"ó","o"),"ǒ","o"),"ò","o"),"ū","u"),"ú","u"),"ǔ","u"),"ù","u"),"ǖ","v"),"ǘ","v"),"ǚ","v"),"ǜ","v") -> |不在乎|buzaihu|不在乎|buzaihu|buzaihu|
A55: 54 | B55: 不管 | C55: bùguǎn | E55: bất kể | F55: 不管; bùguǎn; 无论; wúlùn; 不论; búlùn; buguan; wulun; bulun | G55: =IF(AND(B55="",C55="",F55=""),"","|"&SUBSTITUTE(SUBSTITUTE(SUBSTITUTE(SUBSTITUTE(SUBSTITUTE(SUBSTITUTE(SUBSTITUTE(SUBSTITUTE(SUBSTITUTE(SUBSTITUTE(SUBSTITUTE(SUBSTITUTE(SUBSTITUTE(SUBSTITUTE(SUBSTITUTE(SUBSTITUTE(LOWER(B55&";"&C55&";"&F55)," ",""),"'",""),"’",""),"·",""),"/",""),"-",""),"(",""),")",""),"（",""),"）",""),"ü","v"),";","|"),"；","|"),",","|"),"，","|"),"、","|")&"|") -> |不管|bùguǎn|不管|bùguǎn|无论|wúlùn|不论|búlùn|buguan|wulun|bulun| | H55: =SUBSTITUTE(SUBSTITUTE(SUBSTITUTE(SUBSTITUTE(SUBSTITUTE(SUBSTITUTE(SUBSTITUTE(SUBSTITUTE(SUBSTITUTE(SUBSTITUTE(SUBSTITUTE(SUBSTITUTE(SUBSTITUTE(SUBSTITUTE(SUBSTITUTE(SUBSTITUTE(SUBSTITUTE(SUBSTITUTE(SUBSTITUTE(SUBSTITUTE(SUBSTITUTE(SUBSTITUTE(SUBSTITUTE(SUBSTITUTE(G55,"ā","a"),"á","a"),"ǎ","a"),"à","a"),"ē","e"),"é","e"),"ě","e"),"è","e"),"ī","i"),"í","i"),"ǐ","i"),"ì","i"),"ō","o"),"ó","o"),"ǒ","o"),"ò","o"),"ū","u"),"ú","u"),"ǔ","u"),"ù","u"),"ǖ","v"),"ǘ","v"),"ǚ","v"),"ǜ","v") -> |不管|buguan|不管|buguan|无论|wulun|不论|bulun|buguan|wulun|bulun|
A56: 55 | B56: 不然 | C56: bùrán | E56: nếu không thì | F56: 不然; bùrán; 否则; fǒuzé; 要不然; yàobùrán; buran; fouze; yaoburan | G56: =IF(AND(B56="",C56="",F56=""),"","|"&SUBSTITUTE(SUBSTITUTE(SUBSTITUTE(SUBSTITUTE(SUBSTITUTE(SUBSTITUTE(SUBSTITUTE(SUBSTITUTE(SUBSTITUTE(SUBSTITUTE(SUBSTITUTE(SUBSTITUTE(SUBSTITUTE(SUBSTITUTE(SUBSTITUTE(SUBSTITUTE(LOWER(B56&";"&C56&";"&F56)," ",""),"'",""),"’",""),"·",""),"/",""),"-",""),"(",""),")",""),"（",""),"）",""),"ü","v"),";","|"),"；","|"),",","|"),"，","|"),"、","|")&"|") -> |不然|bùrán|不然|bùrán|否则|fǒuzé|要不然|yàobùrán|buran|fouze|yaoburan| | H56: =SUBSTITUTE(SUBSTITUTE(SUBSTITUTE(SUBSTITUTE(SUBSTITUTE(SUBSTITUTE(SUBSTITUTE(SUBSTITUTE(SUBSTITUTE(SUBSTITUTE(SUBSTITUTE(SUBSTITUTE(SUBSTITUTE(SUBSTITUTE(SUBSTITUTE(SUBSTITUTE(SUBSTITUTE(SUBSTITUTE(SUBSTITUTE(SUBSTITUTE(SUBSTITUTE(SUBSTITUTE(SUBSTITUTE(SUBSTITUTE(G56,"ā","a"),"á","a"),"ǎ","a"),"à","a"),"ē","e"),"é","e"),"ě","e"),"è","e"),"ī","i"),"í","i"),"ǐ","i"),"ì","i"),"ō","o"),"ó","o"),"ǒ","o"),"ò","o"),"ū","u"),"ú","u"),"ǔ","u"),"ù","u"),"ǖ","v"),"ǘ","v"),"ǚ","v"),"ǜ","v") -> |不然|buran|不然|buran|否则|fouze|要不然|yaoburan|buran|fouze|yaoburan|
A57: 56 | B57: 布置 | C57: bùzhì | E57: bố trí, sắp xếp | F57: 布置; bùzhì; 安置; ānzhì; buzhi; anzhi | G57: =IF(AND(B57="",C57="",F57=""),"","|"&SUBSTITUTE(SUBSTITUTE(SUBSTITUTE(SUBSTITUTE(SUBSTITUTE(SUBSTITUTE(SUBSTITUTE(SUBSTITUTE(SUBSTITUTE(SUBSTITUTE(SUBSTITUTE(SUBSTITUTE(SUBSTITUTE(SUBSTITUTE(SUBSTITUTE(SUBSTITUTE(LOWER(B57&";"&C57&";"&F57)," ",""),"'",""),"’",""),"·",""),"/",""),"-",""),"(",""),")",""),"（",""),"）",""),"ü","v"),";","|"),"；","|"),",","|"),"，","|"),"、","|")&"|") -> |布置|bùzhì|布置|bùzhì|安置|ānzhì|buzhi|anzhi| | H57: =SUBSTITUTE(SUBSTITUTE(SUBSTITUTE(SUBSTITUTE(SUBSTITUTE(SUBSTITUTE(SUBSTITUTE(SUBSTITUTE(SUBSTITUTE(SUBSTITUTE(SUBSTITUTE(SUBSTITUTE(SUBSTITUTE(SUBSTITUTE(SUBSTITUTE(SUBSTITUTE(SUBSTITUTE(SUBSTITUTE(SUBSTITUTE(SUBSTITUTE(SUBSTITUTE(SUBSTITUTE(SUBSTITUTE(SUBSTITUTE(G57,"ā","a"),"á","a"),"ǎ","a"),"à","a"),"ē","e"),"é","e"),"ě","e"),"è","e"),"ī","i"),"í","i"),"ǐ","i"),"ì","i"),"ō","o"),"ó","o"),"ǒ","o"),"ò","o"),"ū","u"),"ú","u"),"ǔ","u"),"ù","u"),"ǖ","v"),"ǘ","v"),"ǚ","v"),"ǜ","v") -> |布置|buzhi|布置|buzhi|安置|anzhi|buzhi|anzhi|
A58: 57 | B58: 步行 | C58: bùxíng | E58: đi bộ | F58: 步行; bùxíng; buxing | G58: =IF(AND(B58="",C58="",F58=""),"","|"&SUBSTITUTE(SUBSTITUTE(SUBSTITUTE(SUBSTITUTE(SUBSTITUTE(SUBSTITUTE(SUBSTITUTE(SUBSTITUTE(SUBSTITUTE(SUBSTITUTE(SUBSTITUTE(SUBSTITUTE(SUBSTITUTE(SUBSTITUTE(SUBSTITUTE(SUBSTITUTE(LOWER(B58&";"&C58&";"&F58)," ",""),"'",""),"’",""),"·",""),"/",""),"-",""),"(",""),")",""),"（",""),"）",""),"ü","v"),";","|"),"；","|"),",","|"),"，","|"),"、","|")&"|") -> |步行|bùxíng|步行|bùxíng|buxing| | H58: =SUBSTITUTE(SUBSTITUTE(SUBSTITUTE(SUBSTITUTE(SUBSTITUTE(SUBSTITUTE(SUBSTITUTE(SUBSTITUTE(SUBSTITUTE(SUBSTITUTE(SUBSTITUTE(SUBSTITUTE(SUBSTITUTE(SUBSTITUTE(SUBSTITUTE(SUBSTITUTE(SUBSTITUTE(SUBSTITUTE(SUBSTITUTE(SUBSTITUTE(SUBSTITUTE(SUBSTITUTE(SUBSTITUTE(SUBSTITUTE(G58,"ā","a"),"á","a"),"ǎ","a"),"à","a"),"ē","e"),"é","e"),"ě","e"),"è","e"),"ī","i"),"í","i"),"ǐ","i"),"ì","i"),"ō","o"),"ó","o"),"ǒ","o"),"ò","o"),"ū","u"),"ú","u"),"ǔ","u"),"ù","u"),"ǖ","v"),"ǘ","v"),"ǚ","v"),"ǜ","v") -> |步行|buxing|步行|buxing|buxing|
A59: 58 | B59: 擦 | C59: cā | E59: lau | F59: 擦; cā; ca | G59: =IF(AND(B59="",C59="",F59=""),"","|"&SUBSTITUTE(SUBSTITUTE(SUBSTITUTE(SUBSTITUTE(SUBSTITUTE(SUBSTITUTE(SUBSTITUTE(SUBSTITUTE(SUBSTITUTE(SUBSTITUTE(SUBSTITUTE(SUBSTITUTE(SUBSTITUTE(SUBSTITUTE(SUBSTITUTE(SUBSTITUTE(LOWER(B59&";"&C59&";"&F59)," ",""),"'",""),"’",""),"·",""),"/",""),"-",""),"(",""),")",""),"（",""),"）",""),"ü","v"),";","|"),"；","|"),",","|"),"，","|"),"、","|")&"|") -> |擦|cā|擦|cā|ca| | H59: =SUBSTITUTE(SUBSTITUTE(SUBSTITUTE(SUBSTITUTE(SUBSTITUTE(SUBSTITUTE(SUBSTITUTE(SUBSTITUTE(SUBSTITUTE(SUBSTITUTE(SUBSTITUTE(SUBSTITUTE(SUBSTITUTE(SUBSTITUTE(SUBSTITUTE(SUBSTITUTE(SUBSTITUTE(SUBSTITUTE(SUBSTITUTE(SUBSTITUTE(SUBSTITUTE(SUBSTITUTE(SUBSTITUTE(SUBSTITUTE(G59,"ā","a"),"á","a"),"ǎ","a"),"à","a"),"ē","e"),"é","e"),"ě","e"),"è","e"),"ī","i"),"í","i"),"ǐ","i"),"ì","i"),"ō","o"),"ó","o"),"ǒ","o"),"ò","o"),"ū","u"),"ú","u"),"ǔ","u"),"ù","u"),"ǖ","v"),"ǘ","v"),"ǚ","v"),"ǜ","v") -> |擦|ca|擦|ca|ca|
A60: 59 | B60: 才 | C60: cái | D60: danh từ | E60: tài năng (danh từ) | F60: 才; cái; cai | G60: =IF(AND(B60="",C60="",F60=""),"","|"&SUBSTITUTE(SUBSTITUTE(SUBSTITUTE(SUBSTITUTE(SUBSTITUTE(SUBSTITUTE(SUBSTITUTE(SUBSTITUTE(SUBSTITUTE(SUBSTITUTE(SUBSTITUTE(SUBSTITUTE(SUBSTITUTE(SUBSTITUTE(SUBSTITUTE(SUBSTITUTE(LOWER(B60&";"&C60&";"&F60)," ",""),"'",""),"’",""),"·",""),"/",""),"-",""),"(",""),")",""),"（",""),"）",""),"ü","v"),";","|"),"；","|"),",","|"),"，","|"),"、","|")&"|") -> |才|cái|才|cái|cai| | H60: =SUBSTITUTE(SUBSTITUTE(SUBSTITUTE(SUBSTITUTE(SUBSTITUTE(SUBSTITUTE(SUBSTITUTE(SUBSTITUTE(SUBSTITUTE(SUBSTITUTE(SUBSTITUTE(SUBSTITUTE(SUBSTITUTE(SUBSTITUTE(SUBSTITUTE(SUBSTITUTE(SUBSTITUTE(SUBSTITUTE(SUBSTITUTE(SUBSTITUTE(SUBSTITUTE(SUBSTITUTE(SUBSTITUTE(SUBSTITUTE(G60,"ā","a"),"á","a"),"ǎ","a"),"à","a"),"ē","e"),"é","e"),"ě","e"),"è","e"),"ī","i"),"í","i"),"ǐ","i"),"ì","i"),"ō","o"),"ó","o"),"ǒ","o"),"ò","o"),"ū","u"),"ú","u"),"ǔ","u"),"ù","u"),"ǖ","v"),"ǘ","v"),"ǚ","v"),"ǜ","v") -> |才|cai|才|cai|cai|
A61: 60 | B61: 材料 | C61: cáiliào | E61: vật liệu | F61: 材料; cáiliào; cailiao | G61: =IF(AND(B61="",C61="",F61=""),"","|"&SUBSTITUTE(SUBSTITUTE(SUBSTITUTE(SUBSTITUTE(SUBSTITUTE(SUBSTITUTE(SUBSTITUTE(SUBSTITUTE(SUBSTITUTE(SUBSTITUTE(SUBSTITUTE(SUBSTITUTE(SUBSTITUTE(SUBSTITUTE(SUBSTITUTE(SUBSTITUTE(LOWER(B61&";"&C61&";"&F61)," ",""),"'",""),"’",""),"·",""),"/",""),"-",""),"(",""),")",""),"（",""),"）",""),"ü","v"),";","|"),"；","|"),",","|"),"，","|"),"、","|")&"|") -> |材料|cáiliào|材料|cáiliào|cailiao| | H61: =SUBSTITUTE(SUBSTITUTE(SUBSTITUTE(SUBSTITUTE(SUBSTITUTE(SUBSTITUTE(SUBSTITUTE(SUBSTITUTE(SUBSTITUTE(SUBSTITUTE(SUBSTITUTE(SUBSTITUTE(SUBSTITUTE(SUBSTITUTE(SUBSTITUTE(SUBSTITUTE(SUBSTITUTE(SUBSTITUTE(SUBSTITUTE(SUBSTITUTE(SUBSTITUTE(SUBSTITUTE(SUBSTITUTE(SUBSTITUTE(G61,"ā","a"),"á","a"),"ǎ","a"),"à","a"),"ē","e"),"é","e"),"ě","e"),"è","e"),"ī","i"),"í","i"),"ǐ","i"),"ì","i"),"ō","o"),"ó","o"),"ǒ","o"),"ò","o"),"ū","u"),"ú","u"),"ǔ","u"),"ù","u"),"ǖ","v"),"ǘ","v"),"ǚ","v"),"ǜ","v") -> |材料|cailiao|材料|cailiao|cailiao|
A62: 61 | B62: 财产 | C62: cáichǎn | E62: tài sản | F62: 财产; cáichǎn; caichan | G62: =IF(AND(B62="",C62="",F62=""),"","|"&SUBSTITUTE(SUBSTITUTE(SUBSTITUTE(SUBSTITUTE(SUBSTITUTE(SUBSTITUTE(SUBSTITUTE(SUBSTITUTE(SUBSTITUTE(SUBSTITUTE(SUBSTITUTE(SUBSTITUTE(SUBSTITUTE(SUBSTITUTE(SUBSTITUTE(SUBSTITUTE(LOWER(B62&";"&C62&";"&F62)," ",""),"'",""),"’",""),"·",""),"/",""),"-",""),"(",""),")",""),"（",""),"）",""),"ü","v"),";","|"),"；","|"),",","|"),"，","|"),"、","|")&"|") -> |财产|cáichǎn|财产|cáichǎn|caichan| | H62: =SUBSTITUTE(SUBSTITUTE(SUBSTITUTE(SUBSTITUTE(SUBSTITUTE(SUBSTITUTE(SUBSTITUTE(SUBSTITUTE(SUBSTITUTE(SUBSTITUTE(SUBSTITUTE(SUBSTITUTE(SUBSTITUTE(SUBSTITUTE(SUBSTITUTE(SUBSTITUTE(SUBSTITUTE(SUBSTITUTE(SUBSTITUTE(SUBSTITUTE(SUBSTITUTE(SUBSTITUTE(SUBSTITUTE(SUBSTITUTE(G62,"ā","a"),"á","a"),"ǎ","a"),"à","a"),"ē","e"),"é","e"),"ě","e"),"è","e"),"ī","i"),"í","i"),"ǐ","i"),"ì","i"),"ō","o"),"ó","o"),"ǒ","o"),"ò","o"),"ū","u"),"ú","u"),"ǔ","u"),"ù","u"),"ǖ","v"),"ǘ","v"),"ǚ","v"),"ǜ","v") -> |财产|caichan|财产|caichan|caichan|
A63: 62 | B63: 财富 | C63: cáifù | E63: của cải, sự giàu có | F63: 财富; cáifù; caifu | G63: =IF(AND(B63="",C63="",F63=""),"","|"&SUBSTITUTE(SUBSTITUTE(SUBSTITUTE(SUBSTITUTE(SUBSTITUTE(SUBSTITUTE(SUBSTITUTE(SUBSTITUTE(SUBSTITUTE(SUBSTITUTE(SUBSTITUTE(SUBSTITUTE(SUBSTITUTE(SUBSTITUTE(SUBSTITUTE(SUBSTITUTE(LOWER(B63&";"&C63&";"&F63)," ",""),"'",""),"’",""),"·",""),"/",""),"-",""),"(",""),")",""),"（",""),"）",""),"ü","v"),";","|"),"；","|"),",","|"),"，","|"),"、","|")&"|") -> |财富|cáifù|财富|cáifù|caifu| | H63: =SUBSTITUTE(SUBSTITUTE(SUBSTITUTE(SUBSTITUTE(SUBSTITUTE(SUBSTITUTE(SUBSTITUTE(SUBSTITUTE(SUBSTITUTE(SUBSTITUTE(SUBSTITUTE(SUBSTITUTE(SUBSTITUTE(SUBSTITUTE(SUBSTITUTE(SUBSTITUTE(SUBSTITUTE(SUBSTITUTE(SUBSTITUTE(SUBSTITUTE(SUBSTITUTE(SUBSTITUTE(SUBSTITUTE(SUBSTITUTE(G63,"ā","a"),"á","a"),"ǎ","a"),"à","a"),"ē","e"),"é","e"),"ě","e"),"è","e"),"ī","i"),"í","i"),"ǐ","i"),"ì","i"),"ō","o"),"ó","o"),"ǒ","o"),"ò","o"),"ū","u"),"ú","u"),"ǔ","u"),"ù","u"),"ǖ","v"),"ǘ","v"),"ǚ","v"),"ǜ","v") -> |财富|caifu|财富|caifu|caifu|
A64: 63 | B64: 采访 | C64: cǎifǎng | E64: phỏng vấn | F64: 采访; cǎifǎng; 面试; miànshì; caifang; mianshi | G64: =IF(AND(B64="",C64="",F64=""),"","|"&SUBSTITUTE(SUBSTITUTE(SUBSTITUTE(SUBSTITUTE(SUBSTITUTE(SUBSTITUTE(SUBSTITUTE(SUBSTITUTE(SUBSTITUTE(SUBSTITUTE(SUBSTITUTE(SUBSTITUTE(SUBSTITUTE(SUBSTITUTE(SUBSTITUTE(SUBSTITUTE(LOWER(B64&";"&C64&";"&F64)," ",""),"'",""),"’",""),"·",""),"/",""),"-",""),"(",""),")",""),"（",""),"）",""),"ü","v"),";","|"),"；","|"),",","|"),"，","|"),"、","|")&"|") -> |采访|cǎifǎng|采访|cǎifǎng|面试|miànshì|caifang|mianshi| | H64: =SUBSTITUTE(SUBSTITUTE(SUBSTITUTE(SUBSTITUTE(SUBSTITUTE(SUBSTITUTE(SUBSTITUTE(SUBSTITUTE(SUBSTITUTE(SUBSTITUTE(SUBSTITUTE(SUBSTITUTE(SUBSTITUTE(SUBSTITUTE(SUBSTITUTE(SUBSTITUTE(SUBSTITUTE(SUBSTITUTE(SUBSTITUTE(SUBSTITUTE(SUBSTITUTE(SUBSTITUTE(SUBSTITUTE(SUBSTITUTE(G64,"ā","a"),"á","a"),"ǎ","a"),"à","a"),"ē","e"),"é","e"),"ě","e"),"è","e"),"ī","i"),"í","i"),"ǐ","i"),"ì","i"),"ō","o"),"ó","o"),"ǒ","o"),"ò","o"),"ū","u"),"ú","u"),"ǔ","u"),"ù","u"),"ǖ","v"),"ǘ","v"),"ǚ","v"),"ǜ","v") -> |采访|caifang|采访|caifang|面试|mianshi|caifang|mianshi|
A65: 64 | B65: 参考 | C65: cānkǎo | E65: tham khảo | F65: 参考; cānkǎo; cankao | G65: =IF(AND(B65="",C65="",F65=""),"","|"&SUBSTITUTE(SUBSTITUTE(SUBSTITUTE(SUBSTITUTE(SUBSTITUTE(SUBSTITUTE(SUBSTITUTE(SUBSTITUTE(SUBSTITUTE(SUBSTITUTE(SUBSTITUTE(SUBSTITUTE(SUBSTITUTE(SUBSTITUTE(SUBSTITUTE(SUBSTITUTE(LOWER(B65&";"&C65&";"&F65)," ",""),"'",""),"’",""),"·",""),"/",""),"-",""),"(",""),")",""),"（",""),"）",""),"ü","v"),";","|"),"；","|"),",","|"),"，","|"),"、","|")&"|") -> |参考|cānkǎo|参考|cānkǎo|cankao| | H65: =SUBSTITUTE(SUBSTITUTE(SUBSTITUTE(SUBSTITUTE(SUBSTITUTE(SUBSTITUTE(SUBSTITUTE(SUBSTITUTE(SUBSTITUTE(SUBSTITUTE(SUBSTITUTE(SUBSTITUTE(SUBSTITUTE(SUBSTITUTE(SUBSTITUTE(SUBSTITUTE(SUBSTITUTE(SUBSTITUTE(SUBSTITUTE(SUBSTITUTE(SUBSTITUTE(SUBSTITUTE(SUBSTITUTE(SUBSTITUTE(G65,"ā","a"),"á","a"),"ǎ","a"),"à","a"),"ē","e"),"é","e"),"ě","e"),"è","e"),"ī","i"),"í","i"),"ǐ","i"),"ì","i"),"ō","o"),"ó","o"),"ǒ","o"),"ò","o"),"ū","u"),"ú","u"),"ǔ","u"),"ù","u"),"ǖ","v"),"ǘ","v"),"ǚ","v"),"ǜ","v") -> |参考|cankao|参考|cankao|cankao|
A66: 65 | B66: 参与 | C66: cānyù | E66: tham gia | F66: 参与; cānyù; canyu | G66: =IF(AND(B66="",C66="",F66=""),"","|"&SUBSTITUTE(SUBSTITUTE(SUBSTITUTE(SUBSTITUTE(SUBSTITUTE(SUBSTITUTE(SUBSTITUTE(SUBSTITUTE(SUBSTITUTE(SUBSTITUTE(SUBSTITUTE(SUBSTITUTE(SUBSTITUTE(SUBSTITUTE(SUBSTITUTE(SUBSTITUTE(LOWER(B66&";"&C66&";"&F66)," ",""),"'",""),"’",""),"·",""),"/",""),"-",""),"(",""),")",""),"（",""),"）",""),"ü","v"),";","|"),"；","|"),",","|"),"，","|"),"、","|")&"|") -> |参与|cānyù|参与|cānyù|canyu| | H66: =SUBSTITUTE(SUBSTITUTE(SUBSTITUTE(SUBSTITUTE(SUBSTITUTE(SUBSTITUTE(SUBSTITUTE(SUBSTITUTE(SUBSTITUTE(SUBSTITUTE(SUBSTITUTE(SUBSTITUTE(SUBSTITUTE(SUBSTITUTE(SUBSTITUTE(SUBSTITUTE(SUBSTITUTE(SUBSTITUTE(SUBSTITUTE(SUBSTITUTE(SUBSTITUTE(SUBSTITUTE(SUBSTITUTE(SUBSTITUTE(G66,"ā","a"),"á","a"),"ǎ","a"),"à","a"),"ē","e"),"é","e"),"ě","e"),"è","e"),"ī","i"),"í","i"),"ǐ","i"),"ì","i"),"ō","o"),"ó","o"),"ǒ","o"),"ò","o"),"ū","u"),"ú","u"),"ǔ","u"),"ù","u"),"ǖ","v"),"ǘ","v"),"ǚ","v"),"ǜ","v") -> |参与|canyu|参与|canyu|canyu|
A67: 66 | B67: 操场 | C67: cāochǎng | E67: sân thể thao | F67: 操场; cāochǎng; caochang | G67: =IF(AND(B67="",C67="",F67=""),"","|"&SUBSTITUTE(SUBSTITUTE(SUBSTITUTE(SUBSTITUTE(SUBSTITUTE(SUBSTITUTE(SUBSTITUTE(SUBSTITUTE(SUBSTITUTE(SUBSTITUTE(SUBSTITUTE(SUBSTITUTE(SUBSTITUTE(SUBSTITUTE(SUBSTITUTE(SUBSTITUTE(LOWER(B67&";"&C67&";"&F67)," ",""),"'",""),"’",""),"·",""),"/",""),"-",""),"(",""),")",""),"（",""),"）",""),"ü","v"),";","|"),"；","|"),",","|"),"，","|"),"、","|")&"|") -> |操场|cāochǎng|操场|cāochǎng|caochang| | H67: =SUBSTITUTE(SUBSTITUTE(SUBSTITUTE(SUBSTITUTE(SUBSTITUTE(SUBSTITUTE(SUBSTITUTE(SUBSTITUTE(SUBSTITUTE(SUBSTITUTE(SUBSTITUTE(SUBSTITUTE(SUBSTITUTE(SUBSTITUTE(SUBSTITUTE(SUBSTITUTE(SUBSTITUTE(SUBSTITUTE(SUBSTITUTE(SUBSTITUTE(SUBSTITUTE(SUBSTITUTE(SUBSTITUTE(SUBSTITUTE(G67,"ā","a"),"á","a"),"ǎ","a"),"à","a"),"ē","e"),"é","e"),"ě","e"),"è","e"),"ī","i"),"í","i"),"ǐ","i"),"ì","i"),"ō","o"),"ó","o"),"ǒ","o"),"ò","o"),"ū","u"),"ú","u"),"ǔ","u"),"ù","u"),"ǖ","v"),"ǘ","v"),"ǚ","v"),"ǜ","v") -> |操场|caochang|操场|caochang|caochang|
A68: 67 | B68: 操作 | C68: cāozuò | E68: thao tác, vận hành | F68: 操作; cāozuò; 操纵; cāozòng; caozuo; caozong | G68: =IF(AND(B68="",C68="",F68=""),"","|"&SUBSTITUTE(SUBSTITUTE(SUBSTITUTE(SUBSTITUTE(SUBSTITUTE(SUBSTITUTE(SUBSTITUTE(SUBSTITUTE(SUBSTITUTE(SUBSTITUTE(SUBSTITUTE(SUBSTITUTE(SUBSTITUTE(SUBSTITUTE(SUBSTITUTE(SUBSTITUTE(LOWER(B68&";"&C68&";"&F68)," ",""),"'",""),"’",""),"·",""),"/",""),"-",""),"(",""),")",""),"（",""),"）",""),"ü","v"),";","|"),"；","|"),",","|"),"，","|"),"、","|")&"|") -> |操作|cāozuò|操作|cāozuò|操纵|cāozòng|caozuo|caozong| | H68: =SUBSTITUTE(SUBSTITUTE(SUBSTITUTE(SUBSTITUTE(SUBSTITUTE(SUBSTITUTE(SUBSTITUTE(SUBSTITUTE(SUBSTITUTE(SUBSTITUTE(SUBSTITUTE(SUBSTITUTE(SUBSTITUTE(SUBSTITUTE(SUBSTITUTE(SUBSTITUTE(SUBSTITUTE(SUBSTITUTE(SUBSTITUTE(SUBSTITUTE(SUBSTITUTE(SUBSTITUTE(SUBSTITUTE(SUBSTITUTE(G68,"ā","a"),"á","a"),"ǎ","a"),"à","a"),"ē","e"),"é","e"),"ě","e"),"è","e"),"ī","i"),"í","i"),"ǐ","i"),"ì","i"),"ō","o"),"ó","o"),"ǒ","o"),"ò","o"),"ū","u"),"ú","u"),"ǔ","u"),"ù","u"),"ǖ","v"),"ǘ","v"),"ǚ","v"),"ǜ","v") -> |操作|caozuo|操作|caozuo|操纵|caozong|caozuo|caozong|
A69: 68 | B69: 测 | C69: cè | E69: đo lường | F69: 测; cè; ce | G69: =IF(AND(B69="",C69="",F69=""),"","|"&SUBSTITUTE(SUBSTITUTE(SUBSTITUTE(SUBSTITUTE(SUBSTITUTE(SUBSTITUTE(SUBSTITUTE(SUBSTITUTE(SUBSTITUTE(SUBSTITUTE(SUBSTITUTE(SUBSTITUTE(SUBSTITUTE(SUBSTITUTE(SUBSTITUTE(SUBSTITUTE(LOWER(B69&";"&C69&";"&F69)," ",""),"'",""),"’",""),"·",""),"/",""),"-",""),"(",""),")",""),"（",""),"）",""),"ü","v"),";","|"),"；","|"),",","|"),"，","|"),"、","|")&"|") -> |测|cè|测|cè|ce| | H69: =SUBSTITUTE(SUBSTITUTE(SUBSTITUTE(SUBSTITUTE(SUBSTITUTE(SUBSTITUTE(SUBSTITUTE(SUBSTITUTE(SUBSTITUTE(SUBSTITUTE(SUBSTITUTE(SUBSTITUTE(SUBSTITUTE(SUBSTITUTE(SUBSTITUTE(SUBSTITUTE(SUBSTITUTE(SUBSTITUTE(SUBSTITUTE(SUBSTITUTE(SUBSTITUTE(SUBSTITUTE(SUBSTITUTE(SUBSTITUTE(G69,"ā","a"),"á","a"),"ǎ","a"),"à","a"),"ē","e"),"é","e"),"ě","e"),"è","e"),"ī","i"),"í","i"),"ǐ","i"),"ì","i"),"ō","o"),"ó","o"),"ǒ","o"),"ò","o"),"ū","u"),"ú","u"),"ǔ","u"),"ù","u"),"ǖ","v"),"ǘ","v"),"ǚ","v"),"ǜ","v") -> |测|ce|测|ce|ce|
A70: 69 | B70: 测量 | C70: cèliáng | E70: đo đạc | F70: 测量; cèliáng; celiang | G70: =IF(AND(B70="",C70="",F70=""),"","|"&SUBSTITUTE(SUBSTITUTE(SUBSTITUTE(SUBSTITUTE(SUBSTITUTE(SUBSTITUTE(SUBSTITUTE(SUBSTITUTE(SUBSTITUTE(SUBSTITUTE(SUBSTITUTE(SUBSTITUTE(SUBSTITUTE(SUBSTITUTE(SUBSTITUTE(SUBSTITUTE(LOWER(B70&";"&C70&";"&F70)," ",""),"'",""),"’",""),"·",""),"/",""),"-",""),"(",""),")",""),"（",""),"）",""),"ü","v"),";","|"),"；","|"),",","|"),"，","|"),"、","|")&"|") -> |测量|cèliáng|测量|cèliáng|celiang| | H70: =SUBSTITUTE(SUBSTITUTE(SUBSTITUTE(SUBSTITUTE(SUBSTITUTE(SUBSTITUTE(SUBSTITUTE(SUBSTITUTE(SUBSTITUTE(SUBSTITUTE(SUBSTITUTE(SUBSTITUTE(SUBSTITUTE(SUBSTITUTE(SUBSTITUTE(SUBSTITUTE(SUBSTITUTE(SUBSTITUTE(SUBSTITUTE(SUBSTITUTE(SUBSTITUTE(SUBSTITUTE(SUBSTITUTE(SUBSTITUTE(G70,"ā","a"),"á","a"),"ǎ","a"),"à","a"),"ē","e"),"é","e"),"ě","e"),"è","e"),"ī","i"),"í","i"),"ǐ","i"),"ì","i"),"ō","o"),"ó","o"),"ǒ","o"),"ò","o"),"ū","u"),"ú","u"),"ǔ","u"),"ù","u"),"ǖ","v"),"ǘ","v"),"ǚ","v"),"ǜ","v") -> |测量|celiang|测量|celiang|celiang|
A71: 70 | B71: 测试 | C71: cèshì | E71: kiểm tra | F71: 测试; cèshì; 检测; jiǎncè; ceshi; jiance | G71: =IF(AND(B71="",C71="",F71=""),"","|"&SUBSTITUTE(SUBSTITUTE(SUBSTITUTE(SUBSTITUTE(SUBSTITUTE(SUBSTITUTE(SUBSTITUTE(SUBSTITUTE(SUBSTITUTE(SUBSTITUTE(SUBSTITUTE(SUBSTITUTE(SUBSTITUTE(SUBSTITUTE(SUBSTITUTE(SUBSTITUTE(LOWER(B71&";"&C71&";"&F71)," ",""),"'",""),"’",""),"·",""),"/",""),"-",""),"(",""),")",""),"（",""),"）",""),"ü","v"),";","|"),"；","|"),",","|"),"，","|"),"、","|")&"|") -> |测试|cèshì|测试|cèshì|检测|jiǎncè|ceshi|jiance| | H71: =SUBSTITUTE(SUBSTITUTE(SUBSTITUTE(SUBSTITUTE(SUBSTITUTE(SUBSTITUTE(SUBSTITUTE(SUBSTITUTE(SUBSTITUTE(SUBSTITUTE(SUBSTITUTE(SUBSTITUTE(SUBSTITUTE(SUBSTITUTE(SUBSTITUTE(SUBSTITUTE(SUBSTITUTE(SUBSTITUTE(SUBSTITUTE(SUBSTITUTE(SUBSTITUTE(SUBSTITUTE(SUBSTITUTE(SUBSTITUTE(G71,"ā","a"),"á","a"),"ǎ","a"),"à","a"),"ē","e"),"é","e"),"ě","e"),"è","e"),"ī","i"),"í","i"),"ǐ","i"),"ì","i"),"ō","o"),"ó","o"),"ǒ","o"),"ò","o"),"ū","u"),"ú","u"),"ǔ","u"),"ù","u"),"ǖ","v"),"ǘ","v"),"ǚ","v"),"ǜ","v") -> |测试|ceshi|测试|ceshi|检测|jiance|ceshi|jiance|
A72: 71 | B72: 曾 | C72: céng | E72: đã từng | F72: 曾; céng; ceng | G72: =IF(AND(B72="",C72="",F72=""),"","|"&SUBSTITUTE(SUBSTITUTE(SUBSTITUTE(SUBSTITUTE(SUBSTITUTE(SUBSTITUTE(SUBSTITUTE(SUBSTITUTE(SUBSTITUTE(SUBSTITUTE(SUBSTITUTE(SUBSTITUTE(SUBSTITUTE(SUBSTITUTE(SUBSTITUTE(SUBSTITUTE(LOWER(B72&";"&C72&";"&F72)," ",""),"'",""),"’",""),"·",""),"/",""),"-",""),"(",""),")",""),"（",""),"）",""),"ü","v"),";","|"),"；","|"),",","|"),"，","|"),"、","|")&"|") -> |曾|céng|曾|céng|ceng| | H72: =SUBSTITUTE(SUBSTITUTE(SUBSTITUTE(SUBSTITUTE(SUBSTITUTE(SUBSTITUTE(SUBSTITUTE(SUBSTITUTE(SUBSTITUTE(SUBSTITUTE(SUBSTITUTE(SUBSTITUTE(SUBSTITUTE(SUBSTITUTE(SUBSTITUTE(SUBSTITUTE(SUBSTITUTE(SUBSTITUTE(SUBSTITUTE(SUBSTITUTE(SUBSTITUTE(SUBSTITUTE(SUBSTITUTE(SUBSTITUTE(G72,"ā","a"),"á","a"),"ǎ","a"),"à","a"),"ē","e"),"é","e"),"ě","e"),"è","e"),"ī","i"),"í","i"),"ǐ","i"),"ì","i"),"ō","o"),"ó","o"),"ǒ","o"),"ò","o"),"ū","u"),"ú","u"),"ǔ","u"),"ù","u"),"ǖ","v"),"ǘ","v"),"ǚ","v"),"ǜ","v") -> |曾|ceng|曾|ceng|ceng|
... A124: 123 | B124: 此外 | C124: cǐwài | E124: ngoài ra | F124: 此外; cǐwài; ciwai | G124: =IF(AND(B124="",C124="",F124=""),"","|"&SUBSTITUTE(SUBSTITUTE(SUBSTITUTE(SUBSTITUTE(SUBSTITUTE(SUBSTITUTE(SUBSTITUTE(SUBSTITUTE(SUBSTITUTE(SUBSTITUTE(SUBSTITUTE(SUBSTITUTE(SUBSTITUTE(SUBSTITUTE(SUBSTITUTE(SUBSTITUTE(LOWER(B124&";"&C124&";"&F124)," ",""),"'",""),"’",""),"·",""),"/",""),"-",""),"(",""),")",""),"（",""),"）",""),"ü","v"),";","|"),"；","|"),",","|"),"，","|"),"、","|")&"|") -> |此外|cǐwài|此外|cǐwài|ciwai| | H124: =SUBSTITUTE(SUBSTITUTE(SUBSTITUTE(SUBSTITUTE(SUBSTITUTE(SUBSTITUTE(SUBSTITUTE(SUBSTITUTE(SUBSTITUTE(SUBSTITUTE(SUBSTITUTE(SUBSTITUTE(SUBSTITUTE(SUBSTITUTE(SUBSTITUTE(SUBSTITUTE(SUBSTITUTE(SUBSTITUTE(SUBSTITUTE(SUBSTITUTE(SUBSTITUTE(SUBSTITUTE(SUBSTITUTE(SUBSTITUTE(G124,"ā","a"),"á","a"),"ǎ","a"),"à","a"),"ē","e"),"é","e"),"ě","e"),"è","e"),"ī","i"),"í","i"),"ǐ","i"),"ì","i"),"ō","o"),"ó","o"),"ǒ","o"),"ò","o"),"ū","u"),"ú","u"),"ǔ","u"),"ù","u"),"ǖ","v"),"ǘ","v"),"ǚ","v"),"ǜ","v") -> |此外|ciwai|此外|ciwai|ciwai|
A125: 124 | B125: 次 | C125: cì | D125: tính từ | E125: thứ cấp (tính từ) | F125: 次; cì; ci | G125: =IF(AND(B125="",C125="",F125=""),"","|"&SUBSTITUTE(SUBSTITUTE(SUBSTITUTE(SUBSTITUTE(SUBSTITUTE(SUBSTITUTE(SUBSTITUTE(SUBSTITUTE(SUBSTITUTE(SUBSTITUTE(SUBSTITUTE(SUBSTITUTE(SUBSTITUTE(SUBSTITUTE(SUBSTITUTE(SUBSTITUTE(LOWER(B125&";"&C125&";"&F125)," ",""),"'",""),"’",""),"·",""),"/",""),"-",""),"(",""),")",""),"（",""),"）",""),"ü","v"),";","|"),"；","|"),",","|"),"，","|"),"、","|")&"|") -> |次|cì|次|cì|ci| | H125: =SUBSTITUTE(SUBSTITUTE(SUBSTITUTE(SUBSTITUTE(SUBSTITUTE(SUBSTITUTE(SUBSTITUTE(SUBSTITUTE(SUBSTITUTE(SUBSTITUTE(SUBSTITUTE(SUBSTITUTE(SUBSTITUTE(SUBSTITUTE(SUBSTITUTE(SUBSTITUTE(SUBSTITUTE(SUBSTITUTE(SUBSTITUTE(SUBSTITUTE(SUBSTITUTE(SUBSTITUTE(SUBSTITUTE(SUBSTITUTE(G125,"ā","a"),"á","a"),"ǎ","a"),"à","a"),"ē","e"),"é","e"),"ě","e"),"è","e"),"ī","i"),"í","i"),"ǐ","i"),"ì","i"),"ō","o"),"ó","o"),"ǒ","o"),"ò","o"),"ū","u"),"ú","u"),"ǔ","u"),"ù","u"),"ǖ","v"),"ǘ","v"),"ǚ","v"),"ǜ","v") -> |次|ci|次|ci|ci|
A126: 125 | B126: 刺 | C126: cì | E126: gai, đâm | F126: 刺; cì; ci | G126: =IF(AND(B126="",C126="",F126=""),"","|"&SUBSTITUTE(SUBSTITUTE(SUBSTITUTE(SUBSTITUTE(SUBSTITUTE(SUBSTITUTE(SUBSTITUTE(SUBSTITUTE(SUBSTITUTE(SUBSTITUTE(SUBSTITUTE(SUBSTITUTE(SUBSTITUTE(SUBSTITUTE(SUBSTITUTE(SUBSTITUTE(LOWER(B126&";"&C126&";"&F126)," ",""),"'",""),"’",""),"·",""),"/",""),"-",""),"(",""),")",""),"（",""),"）",""),"ü","v"),";","|"),"；","|"),",","|"),"，","|"),"、","|")&"|") -> |刺|cì|刺|cì|ci| | H126: =SUBSTITUTE(SUBSTITUTE(SUBSTITUTE(SUBSTITUTE(SUBSTITUTE(SUBSTITUTE(SUBSTITUTE(SUBSTITUTE(SUBSTITUTE(SUBSTITUTE(SUBSTITUTE(SUBSTITUTE(SUBSTITUTE(SUBSTITUTE(SUBSTITUTE(SUBSTITUTE(SUBSTITUTE(SUBSTITUTE(SUBSTITUTE(SUBSTITUTE(SUBSTITUTE(SUBSTITUTE(SUBSTITUTE(SUBSTITUTE(G126,"ā","a"),"á","a"),"ǎ","a"),"à","a"),"ē","e"),"é","e"),"ě","e"),"è","e"),"ī","i"),"í","i"),"ǐ","i"),"ì","i"),"ō","o"),"ó","o"),"ǒ","o"),"ò","o"),"ū","u"),"ú","u"),"ǔ","u"),"ù","u"),"ǖ","v"),"ǘ","v"),"ǚ","v"),"ǜ","v") -> |刺|ci|刺|ci|ci|
A127: 126 | B127: 刺激 | C127: cìjī | E127: kích thích | F127: 刺激; cìjī; ciji | G127: =IF(AND(B127="",C127="",F127=""),"","|"&SUBSTITUTE(SUBSTITUTE(SUBSTITUTE(SUBSTITUTE(SUBSTITUTE(SUBSTITUTE(SUBSTITUTE(SUBSTITUTE(SUBSTITUTE(SUBSTITUTE(SUBSTITUTE(SUBSTITUTE(SUBSTITUTE(SUBSTITUTE(SUBSTITUTE(SUBSTITUTE(LOWER(B127&";"&C127&";"&F127)," ",""),"'",""),"’",""),"·",""),"/",""),"-",""),"(",""),")",""),"（",""),"）",""),"ü","v"),";","|"),"；","|"),",","|"),"，","|"),"、","|")&"|") -> |刺激|cìjī|刺激|cìjī|ciji| | H127: =SUBSTITUTE(SUBSTITUTE(SUBSTITUTE(SUBSTITUTE(SUBSTITUTE(SUBSTITUTE(SUBSTITUTE(SUBSTITUTE(SUBSTITUTE(SUBSTITUTE(SUBSTITUTE(SUBSTITUTE(SUBSTITUTE(SUBSTITUTE(SUBSTITUTE(SUBSTITUTE(SUBSTITUTE(SUBSTITUTE(SUBSTITUTE(SUBSTITUTE(SUBSTITUTE(SUBSTITUTE(SUBSTITUTE(SUBSTITUTE(G127,"ā","a"),"á","a"),"ǎ","a"),"à","a"),"ē","e"),"é","e"),"ě","e"),"è","e"),"ī","i"),"í","i"),"ǐ","i"),"ì","i"),"ō","o"),"ó","o"),"ǒ","o"),"ò","o"),"ū","u"),"ú","u"),"ǔ","u"),"ù","u"),"ǖ","v"),"ǘ","v"),"ǚ","v"),"ǜ","v") -> |刺激|ciji|刺激|ciji|ciji|
